Workbook

Sheet Calendário 2026
A1: Carimbo de data/hora | B1: Município | C1: Faz parte de uma Região Turística? | D1: Nome do evento | E1: Descrição do evento (breve descrição) | F1: Lei estadual (se aplicada) | G1: Endereço do evento | H1: Site do Evento (se possuir) | I1: Mês de Realização do evento | J1: Data inicial do evento (data prevista) | K1: Data final do evento (data prevista) | L1: Horário do evento - Início (Horário previsto. Caso não tenha, deixar em branco) | M1: Horário do evento - Fim (Horário previsto. Caso não tenha, deixar em branco) | N1: Tipo de evento (consultar manual: clique aqui) | O1: Categoria (consultar manual: clique aqui) | P1: Faz parte das categorias abaixo? | Q1: O evento é ligado à | R1: Tipo de público | S1: Público esperado (somente números) | T1: Público da edição de 2025 (somente números) | U1: Público da edição de 2024 (somente números) | V1: Público da edição de 2023 (somente números) | W1: Órgão ou empresa organizadora | X1: Site para compra do ingresso (se possuir) | Y1: Contato para mais informações (email) | Z1: Acessibilidade Informe para qual deficiência o seu evento esta preparado para receber: | AA1: Acessibilidade O que o evento possui: | AB1: Acessibilidade Digital Acessibilidade digital no site do Evento: | AC1: Classificação etária | AD1: Regiões Administrativas | AE1: ID | AF1: CD_GEOCODIGO | AG1: CD_GEOCODMU | AH1: LONG | AI1: LAT | AJ1: ALT | AK1: GM_PONTO_sk
A2: 46002.489 | B2: BARRETOS | C2: Águas Sertanejas | D2: 71ª Festa do Peão de Boiadeiro de Barretos | E2: Realizada anualmente em Barretos (SP), a Festa do Peão de Barretos é o maior rodeio da América Latina. O evento reúne competições de montaria, apresentações musicais nacionais e internacionais, atividades culturais, gastronomia típica e eventos voltados à tradição sertaneja e ao agronegócio. | G2: Parque do Peão - Rodovia Brigadeiro Faria Lima, km 428 – Barretos/SP – CEP 14783-000 | H2: https://www.independentes.com.br/festadopeao/inicio | I2: Agosto | J2: 45889 | K2: 45899 | N2: Festa | O2: Artístico/Cultural/Folclórico | P2: Rodeio | Q2: Nehuma das opções acima | R2: Nacional | S2: 900000 | T2: 900000 | U2: 900000 | V2: 900000 | W2: Os Independentes | X2: www.barretos.totalacesso.com/ | Y2: turismo@independentes.com.br | Z2: Deficiência Fisica, Deficiência Visual, Deficiência Auditiva | AA2: Atendimento em Línguas de Sinais, Piso Tátil, Rampa, Braille, Banheiro Acessível, Portas Largas para PCR (Pessoa com cadeira de rodas) | AB2: Intérprete de Libras no site do evento | AC2: Indicado para maiores de 18 anos | AD2: =IFERROR(VLOOKUP(B2,'Regiões Administrativas'!$A$1:$B$646,2,0),"") -> Barretos | AE2: =IFERROR(VLOOKUP(Form_Responses[[#This Row],[Município]],'Regiões Administrativas'!$A$1:$I$646,3,0),"") -> 15545 | AF2: =IFERROR(VLOOKUP(Form_Responses[[#This Row],[Município]],'Regiões Administrativas'!$A$1:$I$646,4,0),"") -> 350550005000001 | AG2: =IFERROR(VLOOKUP(Form_Responses[[#This Row],[Município]],'Regiões Administrativas'!$A$1:$I$646,4,0),"") -> 350550005000001 | AH2: =IFERROR(VLOOKUP(B2,'Regiões Administrativas'!$A$1:$I$646,5,0),"") -> 3505500 | AI2: =IFERROR(VLOOKUP(B2,'Regiões Administrativas'!$A$1:$I$646,6,0),"") -> -48.567378 | AJ2: =IFERROR(VLOOKUP(B2,'Regiões Administrativas'!$A$1:$I$646,8,0),"") -> 537.6636 | AK2: =IFERROR(VLOOKUP(Form_Responses[[#This Row],[Município]],'Regiões Administrativas'!$A$1:$I$646,9,0),"") -> 1J6RD.n:?3O>
A3: 46002.559 | B3: BOITUVA | C3: Raízes do Interior Paulista | D3: Campeonato Brasileiro de Balonismo | E3: Campeonato Brasileiro de Balonismo | G3: Rua Benedito Rodrigues de Melo, s/n, no bairro Portal Ville Primavera/Azaleia | I3: Junho | N3: Campeonato/Torneio/Concurso | O3: Esportivo | P3: Nenhuma das opções acima | Q3: Nehuma das opções acima | R3: Nacional | S3: 45000 | T3: 40000 | U3: 37000 | V3: 30000 | W3: Prefeitura e Confederação Brasileira de Balonismo | Y3: felipealvim50@gmail.com | Z3: Não possui | AA3: Banheiro Acessível | AB3: Não possui | AC3: Livre | AD3: =IFERROR(VLOOKUP(B3,'Regiões Administrativas'!$A$1:$B$646,2,0),"") -> Sorocaba | AE3: =IFERROR(VLOOKUP(Form_Responses[[#This Row],[Município]],'Regiões Administrativas'!$A$1:$I$646,3,0),"") -> 15591 | AF3: =IFERROR(VLOOKUP(Form_Responses[[#This Row],[Município]],'Regiões Administrativas'!$A$1:$I$646,4,0),"") -> 350700105000001 | AG3: =IFERROR(VLOOKUP(Form_Responses[[#This Row],[Município]],'Regiões Administrativas'!$A$1:$I$646,4,0),"") -> 350700105000001 | AH3: =IFERROR(VLOOKUP(B3,'Regiões Administrativas'!$A$1:$I$646,5,0),"") -> 3507001 | AI3: =IFERROR(VLOOKUP(B3,'Regiões Administrativas'!$A$1:$I$646,6,0),"") -> -47.671473 | AJ3: =IFERROR(VLOOKUP(B3,'Regiões Administrativas'!$A$1:$I$646,8,0),"") -> 643.45961 | AK3: =IFERROR(VLOOKUP(Form_Responses[[#This Row],[Município]],'Regiões Administrativas'!$A$1:$I$646,9,0),"") -> 1J6tlW*483;>
A4: 46002.561 | B4: BOITUVA | C4: Raízes do Interior Paulista | D4: 19° Festival de Inverno | E4: Festival de Inverno | G4: Av. Pereira Ignacio, 101 - Res Primo, Boituva | I4: Julho | N4: Festival | O4: Artístico/Cultural/Folclórico | P4: Nenhuma das opções acima | Q4: Nehuma das opções acima | R4: Regional | S4: 30000 | T4: 27000 | U4: 23000 | V4: 20000 | W4: Prefeitura de Boituva | Y4: felipealvim50@gmail.com | Z4: Deficiência Fisica | AA4: Rampa, Elevador, Banheiro Acessível | AB4: Intérprete de Libras no site do evento | AC4: Livre | AD4: =IFERROR(VLOOKUP(B4,'Regiões Administrativas'!$A$1:$B$646,2,0),"") -> Sorocaba | AE4: =IFERROR(VLOOKUP(Form_Responses[[#This Row],[Município]],'Regiões Administrativas'!$A$1:$I$646,3,0),"") -> 15591 | AF4: =IFERROR(VLOOKUP(Form_Responses[[#This Row],[Município]],'Regiões Administrativas'!$A$1:$I$646,4,0),"") -> 350700105000001 | AG4: =IFERROR(VLOOKUP(Form_Responses[[#This Row],[Município]],'Regiões Administrativas'!$A$1:$I$646,4,0),"") -> 350700105000001 | AH4: =IFERROR(VLOOKUP(B4,'Regiões Administrativas'!$A$1:$I$646,5,0),"") -> 3507001 | AI4: =IFERROR(VLOOKUP(B4,'Regiões Administrativas'!$A$1:$I$646,6,0),"") -> -47.671473 | AJ4: =IFERROR(VLOOKUP(B4,'Regiões Administrativas'!$A$1:$I$646,8,0),"") -> 643.45961 | AK4: =IFERROR(VLOOKUP(Form_Responses[[#This Row],[Município]],'Regiões Administrativas'!$A$1:$I$646,9,0),"") -> 1J6tlW*483;>
A5: 46002.563 | B5: BOITUVA | C5: Raízes do Interior Paulista | D5: Boituvana 2026 | E5: Festival de Rodeiro | G5: Rua Benedito Mazuquim | I5: Setembro | N5: Festa | O5: Artístico/Cultural/Folclórico | P5: Rodeio | Q5: Nehuma das opções acima | R5: Regional | S5: 45000 | T5: 39000 | U5: 35000 | V5: 30000 | W5: Prefeitura de Boituva | Y5: felipealvim50@gmail.com | Z5: Não possui | AA5: Não possui | AB5: Não possui | AC5: Indicado para maiores de 14 anos | AD5: =IFERROR(VLOOKUP(B5,'Regiões Administrativas'!$A$1:$B$646,2,0),"") -> Sorocaba | AE5: =IFERROR(VLOOKUP(Form_Responses[[#This Row],[Município]],'Regiões Administrativas'!$A$1:$I$646,3,0),"") -> 15591 | AF5: =IFERROR(VLOOKUP(Form_Responses[[#This Row],[Município]],'Regiões Administrativas'!$A$1:$I$646,4,0),"") -> 350700105000001 | AG5: =IFERROR(VLOOKUP(Form_Responses[[#This Row],[Município]],'Regiões Administrativas'!$A$1:$I$646,4,0),"") -> 350700105000001 | AH5: =IFERROR(VLOOKUP(B5,'Regiões Administrativas'!$A$1:$I$646,5,0),"") -> 3507001 | AI5: =IFERROR(VLOOKUP(B5,'Regiões Administrativas'!$A$1:$I$646,6,0),"") -> -47.671473 | AJ5: =IFERROR(VLOOKUP(B5,'Regiões Administrativas'!$A$1:$I$646,8,0),"") -> 643.45961 | AK5: =IFERROR(VLOOKUP(Form_Responses[[#This Row],[Município]],'Regiões Administrativas'!$A$1:$I$646,9,0),"") -> 1J6tlW*483;>
A6: 46002.569 | B6: SÃO JOSÉ DO RIO PARDO | C6: Entre Rios, Serras e Cafés | D6: CARNAVAL 2026 | E6: O Carnaval de São José do Rio Pardo tem se consolidado como um dos maiores e melhores do interior do Estado de São Paulo. No último ano, o evento atraiu cerca de 5 mil pessoas por noite, demonstrando sua crescente relevância regional. A programação ocorre nas noites de sexta, sábado, domingo, segunda e terça-feira, além de matinê no domingo e na terça. Todos os dias contamos com uma atração de destaque nacional e outra de reconhecimento regional, garantindo diversidade, qualidade e grande participação do público. | G6: AVENIDA EUCLIDES DA CUNHA, S/N | I6: Fevereiro | J6: 46066 | K6: 46070 | N6: Festa | O6: Artístico/Cultural/Folclórico | P6: Carnaval | Q6: Nehuma das opções acima | R6: Nacional | S6: 25000 | T6: 20000 | U6: 15000 | V6: 15000 | W6: PREFEITURA MUNICIPAL | Y6: secturismocultura@saojosedoriopardo.sp.gov.br | Z6: Deficiência Fisica | AA6: Rampa, Banheiro Acessível, Portas Largas para PCR (Pessoa com cadeira de rodas) | AB6: Não possui | AC6: Indicado para maiores de 16 anos | AD6: =IFERROR(VLOOKUP(B6,'Regiões Administrativas'!$A$1:$B$646,2,0),"") -> Campinas | AE6: =IFERROR(VLOOKUP(Form_Responses[[#This Row],[Município]],'Regiões Administrativas'!$A$1:$I$646,3,0),"") -> 17171 | AF6: =IFERROR(VLOOKUP(Form_Responses[[#This Row],[Município]],'Regiões Administrativas'!$A$1:$I$646,4,0),"") -> 354970605000001 | AG6: =IFERROR(VLOOKUP(Form_Responses[[#This Row],[Município]],'Regiões Administrativas'!$A$1:$I$646,4,0),"") -> 354970605000001 | AH6: =IFERROR(VLOOKUP(B6,'Regiões Administrativas'!$A$1:$I$646,5,0),"") -> 3549706 | AI6: =IFERROR(VLOOKUP(B6,'Regiões Administrativas'!$A$1:$I$646,6,0),"") -> -46.888266 | AJ6: =IFERROR(VLOOKUP(B6,'Regiões Administrativas'!$A$1:$I$646,8,0),"") -> 718.57108 | AK6: =IFERROR(VLOOKUP(Form_Responses[[#This Row],[Município]],'Regiões Administrativas'!$A$1:$I$646,9,0),"") -> 1J6t_zRG<GU-
A7: 46002.58 | B7: SÃO JOSÉ DO RIO PARDO | C7: Entre Rios, Serras e Cafés | D7: SEMANA EUCLIDIANA | E7: A Semana Euclidiana é um evento cultural anual e o mais antigo do Brasil, realizado em São José do Rio Pardo (SP) entre 9 e 15 de agosto, para celebrar a vida e obra do escritor Euclides da Cunha, autor de Os Sertões, conectando sua memória à identidade local através de palestras, estudos, oficinas e atividades cívicas que envolvem a comunidade e pesquisadores. | G7: ACONTECE EM DIVERSOS LOCAIS DO MUNICIPIO DE ACORDO COM A PROGRAMAÇÃO | I7: Agosto | J7: 46243 | K7: 46249 | N7: Movimento | O7: Social/Cívico/Histórico | P7: Social/Cívico/Histórico | Q7: Nehuma das opções acima | R7: Nacional | S7: 15000 | T7: 15000 | U7: 13000 | V7: 11000 | W7: PREFEITURA MUNICIPAL DE SÃO JOSE DO RIO PARDO | Y7: secturismocultura@saojosedoriopardo.sp.gov.br | Z7: Deficiência Fisica, Deficiência Visual, Deficiência Auditiva | AA7: Atendimento em Línguas de Sinais, Rampa, Elevador, Banheiro Acessível, Portas Largas para PCR (Pessoa com cadeira de rodas) | AB7: Não possui | AC7: Livre | AD7: =IFERROR(VLOOKUP(B7,'Regiões Administrativas'!$A$1:$B$646,2,0),"") -> Campinas | AE7: =IFERROR(VLOOKUP(Form_Responses[[#This Row],[Município]],'Regiões Administrativas'!$A$1:$I$646,3,0),"") -> 17171 | AF7: =IFERROR(VLOOKUP(Form_Responses[[#This Row],[Município]],'Regiões Administrativas'!$A$1:$I$646,4,0),"") -> 354970605000001 | AG7: =IFERROR(VLOOKUP(Form_Responses[[#This Row],[Município]],'Regiões Administrativas'!$A$1:$I$646,4,0),"") -> 354970605000001 | AH7: =IFERROR(VLOOKUP(B7,'Regiões Administrativas'!$A$1:$I$646,5,0),"") -> 3549706 | AI7: =IFERROR(VLOOKUP(B7,'Regiões Administrativas'!$A$1:$I$646,6,0),"") -> -46.888266 | AJ7: =IFERROR(VLOOKUP(B7,'Regiões Administrativas'!$A$1:$I$646,8,0),"") -> 718.57108 | AK7: =IFERROR(VLOOKUP(Form_Responses[[#This Row],[Município]],'Regiões Administrativas'!$A$1:$I$646,9,0),"") -> 1J6t_zRG<GU-
A8: 46002.617 | B8: SANTA SALETE | C8: Entre Rios | D8: FESTIVIDADES DE ANIVERSÁRIO DO MUNICIPIO | E8: FESTIVIDADE ANIVERSÁRIO DO MUNICIPIO COM DESFILI CIVICO, ATRAÇÕES CULTURAIS, SHOW SERTANEJOS, EVENTOS ESPORTIVOS, CAVALGADA. | F8: NÃO | G8: AVENIDA XV DE NOVEMBRO CENTRO | H8: www.prefeituramunicipaldesantasalete.sp.gov.br | I8: Março | J8: 46103 | K8: 46110 | N8: Aniversário | O8: Social/Cívico/Histórico | P8: Social/Cívico/Histórico | Q8: Nehuma das opções acima | R8: Regional | S8: 4000 | T8: 3000 | U8: 2500 | V8: 1500 | W8: secretaria de cultura do município | Y8: esporte@santasalete.sp.gov.br | Z8: Deficiência Fisica | AA8: Rampa, Banheiro Acessível | AB8: Não possui | AC8: Livre | AD8: =IFERROR(VLOOKUP(B8,'Regiões Administrativas'!$A$1:$B$646,2,0),"") -> São José do Rio Preto | AE8: =IFERROR(VLOOKUP(Form_Responses[[#This Row],[Município]],'Regiões Administrativas'!$A$1:$I$646,3,0),"") -> 17107 | AF8: =IFERROR(VLOOKUP(Form_Responses[[#This Row],[Município]],'Regiões Administrativas'!$A$1:$I$646,4,0),"") -> 354765005000001 | AG8: =IFERROR(VLOOKUP(Form_Responses[[#This Row],[Município]],'Regiões Administrativas'!$A$1:$I$646,4,0),"") -> 354765005000001 | AH8: =IFERROR(VLOOKUP(B8,'Regiões Administrativas'!$A$1:$I$646,5,0),"") -> 3547650 | AI8: =IFERROR(VLOOKUP(B8,'Regiões Administrativas'!$A$1:$I$646,6,0),"") -> -50.688462 | AJ8: =IFERROR(VLOOKUP(B8,'Regiões Administrativas'!$A$1:$I$646,8,0),"") -> 443.15183 | AK8: =IFERROR(VLOOKUP(Form_Responses[[#This Row],[Município]],'Regiões Administrativas'!$A$1:$I$646,9,0),"") -> 1J6R@Sgi2B<f
A9: 46002.621 | B9: ITAPORANGA | C9: Angra Paulista | D9: ITAPÔ FOILIA - CARNAVAL DE RUA DE ITAPORANGA | E9: O Itapô Folia é o tradicional carnaval de rua de Itaporanga, realizado de 13 a 15 de fevereiro na Praça João Abdallah, com entrada totalmente gratuita. O evento reúne famílias e visitantes de diversas cidades, oferecendo um ambiente acolhedor, alegre e repleto de cores e fantasias. A programação conta com bandas show típicas de carnaval, garantindo animação durante todas as noites. O espaço possui praça de alimentação completa, estrutura de banheiros e um sistema de segurança especializada, com monitoramento por câmeras em 100% da área do evento. Marcado pela organização e pelo clima familiar, o Itapô Folia se consolidou como um dos eventos mais aguardados da região, celebrando a cultura e a diversão de forma segura e acessível a todos. | F9: NÃO POSSUI | G9: PRAÇA JOÃO ABDALLAH | H9: SOMENTE PAGINAS OFICIAIS DA PREFEITURA MUNICIPAL | I9: Fevereiro | J9: 46066 | K9: 46068 | L9: 0.83333333 | M9: 0.083333333 | N9: Festa | O9: Artístico/Cultural/Folclórico | P9: Carnaval | Q9: Nehuma das opções acima | R9: Regional | S9: 10000 | T9: 9000 | U9: 8000 | V9: 6500 | W9: PREFEITURA MUNICIPAAL | X9: ENTRADA FRANCA | Y9: 15 3565 1397 | Z9: Deficiência Fisica | AA9: Rampa, Banheiro Acessível | AB9: Não possui | AC9: Livre | AD9: =IFERROR(VLOOKUP(B9,'Regiões Administrativas'!$A$1:$B$646,2,0),"") -> Itapeva | AE9: =IFERROR(VLOOKUP(Form_Responses[[#This Row],[Município]],'Regiões Administrativas'!$A$1:$I$646,3,0),"") -> 16121 | AF9: =IFERROR(VLOOKUP(Form_Responses[[#This Row],[Município]],'Regiões Administrativas'!$A$1:$I$646,4,0),"") -> 352280205000001 | AG9: =IFERROR(VLOOKUP(Form_Responses[[#This Row],[Município]],'Regiões Administrativas'!$A$1:$I$646,4,0),"") -> 352280205000001 | AH9: =IFERROR(VLOOKUP(B9,'Regiões Administrativas'!$A$1:$I$646,5,0),"") -> 3522802 | AI9: =IFERROR(VLOOKUP(B9,'Regiões Administrativas'!$A$1:$I$646,6,0),"") -> -49.484396 | AJ9: =IFERROR(VLOOKUP(B9,'Regiões Administrativas'!$A$1:$I$646,8,0),"") -> 545.30365 | AK9: =IFERROR(VLOOKUP(Form_Responses[[#This Row],[Município]],'Regiões Administrativas'!$A$1:$I$646,9,0),"") -> 1J6RXcH1e3dp
A10: 46002.628 | B10: ITAPORANGA | C10: Angra Paulista | D10: FESTIVIDADES INDIGENAS ALDEIA TEKOÁ PORÃ | E10: As Festividades Indígenas Tekoá Porã fazem parte do Mês dos Povos Indígenas e serão realizadas de 27 de abril a 1º de maio de 2026, na Aldeia Tekoá Porã, em Itaporanga/SP. O evento tem caráter cultural e educativo, oferecendo ao público uma imersão na tradição e no modo de vida indígena. Durante os dias de programação, a comunidade abre suas portas gratuitamente para visitas monitoradas pelos Guias Culturais da Aldeia. O evento recebe turistas, grupos escolares e visitantes de diversos municípios, somando milhares de pessoas ao longo das festividades. As atividades incluem cantos e danças tradicionais, rodas de conversa sobre cultura e costumes, visita à Oca Sagrada, Museu, Escola, trilhas e espaços comunitários. Na Arena Indígena, os participantes vivenciam esportes tradicionais como Uca-Uca, corrida de tora, cabo de guerra com cipó, arco e flecha e zarabatana. Há ainda exposição de artesanato e culinária típica. Reconhecido pela organização e pelo grande fluxo de visitantes, o evento reforça a valorização da cultura indígena e a importância do turismo cultural no município. | F10: não possui | G10: BAIRRO PRAINHA - ALDEIA TEKOÁ PORÃ | H10: NÃO POSSUI | I10: Abril | J10: 46139 | K10: 46143 | L10: 0.33333333 | M10: 0.75 | N10: Festa | O10: Artístico/Cultural/Folclórico | P10: Nenhuma das opções acima | Q10: Nehuma das opções acima | R10: Nacional | S10: 6000 | T10: 5500 | U10: 4800 | V10: 4000 | W10: ALDEIA TEKOÁ PORÃ | X10: NÃO POSSUI | Y10: 15 3565 1397 | Z10: Deficiência Fisica | AA10: Não possui | AB10: Não possui | AC10: Livre | AD10: =IFERROR(VLOOKUP(B10,'Regiões Administrativas'!$A$1:$B$646,2,0),"") -> Itapeva | AE10: =IFERROR(VLOOKUP(Form_Responses[[#This Row],[Município]],'Regiões Administrativas'!$A$1:$I$646,3,0),"") -> 16121 | AF10: =IFERROR(VLOOKUP(Form_Responses[[#This Row],[Município]],'Regiões Administrativas'!$A$1:$I$646,4,0),"") -> 352280205000001 | AG10: =IFERROR(VLOOKUP(Form_Responses[[#This Row],[Município]],'Regiões Administrativas'!$A$1:$I$646,4,0),"") -> 352280205000001 | AH10: =IFERROR(VLOOKUP(B10,'Regiões Administrativas'!$A$1:$I$646,5,0),"") -> 3522802 | AI10: =IFERROR(VLOOKUP(B10,'Regiões Administrativas'!$A$1:$I$646,6,0),"") -> -49.484396 | AJ10: =IFERROR(VLOOKUP(B10,'Regiões Administrativas'!$A$1:$I$646,8,0),"") -> 545.30365 | AK10: =IFERROR(VLOOKUP(Form_Responses[[#This Row],[Município]],'Regiões Administrativas'!$A$1:$I$646,9,0),"") -> 1J6RXcH1e3dp
A11: 46002.64 | B11: SANTA SALETE | C11: Entre Rios | D11: FESTA JUNINA - SÃO PEDRO | E11: FESTA JUNINA DE LONGA TRADIÇÃO - ONDE ENVOLVE TODA COMUNIDADE NA PREPARAÇÃO. COM DANÇA TIPICAS DO PERIODO JUNINO, TERÇO A SÃO PEDRO, E MUITA COMIDA, AMENDOIM, PIPOCA, QUENTÃO ACHOCOLATADO, DOCES TIPICOS. TUDO DE GRAÇA PARA POPULAÇÃO E O TURISTA | G11: PRAÇA DA IGREJA MATRIZ RUA OSVALDO CRUZ - CENTRO | I11: Junho | J11: 46201 | K11: 46202 | L11: 0.79166667 | M11: 0.083333333 | N11: Festa | O11: Artístico/Cultural/Folclórico | P11: Festa Junina | Q11: Nehuma das opções acima | R11: Regional | S11: 3000 | T11: 2000 | U11: 1500 | V11: 1500 | W11: PREFEITURA MUNICIPAL DE SANTA SALETE | Y11: esporte@santasalete.sp.gov.br | Z11: Deficiência Fisica | AA11: Rampa, Banheiro Acessível | AB11: Não possui | AC11: Livre | AD11: =IFERROR(VLOOKUP(B11,'Regiões Administrativas'!$A$1:$B$646,2,0),"") -> São José do Rio Preto | AE11: =IFERROR(VLOOKUP(Form_Responses[[#This Row],[Município]],'Regiões Administrativas'!$A$1:$I$646,3,0),"") -> 17107 | AF11: =IFERROR(VLOOKUP(Form_Responses[[#This Row],[Município]],'Regiões Administrativas'!$A$1:$I$646,4,0),"") -> 354765005000001 | AG11: =IFERROR(VLOOKUP(Form_Responses[[#This Row],[Município]],'Regiões Administrativas'!$A$1:$I$646,4,0),"") -> 354765005000001 | AH11: =IFERROR(VLOOKUP(B11,'Regiões Administrativas'!$A$1:$I$646,5,0),"") -> 3547650 | AI11: =IFERROR(VLOOKUP(B11,'Regiões Administrativas'!$A$1:$I$646,6,0),"") -> -50.688462 | AJ11: =IFERROR(VLOOKUP(B11,'Regiões Administrativas'!$A$1:$I$646,8,0),"") -> 443.15183 | AK11: =IFERROR(VLOOKUP(Form_Responses[[#This Row],[Município]],'Regiões Administrativas'!$A$1:$I$646,9,0),"") -> 1J6R@Sgi2B<f
A12: 46002.657 | B12: AREIAS | C12: Vale Histórico | D12: Micareias | E12: Carnaval antecipado. Acontece há mais de 30 anos um fim de semana antes do carnaval oficial. Atrai folioes de SP, RJ e Sul de Minas. | G12: Praça 09 de Julho | I12: Fevereiro | J12: 46059 | K12: 46060 | L12: 0.83333333 | M12: 0.125 | N12: Festa | O12: Comercial/Promocional | P12: Carnaval | Q12: Nehuma das opções acima | R12: Regional | S12: 5000 | U12: 4500 | V12: 6000 | W12: Prefeitura Municipal de Areias | Y12: areiastur@gmail.com | Z12: Não possui | AA12: Não possui | AB12: Não possui | AC12: Livre | AD12: =IFERROR(VLOOKUP(B12,'Regiões Administrativas'!$A$1:$B$646,2,0),"") -> São José dos Campos | AE12: =IFERROR(VLOOKUP(Form_Responses[[#This Row],[Município]],'Regiões Administrativas'!$A$1:$I$646,3,0),"") -> 15465 | AF12: =IFERROR(VLOOKUP(Form_Responses[[#This Row],[Município]],'Regiões Administrativas'!$A$1:$I$646,4,0),"") -> 350350505000001 | AG12: =IFERROR(VLOOKUP(Form_Responses[[#This Row],[Município]],'Regiões Administrativas'!$A$1:$I$646,4,0),"") -> 350350505000001 | AH12: =IFERROR(VLOOKUP(B12,'Regiões Administrativas'!$A$1:$I$646,5,0),"") -> 3503505 | AI12: =IFERROR(VLOOKUP(B12,'Regiões Administrativas'!$A$1:$I$646,6,0),"") -> -44.699432 | AJ12: =IFERROR(VLOOKUP(B12,'Regiões Administrativas'!$A$1:$I$646,8,0),"") -> 534.09202 | AK12: =IFERROR(VLOOKUP(Form_Responses[[#This Row],[Município]],'Regiões Administrativas'!$A$1:$I$646,9,0),"") -> 1J6tSQUiW^Gf
A13: 46002.664 | B13: AREIAS | C13: Vale Histórico | D13: Carnaval Bloco a Bloco | E13: O Carnaval reuni vários blocos do município, que vendem seus abadas, atraem turistas da região em um programação vespertina e noturna. Utilizam de trio elétrico para desfile do bloco e seguem para a praça de eventos onde acontece a apresentação de bandas de carnaval. | G13: Praça Senhor Bom Jesus | I13: Fevereiro | J13: 46067 | K13: 46071 | L13: 0.83333333 | M13: 0.125 | N13: Festa | O13: Artístico/Cultural/Folclórico | P13: Carnaval | Q13: Nehuma das opções acima | R13: Regional | S13: 3000 | T13: 3000 | U13: 4000 | V13: 4000 | W13: Prefeitura Municipal de Areias | Y13: areiastur@gmail.com | Z13: Não possui | AA13: Não possui | AB13: Não possui | AC13: Livre | AD13: =IFERROR(VLOOKUP(B13,'Regiões Administrativas'!$A$1:$B$646,2,0),"") -> São José dos Campos | AE13: =IFERROR(VLOOKUP(Form_Responses[[#This Row],[Município]],'Regiões Administrativas'!$A$1:$I$646,3,0),"") -> 15465 | AF13: =IFERROR(VLOOKUP(Form_Responses[[#This Row],[Município]],'Regiões Administrativas'!$A$1:$I$646,4,0),"") -> 350350505000001 | AG13: =IFERROR(VLOOKUP(Form_Responses[[#This Row],[Município]],'Regiões Administrativas'!$A$1:$I$646,4,0),"") -> 350350505000001 | AH13: =IFERROR(VLOOKUP(B13,'Regiões Administrativas'!$A$1:$I$646,5,0),"") -> 3503505 | AI13: =IFERROR(VLOOKUP(B13,'Regiões Administrativas'!$A$1:$I$646,6,0),"") -> -44.699432 | AJ13: =IFERROR(VLOOKUP(B13,'Regiões Administrativas'!$A$1:$I$646,8,0),"") -> 534.09202 | AK13: =IFERROR(VLOOKUP(Form_Responses[[#This Row],[Município]],'Regiões Administrativas'!$A$1:$I$646,9,0),"") -> 1J6tSQUiW^Gf
A14: 46002.665 | B14: CABREÚVA | C14: Roteiro dos Bandeirantes | D14: Carnabreúva | E14: Este evento, geralmente é composto por cinco dias de festa começando na sexta-feira que antecede o feriado de carnaval e finalizando na terça feira. No evento estão incluídas cinco noites de festa, duas matinês com a tradicional Banda São Roque tocando marchinhas. | G14: Praça Comendador Martins, Centro - Cabreúva/SP | H14: www.cabreuva.sp.gov.br | I14: Fevereiro | J14: 45701 | K14: 45705 | L14: 0.58333333 | M14: 0 | N14: Festa | O14: Artístico/Cultural/Folclórico | P14: Carnaval | Q14: Nehuma das opções acima | R14: Regional | S14: 24000 | T14: 24000 | U14: 22000 | V14: 20000 | W14: Secretaria Municipal de Cultura, Turismo e Patrimônio Histórico de Cabreúva | Y14: sec.cultura@cabreuva.sp.gov.br | Z14: Deficiência Fisica | AA14: Piso Tátil, Rampa, Banheiro Acessível | AB14: Não possui | AC14: Livre | AD14: =IFERROR(VLOOKUP(B14,'Regiões Administrativas'!$A$1:$B$646,2,0),"") -> Campinas | AE14: =IFERROR(VLOOKUP(Form_Responses[[#This Row],[Município]],'Regiões Administrativas'!$A$1:$I$646,3,0),"") -> 15658 | AF14: =IFERROR(VLOOKUP(Form_Responses[[#This Row],[Município]],'Regiões Administrativas'!$A$1:$I$646,4,0),"") -> 350840505000001 | AG14: =IFERROR(VLOOKUP(Form_Responses[[#This Row],[Município]],'Regiões Administrativas'!$A$1:$I$646,4,0),"") -> 350840505000001 | AH14: =IFERROR(VLOOKUP(B14,'Regiões Administrativas'!$A$1:$I$646,5,0),"") -> 3508405 | AI14: =IFERROR(VLOOKUP(B14,'Regiões Administrativas'!$A$1:$I$646,6,0),"") -> -47.133658 | AJ14: =IFERROR(VLOOKUP(B14,'Regiões Administrativas'!$A$1:$I$646,8,0),"") -> 656.6031 | AK14: =IFERROR(VLOOKUP(Form_Responses[[#This Row],[Município]],'Regiões Administrativas'!$A$1:$I$646,9,0),"") -> 1J6tLv=^]h4>
A15: 46002.667 | B15: CABREÚVA | C15: Roteiro dos Bandeirantes | D15: Festival de Inverno de Cabreúva | E15: Evento que atrai um público entre 20 e 30 mil pessoas, é a maior festa realizada na cidade. As atrações musicais são grandes nomes do Rock nacional e a gastronomia fica por conta dos estabelecimentos do município, visando assim o incentivo ao comércio local. O evento geralmente ocorre em um final de semana. | G15: Praça Comendador Martins, Centro - Cabreúva/SP | H15: www.cabreuva.sp.gov.br | I15: Julho | J15: 46214 | K15: 46215 | L15: 0.45833333 | M15: 0 | N15: Festival | O15: Artístico/Cultural/Folclórico | P15: Nenhuma das opções acima | Q15: Nehuma das opções acima | R15: Nacional | S15: 30000 | T15: 28000 | U15: 30000 | V15: 26000 | W15: Secretaria Municipal de Cultura, Turismo e Patrimônio Histórico de Cabreúva | Y15: sec.cultura@cabreuva.sp.gov.br | Z15: Deficiência Fisica, Deficiência Visual, Não possui | AA15: Piso Tátil, Rampa, Banheiro Acessível | AB15: Não possui | AC15: Livre | AD15: =IFERROR(VLOOKUP(B15,'Regiões Administrativas'!$A$1:$B$646,2,0),"") -> Campinas | AE15: =IFERROR(VLOOKUP(Form_Responses[[#This Row],[Município]],'Regiões Administrativas'!$A$1:$I$646,3,0),"") -> 15658 | AF15: =IFERROR(VLOOKUP(Form_Responses[[#This Row],[Município]],'Regiões Administrativas'!$A$1:$I$646,4,0),"") -> 350840505000001 | AG15: =IFERROR(VLOOKUP(Form_Responses[[#This Row],[Município]],'Regiões Administrativas'!$A$1:$I$646,4,0),"") -> 350840505000001 | AH15: =IFERROR(VLOOKUP(B15,'Regiões Administrativas'!$A$1:$I$646,5,0),"") -> 3508405 | AI15: =IFERROR(VLOOKUP(B15,'Regiões Administrativas'!$A$1:$I$646,6,0),"") -> -47.133658 | AJ15: =IFERROR(VLOOKUP(B15,'Regiões Administrativas'!$A$1:$I$646,8,0),"") -> 656.6031 | AK15: =IFERROR(VLOOKUP(Form_Responses[[#This Row],[Município]],'Regiões Administrativas'!$A$1:$I$646,9,0),"") -> 1J6tLv=^]h4>
A16: 46002.669 | B16: AREIAS | C16: Vale Histórico | D16: Festival de Bandas e Fanfarras de Areias | E16: Reune varias bandas e fanfarras da região, onde cada uma tem um tempo estimado para apresentação. Em 2026 será a 6 edição. Esse evento tem como anfitriã a Banda Marcial Municipal de Areias, que leva o titulo de Tri campeã Sul-americana de Bandas e Fanfarras de Itapema SC. A Banda faz parte do projeto musica nas escolas. | G16: Praça Senhor Bom Jesus | I16: Dezembro | J16: 46369 | K16: 46369 | L16: 0.45833333 | M16: 0.83333333 | N16: Festival | O16: Artístico/Cultural/Folclórico | P16: Nenhuma das opções acima | Q16: Nehuma das opções acima | R16: Regional | S16: 2000 | T16: 2000 | U16: 0000 | V16: 2000 | W16: Prefeitura Municipal de Areias | X16: gratuito | Y16: areiastur@gmail.com | Z16: Não possui | AA16: Não possui | AB16: Não possui | AC16: Livre | AD16: =IFERROR(VLOOKUP(B16,'Regiões Administrativas'!$A$1:$B$646,2,0),"") -> São José dos Campos | AE16: =IFERROR(VLOOKUP(Form_Responses[[#This Row],[Município]],'Regiões Administrativas'!$A$1:$I$646,3,0),"") -> 15465 | AF16: =IFERROR(VLOOKUP(Form_Responses[[#This Row],[Município]],'Regiões Administrativas'!$A$1:$I$646,4,0),"") -> 350350505000001 | AG16: =IFERROR(VLOOKUP(Form_Responses[[#This Row],[Município]],'Regiões Administrativas'!$A$1:$I$646,4,0),"") -> 350350505000001 | AH16: =IFERROR(VLOOKUP(B16,'Regiões Administrativas'!$A$1:$I$646,5,0),"") -> 3503505 | AI16: =IFERROR(VLOOKUP(B16,'Regiões Administrativas'!$A$1:$I$646,6,0),"") -> -44.699432 | AJ16: =IFERROR(VLOOKUP(B16,'Regiões Administrativas'!$A$1:$I$646,8,0),"") -> 534.09202 | AK16: =IFERROR(VLOOKUP(Form_Responses[[#This Row],[Município]],'Regiões Administrativas'!$A$1:$I$646,9,0),"") -> 1J6tSQUiW^Gf
A17: 46002.674 | B17: IGARATÁ | C17: Entre Serras e Águas | D17: IGT23K + Feira Gastronômica | E17: A IGT23K (Igaratá 23k) é amplamente conhecida como a maior corrida de montanha do Brasil, realizada anualmente em Igaratá/SP, e em sua ultima edição recebeu mais de 3 mil atletas, além do publico que vem acompanhar a corrida. Na na mesma data o COMTUR promove evento gastronômico para atender população e visitantes com diversidade gastronômica e shows na Praça de Eventos. | F17: Não | G17: Largada : Praça Luiz Carlos Lourenço | H17: zbrevents.com.br | I17: Março | J17: 46103 | K17: 46104 | L17: 0.33333333 | N17: Campeonato/Torneio/Concurso | O17: Esportivo | P17: Nenhuma das opções acima | Q17: Nehuma das opções acima | R17: Nacional | S17: 6000 | T17: 5500 | U17: 4600 | V17: 6000 | W17: ZBR com apoio COMTUR e Município Igaratá | X17: zbrevents.com.br | Y17: turismo@igarata.sp.gov.br | Z17: Não possui | AA17: Não possui | AB17: Não possui | AC17: Indicado para maiores de 18 anos | AD17: =IFERROR(VLOOKUP(B17,'Regiões Administrativas'!$A$1:$B$646,2,0),"") -> São José dos Campos | AE17: =IFERROR(VLOOKUP(Form_Responses[[#This Row],[Município]],'Regiões Administrativas'!$A$1:$I$646,3,0),"") -> 16025 | AF17: =IFERROR(VLOOKUP(Form_Responses[[#This Row],[Município]],'Regiões Administrativas'!$A$1:$I$646,4,0),"") -> 352020205000001 | AG17: =IFERROR(VLOOKUP(Form_Responses[[#This Row],[Município]],'Regiões Administrativas'!$A$1:$I$646,4,0),"") -> 352020205000001 | AH17: =IFERROR(VLOOKUP(B17,'Regiões Administrativas'!$A$1:$I$646,5,0),"") -> 3520202 | AI17: =IFERROR(VLOOKUP(B17,'Regiões Administrativas'!$A$1:$I$646,6,0),"") -> -46.156314 | AJ17: =IFERROR(VLOOKUP(B17,'Regiões Administrativas'!$A$1:$I$646,8,0),"") -> 741.81313 | AK17: =IFERROR(VLOOKUP(Form_Responses[[#This Row],[Município]],'Regiões Administrativas'!$A$1:$I$646,9,0),"") -> 1J6tOGPM^=vp
A18: 46002.698 | B18: ITAÓCA | C18: Cavernas da Mata Atlântica | D18: Show da virada | E18: Réveillon, realizado na praça central, atraindo público de diversos municípios vizinhos e de outros estados, com número considerável de visitantes, com shows e diversas atrações para o público | F18: Não se aplica | G18: Rua professor Elias Lages de Magalhães, s/n, centro, Praça José Silva, CEP 18360015 | H18: Não possui | I18: Dezembro | J18: 46019 | K18: 46022 | M18: 0.20833333 | N18: Festa | O18: Social/Cívico/Histórico | P18: Réveillon (Ano Novo) | Q18: Nehuma das opções acima | R18: Nacional | S18: 2500 | T18: 2500 | U18: 1900 | V18: 1500 | W18: Prefeitura Municipal | X18: Não possui | Y18: pmitaoca@gmail.com | Z18: Deficiência Fisica | AA18: Piso Tátil, Rampa, Banheiro Acessível | AB18: Não possui | AC18: Livre | AD18: =IFERROR(VLOOKUP(B18,'Regiões Administrativas'!$A$1:$B$646,2,0),"") -> Itapeva | AE18: =IFERROR(VLOOKUP(Form_Responses[[#This Row],[Município]],'Regiões Administrativas'!$A$1:$I$646,3,0),"") -> 16090 | AF18: =IFERROR(VLOOKUP(Form_Responses[[#This Row],[Município]],'Regiões Administrativas'!$A$1:$I$646,4,0),"") -> 352215805000001 | AG18: =IFERROR(VLOOKUP(Form_Responses[[#This Row],[Município]],'Regiões Administrativas'!$A$1:$I$646,4,0),"") -> 352215805000001 | AH18: =IFERROR(VLOOKUP(B18,'Regiões Administrativas'!$A$1:$I$646,5,0),"") -> 3522158 | AI18: =IFERROR(VLOOKUP(B18,'Regiões Administrativas'!$A$1:$I$646,6,0),"") -> -48.842856 | AJ18: =IFERROR(VLOOKUP(B18,'Regiões Administrativas'!$A$1:$I$646,8,0),"") -> 170.3779 | AK18: =IFERROR(VLOOKUP(Form_Responses[[#This Row],[Município]],'Regiões Administrativas'!$A$1:$I$646,9,0),"") -> 1J6S8237rK;>
A19: 46002.701 | B19: PEDRO DE TOLEDO | C19: Caminhos da Mata Atlântica | D19: CAMPEONATO ANUAL DE CHURRASCO BARBECUE PEDRO DE TOLEDO | E19: Campeonato Brasileiro de Churrasco Barbecue em Pedro de Toledo com Show Musical, O Evento será realizado no nosso Município, com mais de 18 equipes. Projeto de Lei que já faz parte do Calendário anual do Município no Mês de Julho | F19: Projeto de Lei Aprovado Nº 1.601 de 28/02/2020 | G19: Centro de Eventos Comunitários de Pedro de Toledo-SP | I19: Junho | J19: 46193 | K19: 46194 | L19: 0.375 | M19: 0.875 | N19: Campeonato/Torneio/Concurso | O19: Gastronômico | P19: Nenhuma das opções acima | Q19: Nehuma das opções acima | R19: Nacional | S19: 4000 | W19: Prefeitura Municipal de Pedro de Toledo | Y19: turismo@pedrodetoledo.sp.gov.br | Z19: Deficiência Fisica, Deficiência Visual, Deficiência Auditiva | AA19: Banheiro Acessível, Balcão de atendimento com altura reduzida, Portas Largas para PCR (Pessoa com cadeira de rodas), Outro: | AB19: Não possui | AC19: Livre | AD19: =IFERROR(VLOOKUP(B19,'Regiões Administrativas'!$A$1:$B$646,2,0),"") -> Registro | AE19: =IFERROR(VLOOKUP(Form_Responses[[#This Row],[Município]],'Regiões Administrativas'!$A$1:$I$646,3,0),"") -> 16773 | AF19: =IFERROR(VLOOKUP(Form_Responses[[#This Row],[Município]],'Regiões Administrativas'!$A$1:$I$646,4,0),"") -> 353720605000001 | AG19: =IFERROR(VLOOKUP(Form_Responses[[#This Row],[Município]],'Regiões Administrativas'!$A$1:$I$646,4,0),"") -> 353720605000001 | AH19: =IFERROR(VLOOKUP(B19,'Regiões Administrativas'!$A$1:$I$646,5,0),"") -> 3537206 | AI19: =IFERROR(VLOOKUP(B19,'Regiões Administrativas'!$A$1:$I$646,6,0),"") -> -47.229076 | AJ19: =IFERROR(VLOOKUP(B19,'Regiões Administrativas'!$A$1:$I$646,8,0),"") -> 62.710276 | AK19: =IFERROR(VLOOKUP(Form_Responses[[#This Row],[Município]],'Regiões Administrativas'!$A$1:$I$646,9,0),"") -> 1J6U*=,UtcP>
A20: 46002.702 | B20: ITAÓCA | C20: Cavernas da Mata Atlântica | D20: Aniversário da cidade | E20: Festa em comemoração do aniversário da cidade, com shows, apresentações culturais, eventos esportivos e outros | G20: Praça José Silva, rua professor Elias Lages de Magalhães, s/n, centro | I20: Novembro | J20: 45979 | K20: 45983 | N20: Aniversário | O20: Social/Cívico/Histórico | P20: Social/Cívico/Histórico | Q20: Nehuma das opções acima | R20: Nacional | S20: 1500 | T20: 1500 | U20: 1000 | V20: 1000 | W20: Prefeitura Municipal | Y20: pmitaoca@gmail.com | Z20: Deficiência Fisica | AA20: Piso Tátil, Rampa, Banheiro Acessível | AB20: Não possui | AC20: Livre | AD20: =IFERROR(VLOOKUP(B20,'Regiões Administrativas'!$A$1:$B$646,2,0),"") -> Itapeva | AE20: =IFERROR(VLOOKUP(Form_Responses[[#This Row],[Município]],'Regiões Administrativas'!$A$1:$I$646,3,0),"") -> 16090 | AF20: =IFERROR(VLOOKUP(Form_Responses[[#This Row],[Município]],'Regiões Administrativas'!$A$1:$I$646,4,0),"") -> 352215805000001 | AG20: =IFERROR(VLOOKUP(Form_Responses[[#This Row],[Município]],'Regiões Administrativas'!$A$1:$I$646,4,0),"") -> 352215805000001 | AH20: =IFERROR(VLOOKUP(B20,'Regiões Administrativas'!$A$1:$I$646,5,0),"") -> 3522158 | AI20: =IFERROR(VLOOKUP(B20,'Regiões Administrativas'!$A$1:$I$646,6,0),"") -> -48.842856 | AJ20: =IFERROR(VLOOKUP(B20,'Regiões Administrativas'!$A$1:$I$646,8,0),"") -> 170.3779 | AK20: =IFERROR(VLOOKUP(Form_Responses[[#This Row],[Município]],'Regiões Administrativas'!$A$1:$I$646,9,0),"") -> 1J6S8237rK;>
A21: 46003.395 | B21: OLÍMPIA | C21: Águas Sertanejas | D21: Carnaval Olímpia Folia 2026 | E21: Considerado um dos maiores carnavais do noroeste paulista, o evento será realizado no estacionamento do Thermas dos Laranjais e espera receber 80 mil foliões durante quatro noites de shows. A entrada para a pista é gratuita e informações sobre a venda de camarotes serão divulgadas em breve. Além disso, a Praça da Matriz receberá desfile das escolas de samba e matinês. Os distritos de Ribeiro dos Santos e Baguaçu também serão palco de matinês e shows. | F21: DECRETO Nº 9.444, DE 18 DE FEVEREIRO DE 2025 | G21: Estacionamento do Thermas dos Laranjais - Av. do Folclore, 1543, Olímpia-SP | H21: https://www.turismo.olimpia.sp.gov.br/ | I21: Fevereiro | J21: 46066 | K21: 46069 | L21: 0.79166667 | M21: 0.99930556 | N21: Festa | O21: Artístico/Cultural/Folclórico | P21: Carnaval | Q21: Nehuma das opções acima | R21: Nacional | S21: 80000 | T21: 60000 | U21: 40000 | V21: 60000 | W21: Prefeitura Municipal de Olímpia | Y21: prefeitura@olimpia.sp.gov.br | Z21: Deficiência Fisica | AA21: Rampa, Banheiro Acessível, Balcão de atendimento com altura reduzida, Portas Largas para PCR (Pessoa com cadeira de rodas) | AB21: Áudio Descrição no site do evento, Legenda no site do evento | AC21: Livre | AD21: =IFERROR(VLOOKUP(B21,'Regiões Administrativas'!$A$1:$B$646,2,0),"") -> Barretos | AE21: =IFERROR(VLOOKUP(Form_Responses[[#This Row],[Município]],'Regiões Administrativas'!$A$1:$I$646,3,0),"") -> 16671 | AF21: =IFERROR(VLOOKUP(Form_Responses[[#This Row],[Município]],'Regiões Administrativas'!$A$1:$I$646,4,0),"") -> 353390805000001 | AG21: =IFERROR(VLOOKUP(Form_Responses[[#This Row],[Município]],'Regiões Administrativas'!$A$1:$I$646,4,0),"") -> 353390805000001 | AH21: =IFERROR(VLOOKUP(B21,'Regiões Administrativas'!$A$1:$I$646,5,0),"") -> 3533908 | AI21: =IFERROR(VLOOKUP(B21,'Regiões Administrativas'!$A$1:$I$646,6,0),"") -> -48.913492 | AJ21: =IFERROR(VLOOKUP(B21,'Regiões Administrativas'!$A$1:$I$646,8,0),"") -> 500.31554 | AK21: =IFERROR(VLOOKUP(Form_Responses[[#This Row],[Município]],'Regiões Administrativas'!$A$1:$I$646,9,0),"") -> 1J6RdQ4;ieE-
A22: 46003.409 | B22: PAULICÉIA | C22: Sol do Oeste | D22: Réveillon | E22: Baile show em praça pública, aberta ao público em geral, com queima de fogos | F22: n | G22: Praça da Amizade | H22: n | I22: Dezembro | J22: 46387 | K22: 46388 | L22: 0.89583333 | M22: 0.125 | N22: Festa | O22: Social/Cívico/Histórico | P22: Réveillon (Ano Novo) | Q22: Nehuma das opções acima | R22: Regional | S22: 4500 | T22: 4500 | U22: 4000 | V22: 4000 | W22: Município | X22: n | Y22: turismo@pauliceia.sp.gov.br | Z22: Deficiência Fisica | AA22: Rampa, Banheiro Acessível, Portas Largas para PCR (Pessoa com cadeira de rodas) | AB22: Não possui | AC22: Livre | AD22: =IFERROR(VLOOKUP(B22,'Regiões Administrativas'!$A$1:$B$646,2,0),"") -> Presidente Prudente | AE22: =IFERROR(VLOOKUP(Form_Responses[[#This Row],[Município]],'Regiões Administrativas'!$A$1:$I$646,3,0),"") -> 16749 | AF22: =IFERROR(VLOOKUP(Form_Responses[[#This Row],[Município]],'Regiões Administrativas'!$A$1:$I$646,4,0),"") -> 353640605000001 | AG22: =IFERROR(VLOOKUP(Form_Responses[[#This Row],[Município]],'Regiões Administrativas'!$A$1:$I$646,4,0),"") -> 353640605000001 | AH22: =IFERROR(VLOOKUP(B22,'Regiões Administrativas'!$A$1:$I$646,5,0),"") -> 3536406 | AI22: =IFERROR(VLOOKUP(B22,'Regiões Administrativas'!$A$1:$I$646,6,0),"") -> -51.84714 | AJ22: =IFERROR(VLOOKUP(B22,'Regiões Administrativas'!$A$1:$I$646,8,0),"") -> 294.97142 | AK22: =IFERROR(VLOOKUP(Form_Responses[[#This Row],[Município]],'Regiões Administrativas'!$A$1:$I$646,9,0),"") -> 1J6R_cv7:*h>
A23: 46003.41 | B23: ITANHAÉM | C23: Costa da Mata Atlântica | D23: Festa do Divino Espírito Santo | E23: Realizada há mais de 300 anos, a Festa do Divino tem programação repleta de costumes e envolve fiéis de todas as idades em momentos importantes da comemoração, como a Noite da Soca, Alvorada Festiva, Abertura do Império, Missa Solene, Encerramento do Sentenciou, Procissão do Divino Espírito Santo, entre outros. | G23: Praça Narciso de Andrade | I23: Maio | J23: 46165 | K23: 46180 | L23: 0.79166667 | M23: 0.97916667 | N23: Festa | O23: Religioso | P23: Religioso | Q23: Nehuma das opções acima | R23: Regional | S23: 15000 | T23: 15000 | U23: 14500 | V23: 14500 | W23: Prefeitura de Itanhaém | Y23: turismo@itanhaem.sp.gov.br | Z23: Deficiência Fisica, Deficiência Intelectual | AA23: Rampa | AB23: Não possui | AC23: Livre | AD23: =IFERROR(VLOOKUP(B23,'Regiões Administrativas'!$A$1:$B$646,2,0),"") -> Santos | AE23: =IFERROR(VLOOKUP(Form_Responses[[#This Row],[Município]],'Regiões Administrativas'!$A$1:$I$646,3,0),"") -> 16088 | AF23: =IFERROR(VLOOKUP(Form_Responses[[#This Row],[Município]],'Regiões Administrativas'!$A$1:$I$646,4,0),"") -> 352210905000001 | AG23: =IFERROR(VLOOKUP(Form_Responses[[#This Row],[Município]],'Regiões Administrativas'!$A$1:$I$646,4,0),"") -> 352210905000001 | AH23: =IFERROR(VLOOKUP(B23,'Regiões Administrativas'!$A$1:$I$646,5,0),"") -> 3522109 | AI23: =IFERROR(VLOOKUP(B23,'Regiões Administrativas'!$A$1:$I$646,6,0),"") -> -46.790991 | AJ23: =IFERROR(VLOOKUP(B23,'Regiões Administrativas'!$A$1:$I$646,8,0),"") -> 6.473843 | AK23: =IFERROR(VLOOKUP(Form_Responses[[#This Row],[Município]],'Regiões Administrativas'!$A$1:$I$646,9,0),"") -> 1J6U:\7bhJ?f
A24: 46003.414 | B24: PAULICÉIA | C24: Sol do Oeste | D24: Carnaval | E24: Bailes carnavalescos, aberto ao público, realizado em praça ao ar livre. | F24: n | G24: Praça da Amizade | H24: n | I24: Fevereiro | J24: 46066 | K24: 46070 | L24: 0.91666667 | M24: 0.125 | N24: Festa | O24: Artístico/Cultural/Folclórico | P24: Carnaval | Q24: Nehuma das opções acima | R24: Regional | S24: 5000 | T24: 4500 | U24: 4500 | V24: 4500 | W24: Município | X24: n | Y24: turismo@pauliceia.sp.gov.br | Z24: Deficiência Fisica | AA24: Rampa, Banheiro Acessível, Portas Largas para PCR (Pessoa com cadeira de rodas) | AB24: Não possui | AC24: Livre | AD24: =IFERROR(VLOOKUP(B24,'Regiões Administrativas'!$A$1:$B$646,2,0),"") -> Presidente Prudente | AE24: =IFERROR(VLOOKUP(Form_Responses[[#This Row],[Município]],'Regiões Administrativas'!$A$1:$I$646,3,0),"") -> 16749 | AF24: =IFERROR(VLOOKUP(Form_Responses[[#This Row],[Município]],'Regiões Administrativas'!$A$1:$I$646,4,0),"") -> 353640605000001 | AG24: =IFERROR(VLOOKUP(Form_Responses[[#This Row],[Município]],'Regiões Administrativas'!$A$1:$I$646,4,0),"") -> 353640605000001 | AH24: =IFERROR(VLOOKUP(B24,'Regiões Administrativas'!$A$1:$I$646,5,0),"") -> 3536406 | AI24: =IFERROR(VLOOKUP(B24,'Regiões Administrativas'!$A$1:$I$646,6,0),"") -> -51.84714 | AJ24: =IFERROR(VLOOKUP(B24,'Regiões Administrativas'!$A$1:$I$646,8,0),"") -> 294.97142 | AK24: =IFERROR(VLOOKUP(Form_Responses[[#This Row],[Município]],'Regiões Administrativas'!$A$1:$I$646,9,0),"") -> 1J6R_cv7:*h>
A25: 46003.418 | B25: PAULICÉIA | C25: Sol do Oeste | D25: CarnaCross | E25: Tradicional competição de motocross, que ocorre há 25 anos, sendo realizado na pista permanente de motocross existente no balneário municipal, onde o público pode apreciar além da competição, a prainha, churrasqueiras e amplo espaço para motor home e camping. A competição ocorre durante os dias do carnaval, sendo uma alternativa aos bailes carnavalescos. | F25: n | G25: Balneário Municipal. | H25: n | I25: Fevereiro | J25: 46067 | K25: 46069 | L25: 0.33333333 | M25: 0.83333333 | N25: Campeonato/Torneio/Concurso | O25: Esportivo | P25: Carnaval | Q25: Nehuma das opções acima | R25: Internacional | S25: 4000 | T25: 3800 | U25: 4500 | V25: 4500 | W25: Município | X25: n | Y25: turismo@pauliceia.sp.gov.br | Z25: Deficiência Fisica | AA25: Banheiro Acessível | AB25: Não possui | AC25: Livre | AD25: =IFERROR(VLOOKUP(B25,'Regiões Administrativas'!$A$1:$B$646,2,0),"") -> Presidente Prudente | AE25: =IFERROR(VLOOKUP(Form_Responses[[#This Row],[Município]],'Regiões Administrativas'!$A$1:$I$646,3,0),"") -> 16749 | AF25: =IFERROR(VLOOKUP(Form_Responses[[#This Row],[Município]],'Regiões Administrativas'!$A$1:$I$646,4,0),"") -> 353640605000001 | AG25: =IFERROR(VLOOKUP(Form_Responses[[#This Row],[Município]],'Regiões Administrativas'!$A$1:$I$646,4,0),"") -> 353640605000001 | AH25: =IFERROR(VLOOKUP(B25,'Regiões Administrativas'!$A$1:$I$646,5,0),"") -> 3536406 | AI25: =IFERROR(VLOOKUP(B25,'Regiões Administrativas'!$A$1:$I$646,6,0),"") -> -51.84714 | AJ25: =IFERROR(VLOOKUP(B25,'Regiões Administrativas'!$A$1:$I$646,8,0),"") -> 294.97142 | AK25: =IFERROR(VLOOKUP(Form_Responses[[#This Row],[Município]],'Regiões Administrativas'!$A$1:$I$646,9,0),"") -> 1J6R_cv7:*h>
A26: 46003.423 | B26: PAULICÉIA | C26: Sol do Oeste | D26: Cavalgada | E26: No mês de junho, ocorre os festejos em comemoração ao aniversário de emancipação do município, e uma das atrações, é a cavalgada, que já ocorre há 20 anos, terminando com um almoço entre os participantes. | F26: n | G26: via pública | H26: n | I26: Junho | J26: 46180 | K26: 46180 | L26: 0.3125 | M26: 0.625 | N26: Aniversário | O26: Rural | P26: Agropecuária | Q26: Nehuma das opções acima | R26: Regional | S26: 1500 | T26: 1400 | U26: 1400 | V26: 1400 | W26: Município | X26: n | Y26: turismo@pauliceia.sp.gov.br | Z26: Não possui | AA26: Não possui | AB26: Não possui | AC26: Livre | AD26: =IFERROR(VLOOKUP(B26,'Regiões Administrativas'!$A$1:$B$646,2,0),"") -> Presidente Prudente | AE26: =IFERROR(VLOOKUP(Form_Responses[[#This Row],[Município]],'Regiões Administrativas'!$A$1:$I$646,3,0),"") -> 16749 | AF26: =IFERROR(VLOOKUP(Form_Responses[[#This Row],[Município]],'Regiões Administrativas'!$A$1:$I$646,4,0),"") -> 353640605000001 | AG26: =IFERROR(VLOOKUP(Form_Responses[[#This Row],[Município]],'Regiões Administrativas'!$A$1:$I$646,4,0),"") -> 353640605000001 | AH26: =IFERROR(VLOOKUP(B26,'Regiões Administrativas'!$A$1:$I$646,5,0),"") -> 3536406 | AI26: =IFERROR(VLOOKUP(B26,'Regiões Administrativas'!$A$1:$I$646,6,0),"") -> -51.84714 | AJ26: =IFERROR(VLOOKUP(B26,'Regiões Administrativas'!$A$1:$I$646,8,0),"") -> 294.97142 | AK26: =IFERROR(VLOOKUP(Form_Responses[[#This Row],[Município]],'Regiões Administrativas'!$A$1:$I$646,9,0),"") -> 1J6R_cv7:*h>
A27: 46003.427 | B27: TEODORO SAMPAIO | C27: Pontal Paulista | D27: Folia de Reis | E27: A Folia de Reis é uma celebração da Igreja Católica que rememora a visita dos três reis magos ao menino Jesus após seu nascimento. Trata-se de uma manifestação integrante do folclore brasileiro, realizada entre 24de dezembro, véspera do Natal, e 6 de janeiro, Dia de Reis. No município de Teodoro Sampaio, essa festa folclórica e cultural acontece há 39 anos. | G27: Assentamento Ribeirão Bonito | H27: sites.google.com/view/sec-turismocultura | I27: Dezembro | J27: 46015 | K27: 46032 | L27: 0.95833333 | M27: 0.79166667 | N27: Movimento | O27: Artístico/Cultural/Folclórico | P27: Religioso | Q27: Nehuma das opções acima | R27: Nacional | S27: 2000 | T27: 2500 | U27: 2000 | V27: 1350 | W27: Comissão da Folia de Reis | Y27: turismo@pmteodorosampaio.sp.gov.br | Z27: Deficiência Fisica | AA27: Banheiro Acessível, Portas Largas para PCR (Pessoa com cadeira de rodas) | AB27: Não possui | AC27: Livre | AD27: =IFERROR(VLOOKUP(B27,'Regiões Administrativas'!$A$1:$B$646,2,0),"") -> Presidente Prudente | AE27: =IFERROR(VLOOKUP(Form_Responses[[#This Row],[Município]],'Regiões Administrativas'!$A$1:$I$646,3,0),"") -> 17369 | AF27: =IFERROR(VLOOKUP(Form_Responses[[#This Row],[Município]],'Regiões Administrativas'!$A$1:$I$646,4,0),"") -> 355430005000001 | AG27: =IFERROR(VLOOKUP(Form_Responses[[#This Row],[Município]],'Regiões Administrativas'!$A$1:$I$646,4,0),"") -> 355430005000001 | AH27: =IFERROR(VLOOKUP(B27,'Regiões Administrativas'!$A$1:$I$646,5,0),"") -> 3554300 | AI27: =IFERROR(VLOOKUP(B27,'Regiões Administrativas'!$A$1:$I$646,6,0),"") -> -52.171195 | AJ27: =IFERROR(VLOOKUP(B27,'Regiões Administrativas'!$A$1:$I$646,8,0),"") -> 352.74983 | AK27: =IFERROR(VLOOKUP(Form_Responses[[#This Row],[Município]],'Regiões Administrativas'!$A$1:$I$646,9,0),"") -> 1J6RhG:@,eW>
A28: 46003.441 | B28: PAULICÉIA | C28: Sol do Oeste | D28: Rodeio Show | E28: Nos dias que antecedem a data do aniversário do município, 29/06, ocorre o Rodeio show, com montarias em touros e shows artísticos todas as noites, culminando na noite do dia 28, com distribuição de pipoca, amendoim torrado e quentão para o público presente, e ainda a queima da fogueira gigante, e queima de fogos, tradição desde 1984. | F28: n | G28: Recinto de Rodeio | H28: n | I28: Junho | J28: 46200 | K28: 46201 | L28: 0.79166667 | M28: 0.1875 | N28: Aniversário | O28: Social/Cívico/Histórico | P28: Festa Junina | Q28: Nehuma das opções acima | R28: Nacional | S28: 30000 | T28: 26000 | U28: 24000 | V28: 22000 | W28: Município | X28: n | Y28: turismo@pauliceia.sp.gov.br | Z28: Deficiência Fisica | AA28: Rampa, Banheiro Acessível | AB28: Não possui | AC28: Livre | AD28: =IFERROR(VLOOKUP(B28,'Regiões Administrativas'!$A$1:$B$646,2,0),"") -> Presidente Prudente | AE28: =IFERROR(VLOOKUP(Form_Responses[[#This Row],[Município]],'Regiões Administrativas'!$A$1:$I$646,3,0),"") -> 16749 | AF28: =IFERROR(VLOOKUP(Form_Responses[[#This Row],[Município]],'Regiões Administrativas'!$A$1:$I$646,4,0),"") -> 353640605000001 | AG28: =IFERROR(VLOOKUP(Form_Responses[[#This Row],[Município]],'Regiões Administrativas'!$A$1:$I$646,4,0),"") -> 353640605000001 | AH28: =IFERROR(VLOOKUP(B28,'Regiões Administrativas'!$A$1:$I$646,5,0),"") -> 3536406 | AI28: =IFERROR(VLOOKUP(B28,'Regiões Administrativas'!$A$1:$I$646,6,0),"") -> -51.84714 | AJ28: =IFERROR(VLOOKUP(B28,'Regiões Administrativas'!$A$1:$I$646,8,0),"") -> 294.97142 | AK28: =IFERROR(VLOOKUP(Form_Responses[[#This Row],[Município]],'Regiões Administrativas'!$A$1:$I$646,9,0),"") -> 1J6R_cv7:*h>
A29: 46003.444 | B29: PAULICÉIA | C29: Sol do Oeste | D29: Chegada do Papai Noel | E29: Chegada do Papai Noel, com trem da alegria, personagens infantis, e inauguração da iluminação de decoração natalina. | F29: n | G29: Praça São Pedro | H29: n | I29: Dezembro | J29: 46362 | K29: 46362 | L29: 0.77083333 | M29: 0.89583333 | N29: Festa | O29: Artístico/Cultural/Folclórico | P29: Natal | Q29: Nehuma das opções acima | R29: Regional | S29: 4000 | T29: 4000 | U29: 4000 | V29: 4000 | W29: Município | X29: n | Y29: turismo@pauliceia.sp.gov.br | Z29: Deficiência Fisica | AA29: Rampa, Banheiro Acessível | AB29: Não possui | AC29: Livre | AD29: =IFERROR(VLOOKUP(B29,'Regiões Administrativas'!$A$1:$B$646,2,0),"") -> Presidente Prudente | AE29: =IFERROR(VLOOKUP(Form_Responses[[#This Row],[Município]],'Regiões Administrativas'!$A$1:$I$646,3,0),"") -> 16749 | AF29: =IFERROR(VLOOKUP(Form_Responses[[#This Row],[Município]],'Regiões Administrativas'!$A$1:$I$646,4,0),"") -> 353640605000001 | AG29: =IFERROR(VLOOKUP(Form_Responses[[#This Row],[Município]],'Regiões Administrativas'!$A$1:$I$646,4,0),"") -> 353640605000001 | AH29: =IFERROR(VLOOKUP(B29,'Regiões Administrativas'!$A$1:$I$646,5,0),"") -> 3536406 | AI29: =IFERROR(VLOOKUP(B29,'Regiões Administrativas'!$A$1:$I$646,6,0),"") -> -51.84714 | AJ29: =IFERROR(VLOOKUP(B29,'Regiões Administrativas'!$A$1:$I$646,8,0),"") -> 294.97142 | AK29: =IFERROR(VLOOKUP(Form_Responses[[#This Row],[Município]],'Regiões Administrativas'!$A$1:$I$646,9,0),"") -> 1J6R_cv7:*h>
A30: 46003.448 | B30: PAULICÉIA | C30: Sol do Oeste | D30: Festa do dia das Crianças | E30: Festa em comemoração ao dia das crianças, com distribuição de picolé, hot dog, algodão doce, e atrações circenses bem como brinquedos como cama elástica, escorregador, tudo montado na praça da amizade. | F30: n | G30: Praça da amizade | H30: n | I30: Outubro | L30: 0.33333333 | M30: 0.58333333 | N30: Festa | O30: Social/Cívico/Histórico | P30: Social/Cívico/Histórico | Q30: Nehuma das opções acima | R30: Municipal | S30: 1800 | T30: 1500 | U30: 1500 | V30: 1500 | W30: Município. | X30: n | Y30: turismo@pauliceia.sp.gov.br | Z30: Deficiência Fisica | AA30: Rampa, Banheiro Acessível | AB30: Não possui | AC30: Livre | AD30: =IFERROR(VLOOKUP(B30,'Regiões Administrativas'!$A$1:$B$646,2,0),"") -> Presidente Prudente | AE30: =IFERROR(VLOOKUP(Form_Responses[[#This Row],[Município]],'Regiões Administrativas'!$A$1:$I$646,3,0),"") -> 16749 | AF30: =IFERROR(VLOOKUP(Form_Responses[[#This Row],[Município]],'Regiões Administrativas'!$A$1:$I$646,4,0),"") -> 353640605000001 | AG30: =IFERROR(VLOOKUP(Form_Responses[[#This Row],[Município]],'Regiões Administrativas'!$A$1:$I$646,4,0),"") -> 353640605000001 | AH30: =IFERROR(VLOOKUP(B30,'Regiões Administrativas'!$A$1:$I$646,5,0),"") -> 3536406 | AI30: =IFERROR(VLOOKUP(B30,'Regiões Administrativas'!$A$1:$I$646,6,0),"") -> -51.84714 | AJ30: =IFERROR(VLOOKUP(B30,'Regiões Administrativas'!$A$1:$I$646,8,0),"") -> 294.97142 | AK30: =IFERROR(VLOOKUP(Form_Responses[[#This Row],[Município]],'Regiões Administrativas'!$A$1:$I$646,9,0),"") -> 1J6R_cv7:*h>
A31: 46003.46 | B31: OLÍMPIA | C31: Águas Sertanejas | D31: Aniversário da cidade de Olímpia | E31: O aniversário da cidade de Olímpia (SP) é comemorado em 2 de março, data em que se celebra sua fundação, comemorando 123 anos em 2026, com uma rica programação de shows, eventos cívicos e festividades que marcam a história da cidade e seu desenvolvimento, especialmente pelo turismo das águas termais | G31: Recinto do Folclore de Olímpia - Avenida Menina Moça, nº 800, Vila Hípica, Olímpia - SP, CEP 15407-050 | H31: olimpia.sp.gov.br | I31: Março | J31: 46083 | K31: 46083 | L31: 0.83333333 | M31: 0.99930556 | N31: Aniversário | O31: Social/Cívico/Histórico | P31: Social/Cívico/Histórico | Q31: Nehuma das opções acima | R31: Municipal | S31: 30000 | T31: 50000 | U31: 30000 | V31: 7000 | W31: Prefeitura da Estância Turística de Olímpia | Y31: prefeitura@olimpia.sp.gov.br | Z31: Deficiência Fisica | AA31: Atendimento em Línguas de Sinais, Rampa, Elevador, Banheiro Acessível, Balcão de atendimento com altura reduzida, Portas Largas para PCR (Pessoa com cadeira de rodas) | AB31: Áudio Descrição no site do evento, Legenda no site do evento | AC31: Livre | AD31: =IFERROR(VLOOKUP(B31,'Regiões Administrativas'!$A$1:$B$646,2,0),"") -> Barretos | AE31: =IFERROR(VLOOKUP(Form_Responses[[#This Row],[Município]],'Regiões Administrativas'!$A$1:$I$646,3,0),"") -> 16671 | AF31: =IFERROR(VLOOKUP(Form_Responses[[#This Row],[Município]],'Regiões Administrativas'!$A$1:$I$646,4,0),"") -> 353390805000001 | AG31: =IFERROR(VLOOKUP(Form_Responses[[#This Row],[Município]],'Regiões Administrativas'!$A$1:$I$646,4,0),"") -> 353390805000001 | AH31: =IFERROR(VLOOKUP(B31,'Regiões Administrativas'!$A$1:$I$646,5,0),"") -> 3533908 | AI31: =IFERROR(VLOOKUP(B31,'Regiões Administrativas'!$A$1:$I$646,6,0),"") -> -48.913492 | AJ31: =IFERROR(VLOOKUP(B31,'Regiões Administrativas'!$A$1:$I$646,8,0),"") -> 500.31554 | AK31: =IFERROR(VLOOKUP(Form_Responses[[#This Row],[Município]],'Regiões Administrativas'!$A$1:$I$646,9,0),"") -> 1J6RdQ4;ieE-
A32: 46003.484 | B32: TEODORO SAMPAIO | C32: Pontal Paulista | D32: Inauguração do Balneário Municipal | E32: Trio Elétrico e Banda de Axé | G32: Final da Avenida Manoel Guirado Segura-vicinal que liga ao balneário | H32: sites.google.com/view/sec-turismocultura | I32: Janeiro | J32: 42386 | K32: 46046 | N32: Feira/Exposição/Mostra | O32: Comercial/Promocional | P32: Nenhuma das opções acima | Q32: Nehuma das opções acima | R32: Regional | S32: 10000 | W32: Secretaria de Turismo e Cultura e secretaria de Esporte e Lazer do municipio de Teodoro Sampaio_SP | X32: entrada franca | Y32: turismo@pmteodorosampaio.sp.gov.br | Z32: Deficiência Fisica | AA32: Banheiro Acessível, Portas Largas para PCR (Pessoa com cadeira de rodas) | AB32: Não possui | AC32: Livre | AD32: =IFERROR(VLOOKUP(B32,'Regiões Administrativas'!$A$1:$B$646,2,0),"") -> Presidente Prudente | AE32: =IFERROR(VLOOKUP(Form_Responses[[#This Row],[Município]],'Regiões Administrativas'!$A$1:$I$646,3,0),"") -> 17369 | AF32: =IFERROR(VLOOKUP(Form_Responses[[#This Row],[Município]],'Regiões Administrativas'!$A$1:$I$646,4,0),"") -> 355430005000001 | AG32: =IFERROR(VLOOKUP(Form_Responses[[#This Row],[Município]],'Regiões Administrativas'!$A$1:$I$646,4,0),"") -> 355430005000001 | AH32: =IFERROR(VLOOKUP(B32,'Regiões Administrativas'!$A$1:$I$646,5,0),"") -> 3554300 | AI32: =IFERROR(VLOOKUP(B32,'Regiões Administrativas'!$A$1:$I$646,6,0),"") -> -52.171195 | AJ32: =IFERROR(VLOOKUP(B32,'Regiões Administrativas'!$A$1:$I$646,8,0),"") -> 352.74983 | AK32: =IFERROR(VLOOKUP(Form_Responses[[#This Row],[Município]],'Regiões Administrativas'!$A$1:$I$646,9,0),"") -> 1J6RhG:@,eW>
A33: 46003.497 | B33: ITAPECERICA DA SERRA | C33: Mananciais, Aventura, Artes e Negócios | D33: Festa da Primavera | E33: Evento familiar que acontece anualmente no município com caráter turístico e cultural; Realizado com o objetivo de promover a valorização das tradições locais, estimular a participação social e fomentar a economia criativa da região. A programação contempla atividades como apresentações artísticas, exposições de artesanatos, produtores locais, gastronomia e ações educativas voltadas à preservação ambiental. o evento integra o calendário municipal, contribuindo para o fortalecimento do turismo, para o desenvolvimento sociocultural e para ampliação de espaços de turismo e lazer. | G33: Praça da Fonte - Praça João Ferreira Domingues | H33: @turismoitapecerica | I33: Setembro | J33: 46291 | K33: 46292 | L33: 0.41666667 | M33: 0.95833333 | N33: Festa | O33: Artístico/Cultural/Folclórico | P33: Social/Cívico/Histórico | Q33: Nehuma das opções acima | R33: Regional | S33: 5000 | T33: 2500 | U33: 0 | V33: 0 | W33: Prefeitura Municipal de Itapecerica da Serra - Secretaria Municipal de Turismo | X33: evento gratuito | Y33: setur.itap@gmail.com | Z33: Deficiência Fisica, Deficiência Intelectual | AA33: Rampa, Banheiro Acessível | AB33: Não possui | AC33: Livre | AD33: =IFERROR(VLOOKUP(B33,'Regiões Administrativas'!$A$1:$B$646,2,0),"") -> RMSP | AE33: =IFERROR(VLOOKUP(Form_Responses[[#This Row],[Município]],'Regiões Administrativas'!$A$1:$I$646,3,0),"") -> 16095 | AF33: =IFERROR(VLOOKUP(Form_Responses[[#This Row],[Município]],'Regiões Administrativas'!$A$1:$I$646,4,0),"") -> 352220805000001 | AG33: =IFERROR(VLOOKUP(Form_Responses[[#This Row],[Município]],'Regiões Administrativas'!$A$1:$I$646,4,0),"") -> 352220805000001 | AH33: =IFERROR(VLOOKUP(B33,'Regiões Administrativas'!$A$1:$I$646,5,0),"") -> 3522208 | AI33: =IFERROR(VLOOKUP(B33,'Regiões Administrativas'!$A$1:$I$646,6,0),"") -> -46.850552 | AJ33: =IFERROR(VLOOKUP(B33,'Regiões Administrativas'!$A$1:$I$646,8,0),"") -> 905.95027 | AK33: =IFERROR(VLOOKUP(Form_Responses[[#This Row],[Município]],'Regiões Administrativas'!$A$1:$I$646,9,0),"") -> 1J6to^L]J:6f
A34: 46003.499 | B34: TEODORO SAMPAIO | C34: Pontal Paulista | D34: Aniversario Emancipação Politica Administrativa do Teodoro Sampaio | E34: Evento realizado com Show, desfile cívico, apresentação das bandas marciais regional, cidade dos infláveis, pipoca, algodão doce, refrigerante, dois dias de festa para a população municipal, regional e interestadual. | G34: Praça Antonio Evangelista da Silva, Avenida Cuiabá, n° 1544 | H34: sites.google.com/view/sec-turismocultura | I34: Março | J34: 46101 | K34: 46103 | L34: 0.375 | M34: 0.16666667 | N34: Aniversário | O34: Social/Cívico/Histórico | P34: Social/Cívico/Histórico | Q34: Nehuma das opções acima | R34: Nacional | S34: 10000 | T34: 5000 | U34: 2000 | V34: 800 | W34: Secretaria de Turismo e Cultura e Secretaria de Educação | Y34: turismo@pmteodorosampaio.sp.gov.br | Z34: Deficiência Fisica, Deficiência Intelectual | AA34: Banheiro Acessível, Portas Largas para PCR (Pessoa com cadeira de rodas) | AB34: Não possui | AC34: Livre | AD34: =IFERROR(VLOOKUP(B34,'Regiões Administrativas'!$A$1:$B$646,2,0),"") -> Presidente Prudente | AE34: =IFERROR(VLOOKUP(Form_Responses[[#This Row],[Município]],'Regiões Administrativas'!$A$1:$I$646,3,0),"") -> 17369 | AF34: =IFERROR(VLOOKUP(Form_Responses[[#This Row],[Município]],'Regiões Administrativas'!$A$1:$I$646,4,0),"") -> 355430005000001 | AG34: =IFERROR(VLOOKUP(Form_Responses[[#This Row],[Município]],'Regiões Administrativas'!$A$1:$I$646,4,0),"") -> 355430005000001 | AH34: =IFERROR(VLOOKUP(B34,'Regiões Administrativas'!$A$1:$I$646,5,0),"") -> 3554300 | AI34: =IFERROR(VLOOKUP(B34,'Regiões Administrativas'!$A$1:$I$646,6,0),"") -> -52.171195 | AJ34: =IFERROR(VLOOKUP(B34,'Regiões Administrativas'!$A$1:$I$646,8,0),"") -> 352.74983 | AK34: =IFERROR(VLOOKUP(Form_Responses[[#This Row],[Município]],'Regiões Administrativas'!$A$1:$I$646,9,0),"") -> 1J6RhG:@,eW>
A35: 46003.504 | B35: ITAPECERICA DA SERRA | C35: Mananciais, Aventura, Artes e Negócios | D35: Expoagro | E35: O evento teve como objetivo fortalecer a cadeia do agronegócio regional, promover a economia e ampliar a oferta de atividades voltadas ao turismo e ao desenvolvimento sustentável. A estrutura do evento contou com área de exposição de produtos agrícolas, mostra de animais, espaço para empreendedores, estandes institucionais, praça de alimentação, além de programação cultural com apresentações musicais e atrações para o público geral. A Expoagro também proporcionou integração entre produtores, consumidores, instituições públicas e iniciativas privadas, estimulando o intercâmbio de conhecimentos e oportunidades de negócios. A realização da feira contribuiu para a valorização das atividades agropecuárias de Itapecerica da Serra, ampliando a visibilidade do setor, fortalecendo ações de turismo e promovendo movimentação econômica local durante os dois dias do evento. | G35: Ginásio de Esportes - Centro Educacional Poliesportivo Antonio Baldusco - Av. Dona Anila 1001 | H35: @turismoitapecerica | I35: Maio | J35: 46172 | K35: 46173 | L35: 0.45833333 | M35: 0.95833333 | N35: Feira/Exposição/Mostra | O35: Artístico/Cultural/Folclórico | P35: Agropecuária | Q35: Nehuma das opções acima | R35: Regional | S35: 5000 | T35: 4500 | U35: 0 | V35: 0 | W35: Pref Municipal de Itapecerica da Serra - Sec Municipal de Turismo | X35: evento gratuito | Y35: setur.itap@gmail.com | Z35: Não possui | AA35: Rampa, Banheiro Acessível | AB35: Não possui | AC35: Livre | AD35: =IFERROR(VLOOKUP(B35,'Regiões Administrativas'!$A$1:$B$646,2,0),"") -> RMSP | AE35: =IFERROR(VLOOKUP(Form_Responses[[#This Row],[Município]],'Regiões Administrativas'!$A$1:$I$646,3,0),"") -> 16095 | AF35: =IFERROR(VLOOKUP(Form_Responses[[#This Row],[Município]],'Regiões Administrativas'!$A$1:$I$646,4,0),"") -> 352220805000001 | AG35: =IFERROR(VLOOKUP(Form_Responses[[#This Row],[Município]],'Regiões Administrativas'!$A$1:$I$646,4,0),"") -> 352220805000001 | AH35: =IFERROR(VLOOKUP(B35,'Regiões Administrativas'!$A$1:$I$646,5,0),"") -> 3522208 | AI35: =IFERROR(VLOOKUP(B35,'Regiões Administrativas'!$A$1:$I$646,6,0),"") -> -46.850552 | AJ35: =IFERROR(VLOOKUP(B35,'Regiões Administrativas'!$A$1:$I$646,8,0),"") -> 905.95027 | AK35: =IFERROR(VLOOKUP(Form_Responses[[#This Row],[Município]],'Regiões Administrativas'!$A$1:$I$646,9,0),"") -> 1J6to^L]J:6f
A36: 46003.614 | B36: OLÍMPIA | C36: Águas Sertanejas | D36: Festival do Folclore 2026 - 62° Edição | E36: O Festival do Folclore de Olímpia (FEFOL) é o maior evento de folclore do Brasil, que acontece anualmente em Olímpia (SP), consolidando a cidade como a Capital Nacional do Folclore, reunindo manifestações culturais autênticas de todo o país, com danças, músicas, artesanato, e celebrações que preservam as tradições populares brasileiras, sendo um evento gratuito e com entrada livre, realizado no Recinto do Folclore. | G36: Recinto do Folclore de Olímpia - Avenida Menina Moça, nº 800, Vila Hípica, Olímpia - SP, CEP 15407-050 | H36: https://www.folcloreolimpia.com.br/ | I36: Agosto | J36: 46235 | K36: 46243 | L36: 0.83333333 | M36: 0.99930556 | N36: Festival | O36: Artístico/Cultural/Folclórico | P36: Social/Cívico/Histórico | Q36: Nehuma das opções acima | R36: Nacional | S36: 170000 | T36: 160000 | U36: 180000 | V36: 160000 | W36: Prefeitura da Estância Turística de Olímpia | Y36: prefeitura@olimpia.sp.gov.br | Z36: Deficiência Fisica | AA36: Atendimento em Línguas de Sinais, Rampa, Elevador, Banheiro Acessível, Balcão de atendimento com altura reduzida, Portas Largas para PCR (Pessoa com cadeira de rodas) | AB36: Áudio Descrição no site do evento, Legenda no site do evento | AC36: Livre | AD36: =IFERROR(VLOOKUP(B36,'Regiões Administrativas'!$A$1:$B$646,2,0),"") -> Barretos | AE36: =IFERROR(VLOOKUP(Form_Responses[[#This Row],[Município]],'Regiões Administrativas'!$A$1:$I$646,3,0),"") -> 16671 | AF36: =IFERROR(VLOOKUP(Form_Responses[[#This Row],[Município]],'Regiões Administrativas'!$A$1:$I$646,4,0),"") -> 353390805000001 | AG36: =IFERROR(VLOOKUP(Form_Responses[[#This Row],[Município]],'Regiões Administrativas'!$A$1:$I$646,4,0),"") -> 353390805000001 | AH36: =IFERROR(VLOOKUP(B36,'Regiões Administrativas'!$A$1:$I$646,5,0),"") -> 3533908 | AI36: =IFERROR(VLOOKUP(B36,'Regiões Administrativas'!$A$1:$I$646,6,0),"") -> -48.913492 | AJ36: =IFERROR(VLOOKUP(B36,'Regiões Administrativas'!$A$1:$I$646,8,0),"") -> 500.31554 | AK36: =IFERROR(VLOOKUP(Form_Responses[[#This Row],[Município]],'Regiões Administrativas'!$A$1:$I$646,9,0),"") -> 1J6RdQ4;ieE-
A37: 46003.624 | B37: SANTA ALBERTINA | C37: Entre Rios | D37: Rewillon | E37: Virado do ano , show em praca pública | G37: Avenida Francisco Shimidt | I37: Dezembro | J37: 46022 | K37: 46023 | L37: 0.95833333 | M37: 0.083333333 | N37: Festa | O37: Social/Cívico/Histórico | P37: Réveillon (Ano Novo) | Q37: Nehuma das opções acima | R37: Regional | S37: 3000 | T37: 2500 | U37: 2000 | V37: 2000 | W37: Prefeitura municipal | Y37: 17996425082 | Z37: Deficiência Fisica, Deficiência Visual | AA37: Piso Tátil, Rampa, Banheiro Acessível, Portas Largas para PCR (Pessoa com cadeira de rodas) | AB37: Não possui | AC37: Livre | AD37: =IFERROR(VLOOKUP(B37,'Regiões Administrativas'!$A$1:$B$646,2,0),"") -> São José do Rio Preto | AE37: =IFERROR(VLOOKUP(Form_Responses[[#This Row],[Município]],'Regiões Administrativas'!$A$1:$I$646,3,0),"") -> 17043 | AF37: =IFERROR(VLOOKUP(Form_Responses[[#This Row],[Município]],'Regiões Administrativas'!$A$1:$I$646,4,0),"") -> 354570405000001 | AG37: =IFERROR(VLOOKUP(Form_Responses[[#This Row],[Município]],'Regiões Administrativas'!$A$1:$I$646,4,0),"") -> 354570405000001 | AH37: =IFERROR(VLOOKUP(B37,'Regiões Administrativas'!$A$1:$I$646,5,0),"") -> 3545704 | AI37: =IFERROR(VLOOKUP(B37,'Regiões Administrativas'!$A$1:$I$646,6,0),"") -> -50.730564 | AJ37: =IFERROR(VLOOKUP(B37,'Regiões Administrativas'!$A$1:$I$646,8,0),"") -> 418.52105 | AK37: =IFERROR(VLOOKUP(Form_Responses[[#This Row],[Município]],'Regiões Administrativas'!$A$1:$I$646,9,0),"") -> 1J6R@AKYe3Dp
A38: 46003.629 | B38: TEODORO SAMPAIO | C38: Pontal Paulista | D38: Paixão de Cristo Teatral | E38: Morte e ressurreição da vida de JESUS CRISTO em peça Teatral, onde todos revivem o sofrimento de JESUS para salvar a humanidade | G38: Recinto de Rodeio Toninho Cowboy, rua Alberto amador , nº. 914 | H38: @paroquian.sperpetuosocorro | I38: Abril | J38: 46115 | K38: 46115 | L38: 0.79166667 | N38: Festa | O38: Religioso | P38: Corpus Christi | Q38: Nehuma das opções acima | R38: Nacional | S38: 15000 | T38: 11.0000 | U38: 9000 | V38: 8000 | W38: Comissão Organizadora Religiosa | Y38: paroquiateodorosampaio@hotmail.com | Z38: Deficiência Fisica | AA38: Banheiro Acessível | AB38: Áudio Descrição no site do evento | AC38: Livre | AD38: =IFERROR(VLOOKUP(B38,'Regiões Administrativas'!$A$1:$B$646,2,0),"") -> Presidente Prudente | AE38: =IFERROR(VLOOKUP(Form_Responses[[#This Row],[Município]],'Regiões Administrativas'!$A$1:$I$646,3,0),"") -> 17369 | AF38: =IFERROR(VLOOKUP(Form_Responses[[#This Row],[Município]],'Regiões Administrativas'!$A$1:$I$646,4,0),"") -> 355430005000001 | AG38: =IFERROR(VLOOKUP(Form_Responses[[#This Row],[Município]],'Regiões Administrativas'!$A$1:$I$646,4,0),"") -> 355430005000001 | AH38: =IFERROR(VLOOKUP(B38,'Regiões Administrativas'!$A$1:$I$646,5,0),"") -> 3554300 | AI38: =IFERROR(VLOOKUP(B38,'Regiões Administrativas'!$A$1:$I$646,6,0),"") -> -52.171195 | AJ38: =IFERROR(VLOOKUP(B38,'Regiões Administrativas'!$A$1:$I$646,8,0),"") -> 352.74983 | AK38: =IFERROR(VLOOKUP(Form_Responses[[#This Row],[Município]],'Regiões Administrativas'!$A$1:$I$646,9,0),"") -> 1J6RhG:@,eW>
A39: 46003.691 | B39: TEODORO SAMPAIO | C39: Pontal Paulista | D39: Corrida Ecológica | E39: Comemoração ao dia do Meio Ambiente, corrida no Parque estadual Morro do Diabo, conscientização da preservação e conservação do meio ambiente | G39: Rodovia Rubens Carlos Herling SPV-28 Km 11, Bairro Corrego Seco | I39: Junho | J39: 46174 | K39: 46180 | N39: Movimento | O39: Ecoturismo | P39: Nenhuma das opções acima | Q39: Nehuma das opções acima | R39: Nacional | S39: 2000 | W39: Secretaria de Turismo e Cultura e Parque Estadual Morro do Diabo | Y39: turismo@pmteodorosampaio.sp.gov.br | Z39: Não possui | AA39: Banheiro Acessível, Portas Largas para PCR (Pessoa com cadeira de rodas) | AB39: Não possui | AC39: Indicado para maiores de 16 anos | AD39: =IFERROR(VLOOKUP(B39,'Regiões Administrativas'!$A$1:$B$646,2,0),"") -> Presidente Prudente | AE39: =IFERROR(VLOOKUP(Form_Responses[[#This Row],[Município]],'Regiões Administrativas'!$A$1:$I$646,3,0),"") -> 17369 | AF39: =IFERROR(VLOOKUP(Form_Responses[[#This Row],[Município]],'Regiões Administrativas'!$A$1:$I$646,4,0),"") -> 355430005000001 | AG39: =IFERROR(VLOOKUP(Form_Responses[[#This Row],[Município]],'Regiões Administrativas'!$A$1:$I$646,4,0),"") -> 355430005000001 | AH39: =IFERROR(VLOOKUP(B39,'Regiões Administrativas'!$A$1:$I$646,5,0),"") -> 3554300 | AI39: =IFERROR(VLOOKUP(B39,'Regiões Administrativas'!$A$1:$I$646,6,0),"") -> -52.171195 | AJ39: =IFERROR(VLOOKUP(B39,'Regiões Administrativas'!$A$1:$I$646,8,0),"") -> 352.74983 | AK39: =IFERROR(VLOOKUP(Form_Responses[[#This Row],[Município]],'Regiões Administrativas'!$A$1:$I$646,9,0),"") -> 1J6RhG:@,eW>
A40: 46003.701 | B40: SUZANÁPOLIS | C40: Pontal Paulista | D40: Natal iluminado 2026 | E40: O Natal Iluminado transformou nossa cidade em um verdadeiro cenário de encanto. A praça central, a prefeitura e as avenidas principais ganharam luzes, cores e decoração especial, criando um ambiente acolhedor que celebra a magia natalina e reúne famílias e visitantes em momentos de alegria. | G40: Praça Salvador Ferreira de Souza | H40: Prefeitura municipal | I40: Novembro | J40: 46347 | K40: 46393 | L40: 0.85416667 | M40: 0.083333333 | N40: Festa | O40: Artístico/Cultural/Folclórico | P40: Natal | Q40: Nehuma das opções acima | R40: Regional | S40: 4000 | T40: 3000 | U40: 2500 | V40: 2500 | W40: Prefeitura municipal | Y40: esporte@suzanapolis.sp.gov.br | Z40: Deficiência Fisica | AA40: Rampa, Banheiro Acessível | AB40: Intérprete de Libras no site do evento, Áudio Descrição no site do evento, Legenda no site do evento | AC40: Livre | AD40: =IFERROR(VLOOKUP(B40,'Regiões Administrativas'!$A$1:$B$646,2,0),"") -> Araçatuba | AE40: =IFERROR(VLOOKUP(Form_Responses[[#This Row],[Município]],'Regiões Administrativas'!$A$1:$I$646,3,0),"") -> 17328 | AF40: =IFERROR(VLOOKUP(Form_Responses[[#This Row],[Município]],'Regiões Administrativas'!$A$1:$I$646,4,0),"") -> 355255105000001 | AG40: =IFERROR(VLOOKUP(Form_Responses[[#This Row],[Município]],'Regiões Administrativas'!$A$1:$I$646,4,0),"") -> 355255105000001 | AH40: =IFERROR(VLOOKUP(B40,'Regiões Administrativas'!$A$1:$I$646,5,0),"") -> 3552551 | AI40: =IFERROR(VLOOKUP(B40,'Regiões Administrativas'!$A$1:$I$646,6,0),"") -> -51.028223 | AJ40: =IFERROR(VLOOKUP(B40,'Regiões Administrativas'!$A$1:$I$646,8,0),"") -> 353.76624 | AK40: =IFERROR(VLOOKUP(Form_Responses[[#This Row],[Município]],'Regiões Administrativas'!$A$1:$I$646,9,0),"") -> 1J6R+,1..<Mp
A41: 46003.701 | B41: OLÍMPIA | C41: Águas Sertanejas | D41: Quermesse Santuário de Nossa Senhora Aparecida | E41: A Quermesse do Santuário de Nossa Senhora Aparecida em Olímpia, conhecida como Fenossa (Festa de Nossa Senhora Aparecida), é um evento anual tradicional que acontece em outubro, com programação que inclui comidas típicas (frango assado, churrasco, polenta), shows, bingo, brincadeiras e momentos de fé, reunindo a comunidade para celebrar a Padroeira do Brasil em um ambiente de alegria e confraternização, com atividades no calçadão e no próprio Santuário. | G41: Praça Nossa Senhora Aparecida, 183 - Patrimônio de Nossa Senhora Aparecida, Olímpia - SP, 15400-000 | H41: https://santuarioaparecidaolimpia.com.br/ | I41: Outubro | J41: 46298 | K41: 46307 | L41: 0.79166667 | M41: 0.99930556 | N41: Festa | O41: Religioso | P41: Religioso | Q41: Nehuma das opções acima | R41: Nacional | S41: 12000 | T41: 10000 | U41: 8000 | V41: 10000 | W41: Santuário de Nossa Senhora Aparecida Olímpia | Y41: secretaria@santuarioaparecidaolimpia.com.br | Z41: Deficiência Fisica | AA41: Atendimento em Línguas de Sinais, Rampa, Elevador, Banheiro Acessível, Portas Largas para PCR (Pessoa com cadeira de rodas) | AB41: Não possui | AC41: Livre | AD41: =IFERROR(VLOOKUP(B41,'Regiões Administrativas'!$A$1:$B$646,2,0),"") -> Barretos | AE41: =IFERROR(VLOOKUP(Form_Responses[[#This Row],[Município]],'Regiões Administrativas'!$A$1:$I$646,3,0),"") -> 16671 | AF41: =IFERROR(VLOOKUP(Form_Responses[[#This Row],[Município]],'Regiões Administrativas'!$A$1:$I$646,4,0),"") -> 353390805000001 | AG41: =IFERROR(VLOOKUP(Form_Responses[[#This Row],[Município]],'Regiões Administrativas'!$A$1:$I$646,4,0),"") -> 353390805000001 | AH41: =IFERROR(VLOOKUP(B41,'Regiões Administrativas'!$A$1:$I$646,5,0),"") -> 3533908 | AI41: =IFERROR(VLOOKUP(B41,'Regiões Administrativas'!$A$1:$I$646,6,0),"") -> -48.913492 | AJ41: =IFERROR(VLOOKUP(B41,'Regiões Administrativas'!$A$1:$I$646,8,0),"") -> 500.31554 | AK41: =IFERROR(VLOOKUP(Form_Responses[[#This Row],[Município]],'Regiões Administrativas'!$A$1:$I$646,9,0),"") -> 1J6RdQ4;ieE-
A42: 46003.925 | B42: SALTO DE PIRAPORA | C42: História & Aventuras | D42: Natal Cultural | E42: O Natal Cultural é um evento que celebra o espírito natalino com uma programação diversificada de atrações culturais, musicais e artísticas, promovendo lazer, convivência familiar e valorização dos talentos locais, em um ambiente de alegria, inclusão e tradição. | G42: Rua Francisco de Barros Leite - Centro, Salto de Pirapora | H42: https://www.instagram.com/culturasaltodepirapora/?locale=us&hl=am-et | I42: Dezembro | J42: 46366 | K42: 46375 | L42: 0.79166667 | M42: 0.91666667 | N42: Festival | O42: Artístico/Cultural/Folclórico | P42: Natal | Q42: Nehuma das opções acima | R42: Regional | S42: 15000 | T42: 10000 | U42: 10000 | V42: 10000 | W42: Secretaria de Esporte e Cultura | Y42: turismosaltodepirapora@gmail.com | Z42: Deficiência Intelectual | AA42: Outro: | AB42: Não possui | AC42: Livre | AD42: =IFERROR(VLOOKUP(B42,'Regiões Administrativas'!$A$1:$B$646,2,0),"") -> Sorocaba | AE42: =IFERROR(VLOOKUP(Form_Responses[[#This Row],[Município]],'Regiões Administrativas'!$A$1:$I$646,3,0),"") -> 17030 | AF42: =IFERROR(VLOOKUP(Form_Responses[[#This Row],[Município]],'Regiões Administrativas'!$A$1:$I$646,4,0),"") -> 354530805000001 | AG42: =IFERROR(VLOOKUP(Form_Responses[[#This Row],[Município]],'Regiões Administrativas'!$A$1:$I$646,4,0),"") -> 354530805000001 | AH42: =IFERROR(VLOOKUP(B42,'Regiões Administrativas'!$A$1:$I$646,5,0),"") -> 3545308 | AI42: =IFERROR(VLOOKUP(B42,'Regiões Administrativas'!$A$1:$I$646,6,0),"") -> -47.57468 | AJ42: =IFERROR(VLOOKUP(B42,'Regiões Administrativas'!$A$1:$I$646,8,0),"") -> 632.3872 | AK42: =IFERROR(VLOOKUP(Form_Responses[[#This Row],[Município]],'Regiões Administrativas'!$A$1:$I$646,9,0),"") -> 1J6tmdw\:J2p
A43: 46006.382 | B43: BRODOWSKI | C43: Raízes do Campo | D43: Carnaval Abre Alas | E43: Uma festa organizada para todas as famílias de Brodowski e Região, com a presença de muita música boa, fantasias, concursos e alegoria. | G43: Praça de Aliemntação "Santo Betetti" | H43: https://guia.destinosinteligentes.tur.br/Brodowski/ | I43: Fevereiro | J43: 46067 | K43: 46070 | L43: 0.66666667 | M43: 0.91666667 | N43: Festa | O43: Artístico/Cultural/Folclórico | P43: Carnaval | Q43: Nehuma das opções acima | R43: Regional | S43: 6000 | T43: 5000 | U43: 4000 | V43: 4000 | W43: Prefeitura Municipal de Brodowski-SP | Y43: turismo@brodowski.sp.gov.br | Z43: Deficiência Fisica | AA43: Rampa, Portas Largas para PCR (Pessoa com cadeira de rodas) | AB43: Legenda no site do evento | AC43: Livre | AD43: =IFERROR(VLOOKUP(B43,'Regiões Administrativas'!$A$1:$B$646,2,0),"") -> Ribeirão Preto | AE43: =IFERROR(VLOOKUP(Form_Responses[[#This Row],[Município]],'Regiões Administrativas'!$A$1:$I$646,3,0),"") -> 15635 | AF43: =IFERROR(VLOOKUP(Form_Responses[[#This Row],[Município]],'Regiões Administrativas'!$A$1:$I$646,4,0),"") -> 350780305000001 | AG43: =IFERROR(VLOOKUP(Form_Responses[[#This Row],[Município]],'Regiões Administrativas'!$A$1:$I$646,4,0),"") -> 350780305000001 | AH43: =IFERROR(VLOOKUP(B43,'Regiões Administrativas'!$A$1:$I$646,5,0),"") -> 3507803 | AI43: =IFERROR(VLOOKUP(B43,'Regiões Administrativas'!$A$1:$I$646,6,0),"") -> -47.656398 | AJ43: =IFERROR(VLOOKUP(B43,'Regiões Administrativas'!$A$1:$I$646,8,0),"") -> 863.03352 | AK43: =IFERROR(VLOOKUP(Form_Responses[[#This Row],[Município]],'Regiões Administrativas'!$A$1:$I$646,9,0),"") -> 1J6t\XJ:2{Rp
A44: 46006.389 | B44: BRODOWSKI | C44: Raízes do Campo | D44: Encontro Nacional de Companhias de Santos Reis de Brodowski-SP | E44: A religiosidade do brodowskiano é muito marcante devido à sua formação mesclando imigrantes europeus, principalmente italianos e portugueses, bem como imigrantes do norte-nordeste do país que são povos tradicionalmente religiosos. Essa presença religiosa aflora nessas que é uma das mais bonitas manifestações folclóricas da região: em dezembro e janeiro, as Companhias de Reis ou Folias de Reis, saem em peregrinação pelas fazendas, sítios, e residências da cidade, cantando e rezando o terço. Em virtude de tão popular manifestação folclórica, é realizada, nos meses de Abril/Maio de cada ano, o Encontro Nacional de Companhias de Santos Reis, e se constitui numa grandiosa festa folclórica, que proporciona o encontro de mais 30 cidades da região e do sul de Minas Gerais, com dezenas de Companhias de Reis, que passam o dia cantando, rezando e se confraternizando, num portentoso espetáculo de fé e religiosidade. | G44: Praça Martim Moreira, 142 - Centro - Brodowski-SP | H44: https://guia.destinosinteligentes.tur.br/Brodowski/ | I44: Abril | J44: 46142 | K44: 46145 | L44: 0.79166667 | M44: 0 | N44: Festa | O44: Artístico/Cultural/Folclórico | P44: Religioso | Q44: Nehuma das opções acima | R44: Nacional | S44: 10000 | T44: 8000 | U44: 7000 | V44: 7000 | W44: Prefeitura Municipal de Brodowski-SP | Y44: turismo@brodowski.sp.gov.br | Z44: Deficiência Fisica | AA44: Rampa, Banheiro Acessível, Portas Largas para PCR (Pessoa com cadeira de rodas) | AB44: Legenda no site do evento | AC44: Livre | AD44: =IFERROR(VLOOKUP(B44,'Regiões Administrativas'!$A$1:$B$646,2,0),"") -> Ribeirão Preto | AE44: =IFERROR(VLOOKUP(Form_Responses[[#This Row],[Município]],'Regiões Administrativas'!$A$1:$I$646,3,0),"") -> 15635 | AF44: =IFERROR(VLOOKUP(Form_Responses[[#This Row],[Município]],'Regiões Administrativas'!$A$1:$I$646,4,0),"") -> 350780305000001 | AG44: =IFERROR(VLOOKUP(Form_Responses[[#This Row],[Município]],'Regiões Administrativas'!$A$1:$I$646,4,0),"") -> 350780305000001 | AH44: =IFERROR(VLOOKUP(B44,'Regiões Administrativas'!$A$1:$I$646,5,0),"") -> 3507803 | AI44: =IFERROR(VLOOKUP(B44,'Regiões Administrativas'!$A$1:$I$646,6,0),"") -> -47.656398 | AJ44: =IFERROR(VLOOKUP(B44,'Regiões Administrativas'!$A$1:$I$646,8,0),"") -> 863.03352 | AK44: =IFERROR(VLOOKUP(Form_Responses[[#This Row],[Município]],'Regiões Administrativas'!$A$1:$I$646,9,0),"") -> 1J6t\XJ:2{Rp
A45: 46006.392 | B45: TEODORO SAMPAIO | C45: Pontal Paulista | D45: Semana do Patrimônio Histórico | E45: Palestras, visitas na Sede do Parque Estadual Morro do Diabo- Trilha do Mico Leão Preto | F45: Decreto Estadual 60.519/2014 | G45: Rodovia SPV-28 Rubens Crlos Herling, Km 11, Bairro Corrego Seco | H45: sites.google.com/view/sec-turismocultuta | I45: Agosto | J45: 46235 | K45: 46257 | N45: Movimento | O45: Ecoturismo | P45: Social/Cívico/Histórico | Q45: Nehuma das opções acima | R45: Municipal | S45: 1000 | T45: 500 | W45: secretaria de Turismo e Cultura em parceria com a Secretaria da Educação e Gestor do Parque Estadual Morro do Diabo | Y45: turismo@pmteodorosampaio.sp.gov.br | Z45: Deficiência Intelectual | AA45: Banheiro Acessível, Portas Largas para PCR (Pessoa com cadeira de rodas) | AB45: Não possui | AC45: Indicado para maiores de 12 anos | AD45: =IFERROR(VLOOKUP(B45,'Regiões Administrativas'!$A$1:$B$646,2,0),"") -> Presidente Prudente | AE45: =IFERROR(VLOOKUP(Form_Responses[[#This Row],[Município]],'Regiões Administrativas'!$A$1:$I$646,3,0),"") -> 17369 | AF45: =IFERROR(VLOOKUP(Form_Responses[[#This Row],[Município]],'Regiões Administrativas'!$A$1:$I$646,4,0),"") -> 355430005000001 | AG45: =IFERROR(VLOOKUP(Form_Responses[[#This Row],[Município]],'Regiões Administrativas'!$A$1:$I$646,4,0),"") -> 355430005000001 | AH45: =IFERROR(VLOOKUP(B45,'Regiões Administrativas'!$A$1:$I$646,5,0),"") -> 3554300 | AI45: =IFERROR(VLOOKUP(B45,'Regiões Administrativas'!$A$1:$I$646,6,0),"") -> -52.171195 | AJ45: =IFERROR(VLOOKUP(B45,'Regiões Administrativas'!$A$1:$I$646,8,0),"") -> 352.74983 | AK45: =IFERROR(VLOOKUP(Form_Responses[[#This Row],[Município]],'Regiões Administrativas'!$A$1:$I$646,9,0),"") -> 1J6RhG:@,eW>
A46: 46006.396 | B46: BRODOWSKI | C46: Raízes do Campo | D46: 51ª SEMANA DE PORTINARI | E46: A Semana de Portinari que acontece anualmente de 15 a 22 de agosto, foi criada com o decreto nº 7.245, de 09/12/1975, a fim de promover a memória e a obra do artista genial Candido Portinari, filho ilustre de Brodowski e difundir o gosto pela arte. Muitos são os eventos produzidos durante a semana como: Exposição Coletiva de Artes, Pintura Mural, Concurso Artístico e Literário, Desfile Cívico entre outros. | F46: Decreto nº 7.245, de 09/12/1975 | G46: Praça Candido Portinari, 298 - Centro | H46: https://www.museucasadeportinari.org.br/ | I46: Agosto | J46: 46249 | K46: 46257 | L46: 0.375 | M46: 0.95833333 | N46: Festa | O46: Artístico/Cultural/Folclórico | P46: Social/Cívico/Histórico | Q46: Nehuma das opções acima | R46: Internacional | S46: 25000 | T46: 20000 | U46: 18000 | V46: 18000 | W46: Prefeitura Municipal de Brodowski e Museu Casa de Portinari | Y46: turismo@brodowski.sp.gov.br | Z46: Deficiência Fisica, Deficiência Visual, Deficiência Auditiva, Deficiência Intelectual | AA46: Atendimento em Línguas de Sinais, Mapa Tátil, Rampa, Braille, Banheiro Acessível, Portas Largas para PCR (Pessoa com cadeira de rodas) | AB46: Intérprete de Libras no site do evento, Áudio Descrição no site do evento, Legenda no site do evento | AC46: Livre | AD46: =IFERROR(VLOOKUP(B46,'Regiões Administrativas'!$A$1:$B$646,2,0),"") -> Ribeirão Preto | AE46: =IFERROR(VLOOKUP(Form_Responses[[#This Row],[Município]],'Regiões Administrativas'!$A$1:$I$646,3,0),"") -> 15635 | AF46: =IFERROR(VLOOKUP(Form_Responses[[#This Row],[Município]],'Regiões Administrativas'!$A$1:$I$646,4,0),"") -> 350780305000001 | AG46: =IFERROR(VLOOKUP(Form_Responses[[#This Row],[Município]],'Regiões Administrativas'!$A$1:$I$646,4,0),"") -> 350780305000001 | AH46: =IFERROR(VLOOKUP(B46,'Regiões Administrativas'!$A$1:$I$646,5,0),"") -> 3507803 | AI46: =IFERROR(VLOOKUP(B46,'Regiões Administrativas'!$A$1:$I$646,6,0),"") -> -47.656398 | AJ46: =IFERROR(VLOOKUP(B46,'Regiões Administrativas'!$A$1:$I$646,8,0),"") -> 863.03352 | AK46: =IFERROR(VLOOKUP(Form_Responses[[#This Row],[Município]],'Regiões Administrativas'!$A$1:$I$646,9,0),"") -> 1J6t\XJ:2{Rp
A47: 46006.4 | B47: BRODOWSKI | C47: Raízes do Campo | D47: 18ª Piazza Della Nonna | E47: A cidade de Brodowski tem mais da metade de sua população formada por descendentes de imigrantes italianos, faz parte desta contagem a família do ilustre pintor Candido Portinari; no intuito de homenagear toda essa descendência criou-se esta festa tipicamente italiana cujo nome é alusivo à Nonna que no idioma italiano vem a ser, avó. A Piazza Della Nonna (Praça da Avó) realiza-se durante a Semana de Portinari-15 a 22 de agosto. Com comidas típicas, músicas e danças daquele país, Brodowski recebe nas 4 noites do evento cerca de 10.000 visitantes. | G47: Praça Candido Portinari, 298 - Centro | H47: https://www.museucasadeportinari.org.br/ | I47: Agosto | J47: 46254 | K47: 46257 | L47: 0.79166667 | M47: 0 | N47: Festa | O47: Gastronômico | P47: Social/Cívico/Histórico | Q47: Cultura Italiana | R47: Internacional | S47: 15000 | T47: 10000 | U47: 5000 | W47: Prefeitura Municipal de Brodowski e Museu Casa de Portinari | Y47: turismo@brodowski.sp.gov.br | Z47: Deficiência Fisica, Deficiência Visual, Deficiência Auditiva, Deficiência Intelectual | AA47: Mapa Tátil, Rampa, Braille, Banheiro Acessível, Portas Largas para PCR (Pessoa com cadeira de rodas) | AB47: Intérprete de Libras no site do evento, Áudio Descrição no site do evento, Legenda no site do evento | AC47: Livre | AD47: =IFERROR(VLOOKUP(B47,'Regiões Administrativas'!$A$1:$B$646,2,0),"") -> Ribeirão Preto | AE47: =IFERROR(VLOOKUP(Form_Responses[[#This Row],[Município]],'Regiões Administrativas'!$A$1:$I$646,3,0),"") -> 15635 | AF47: =IFERROR(VLOOKUP(Form_Responses[[#This Row],[Município]],'Regiões Administrativas'!$A$1:$I$646,4,0),"") -> 350780305000001 | AG47: =IFERROR(VLOOKUP(Form_Responses[[#This Row],[Município]],'Regiões Administrativas'!$A$1:$I$646,4,0),"") -> 350780305000001 | AH47: =IFERROR(VLOOKUP(B47,'Regiões Administrativas'!$A$1:$I$646,5,0),"") -> 3507803 | AI47: =IFERROR(VLOOKUP(B47,'Regiões Administrativas'!$A$1:$I$646,6,0),"") -> -47.656398 | AJ47: =IFERROR(VLOOKUP(B47,'Regiões Administrativas'!$A$1:$I$646,8,0),"") -> 863.03352 | AK47: =IFERROR(VLOOKUP(Form_Responses[[#This Row],[Município]],'Regiões Administrativas'!$A$1:$I$646,9,0),"") -> 1J6t\XJ:2{Rp
A48: 46006.439 | B48: MESÓPOLIS | C48: Entre Rios | D48: Aniversario de Mesópolis | E48: O aniversário de Mesópolis é uma ocasião crucial para a cidade, pois, além de trazer artistas de renome nacional e valorizar a cultura local, ela impulsiona o turismo e gera um impacto positivo na economia. Essa avaliação demonstra como o evento é fundamental para o desenvolvimento do município em múltiplos aspectos. | G48: Praça Ângela Finasse s/n - centro | H48: https://www.instagram.com/p/DNOB_waxLGc/ | I48: Agosto | J48: 45884 | K48: 45885 | L48: 0.91666667 | M48: 0.16666667 | N48: Aniversário | O48: Artístico/Cultural/Folclórico | P48: Rodeio | Q48: Nehuma das opções acima | R48: Nacional | S48: 7000 | T48: 6000 | U48: 6000 | V48: 6000 | W48: Prefeitura Municipal | Y48: turismo@mesopolis.com.br | Z48: Deficiência Fisica | AA48: Rampa, Banheiro Acessível, Portas Largas para PCR (Pessoa com cadeira de rodas) | AB48: Não possui | AC48: Livre | AD48: =IFERROR(VLOOKUP(B48,'Regiões Administrativas'!$A$1:$B$646,2,0),"") -> São José do Rio Preto | AE48: =IFERROR(VLOOKUP(Form_Responses[[#This Row],[Município]],'Regiões Administrativas'!$A$1:$I$646,3,0),"") -> 16489 | AF48: =IFERROR(VLOOKUP(Form_Responses[[#This Row],[Município]],'Regiões Administrativas'!$A$1:$I$646,4,0),"") -> 352965805000001 | AG48: =IFERROR(VLOOKUP(Form_Responses[[#This Row],[Município]],'Regiões Administrativas'!$A$1:$I$646,4,0),"") -> 352965805000001 | AH48: =IFERROR(VLOOKUP(B48,'Regiões Administrativas'!$A$1:$I$646,5,0),"") -> 3529658 | AI48: =IFERROR(VLOOKUP(B48,'Regiões Administrativas'!$A$1:$I$646,6,0),"") -> -50.62208 | AJ48: =IFERROR(VLOOKUP(B48,'Regiões Administrativas'!$A$1:$I$646,8,0),"") -> 408.60607 | AK48: =IFERROR(VLOOKUP(Form_Responses[[#This Row],[Município]],'Regiões Administrativas'!$A$1:$I$646,9,0),"") -> 1J6R@4z;?*Z>
A49: 46006.445 | B49: TEODORO SAMPAIO | C49: Pontal Paulista | D49: EXPÔ TEODORO 2026 | E49: EXPÔ TEODORO 2025 - Festa tradicional no Município de Teodoro Sampaio-SP, resgatando a originalidade desse evento Montaria em Touro, Cavalgada, Prova de tambor, Praça de alimentação, Shows, Exposição, | G49: Recinto de rodeios Toninho Cowboy - Rua Alberto Amador, 914 | H49: sites.google.com/vieew/sec-turismocultura | I49: Setembro | J49: 46283 | K49: 46285 | L49: 0.85416667 | M49: 0.20833333 | N49: Feira/Exposição/Mostra | O49: Comercial/Promocional | P49: Rodeio | Q49: Nehuma das opções acima | R49: Nacional | S49: 30000 | T49: 20000 | U49: 10000 | W49: Secretaria de Turismo e Cultura, Comissão Organizadora e COMTUR | X49: sites.google.com/vieew/sec-turismocultura | Y49: turismo@pmteodorosampaio.sp.gov.br | Z49: Deficiência Fisica, Deficiência Intelectual | AA49: Rampa, Banheiro Acessível, Portas Largas para PCR (Pessoa com cadeira de rodas) | AB49: Áudio Descrição no site do evento | AC49: Livre | AD49: =IFERROR(VLOOKUP(B49,'Regiões Administrativas'!$A$1:$B$646,2,0),"") -> Presidente Prudente | AE49: =IFERROR(VLOOKUP(Form_Responses[[#This Row],[Município]],'Regiões Administrativas'!$A$1:$I$646,3,0),"") -> 17369 | AF49: =IFERROR(VLOOKUP(Form_Responses[[#This Row],[Município]],'Regiões Administrativas'!$A$1:$I$646,4,0),"") -> 355430005000001 | AG49: =IFERROR(VLOOKUP(Form_Responses[[#This Row],[Município]],'Regiões Administrativas'!$A$1:$I$646,4,0),"") -> 355430005000001 | AH49: =IFERROR(VLOOKUP(B49,'Regiões Administrativas'!$A$1:$I$646,5,0),"") -> 3554300 | AI49: =IFERROR(VLOOKUP(B49,'Regiões Administrativas'!$A$1:$I$646,6,0),"") -> -52.171195 | AJ49: =IFERROR(VLOOKUP(B49,'Regiões Administrativas'!$A$1:$I$646,8,0),"") -> 352.74983 | AK49: =IFERROR(VLOOKUP(Form_Responses[[#This Row],[Município]],'Regiões Administrativas'!$A$1:$I$646,9,0),"") -> 1J6RhG:@,eW>
A50: 46006.467 | B50: TEODORO SAMPAIO | C50: Pontal Paulista | D50: Festa da Padroeira do Brasil. Nossa Senhora Aparecida | E50: Show e quermesse | G50: Rua Pedro Rodrigues nº 735 | I50: Outubro | J50: 46304 | K50: 46033 | L50: 0.79166667 | M50: 0.083333333 | N50: Festa | O50: Religioso | P50: Religioso | Q50: Nehuma das opções acima | R50: Regional | S50: 4000 | T50: 2500 | U50: 2000 | W50: Paroquia Nossa Senhora Aparecida | Y50: paroquiateodorosampaio@hotmail.com | Z50: Deficiência Fisica, Deficiência Intelectual | AA50: Banheiro Acessível, Portas Largas para PCR (Pessoa com cadeira de rodas) | AB50: Não possui | AC50: Livre | AD50: =IFERROR(VLOOKUP(B50,'Regiões Administrativas'!$A$1:$B$646,2,0),"") -> Presidente Prudente | AE50: =IFERROR(VLOOKUP(Form_Responses[[#This Row],[Município]],'Regiões Administrativas'!$A$1:$I$646,3,0),"") -> 17369 | AF50: =IFERROR(VLOOKUP(Form_Responses[[#This Row],[Município]],'Regiões Administrativas'!$A$1:$I$646,4,0),"") -> 355430005000001 | AG50: =IFERROR(VLOOKUP(Form_Responses[[#This Row],[Município]],'Regiões Administrativas'!$A$1:$I$646,4,0),"") -> 355430005000001 | AH50: =IFERROR(VLOOKUP(B50,'Regiões Administrativas'!$A$1:$I$646,5,0),"") -> 3554300 | AI50: =IFERROR(VLOOKUP(B50,'Regiões Administrativas'!$A$1:$I$646,6,0),"") -> -52.171195 | AJ50: =IFERROR(VLOOKUP(B50,'Regiões Administrativas'!$A$1:$I$646,8,0),"") -> 352.74983 | AK50: =IFERROR(VLOOKUP(Form_Responses[[#This Row],[Município]],'Regiões Administrativas'!$A$1:$I$646,9,0),"") -> 1J6RhG:@,eW>
A51: 46006.484 | B51: ITUPEVA | C51: Circuito das Frutas | D51: Festival Gastronômico e Turístico de Itupeva | E51: O festival convida o público a viver momentos inesquecíveis, onde sabores, aromas e cultura se encontram. Almoços e jantares temáticos despertam os sentidos, enquanto aulas e palestras sobre gastronomia e experiências turísticas ampliam o prazer de descobrir. Degustações de cachaças, cervejas artesanais, vinhos e cafés completam a experiência, que ganha ainda mais encanto com apresentações culturais, exposições, shows e roteiros especiais pelas rotas turísticas do município — um verdadeiro convite para sentir, explorar e se apaixonar. | G51: Município de Itupeva consulte os estabelecimentos participantes. | H51: https://itupeva.sp.gov.br | I51: Setembro | J51: 46276 | K51: 46306 | N51: Festival | O51: Gastronômico | P51: Nenhuma das opções acima | Q51: Nehuma das opções acima | R51: Nacional | S51: 10000 | W51: Prefeitura Municipal de Itupeva | Y51: turismo@itupeva.sp.gov.br | Z51: Deficiência Fisica | AA51: Rampa, Banheiro Acessível | AB51: Não possui | AC51: Livre | AD51: =IFERROR(VLOOKUP(B51,'Regiões Administrativas'!$A$1:$B$646,2,0),"") -> Campinas | AE51: =IFERROR(VLOOKUP(Form_Responses[[#This Row],[Município]],'Regiões Administrativas'!$A$1:$I$646,3,0),"") -> 16193 | AF51: =IFERROR(VLOOKUP(Form_Responses[[#This Row],[Município]],'Regiões Administrativas'!$A$1:$I$646,4,0),"") -> 352400605000001 | AG51: =IFERROR(VLOOKUP(Form_Responses[[#This Row],[Município]],'Regiões Administrativas'!$A$1:$I$646,4,0),"") -> 352400605000001 | AH51: =IFERROR(VLOOKUP(B51,'Regiões Administrativas'!$A$1:$I$646,5,0),"") -> 3524006 | AI51: =IFERROR(VLOOKUP(B51,'Regiões Administrativas'!$A$1:$I$646,6,0),"") -> -47.055701 | AJ51: =IFERROR(VLOOKUP(B51,'Regiões Administrativas'!$A$1:$I$646,8,0),"") -> 672.32715 | AK51: =IFERROR(VLOOKUP(Form_Responses[[#This Row],[Município]],'Regiões Administrativas'!$A$1:$I$646,9,0),"") -> 1J6tLR+<QWRf
A52: 46006.501 | B52: ITUPEVA | C52: Circuito das Frutas | D52: Natal Encantado | E52: A magia do Natal ilumina Itupeva com uma programação especial, oferecendo à população uma série de atrações que promovem lazer, encantamento e confraternização. Com atividades para todas as idades, o evento proporciona momentos de alegria e celebração, reforçando o espírito comunitário e as tradições natalinas. Atrações: • Chegada do Papai Noel • Castelo do Papai Noel • Ônibus iluminado gratuito • Neve artificial • Apresentação do Coral CCI • Show de luzes no parque • Show de fogos sem ruído • Túnel iluminado • Personagens temáticos • Brinquedos infláveis, algodão-doce e pipoca gratuitos. | G52: Av. Emílio Checchinato, 706 - Jardim Samambaia, Itupeva SP. | H52: https://www.itupeva.sp.gov.br | I52: Dezembro | J52: 46360 | K52: 46376 | N52: Festa | O52: Religioso | P52: Natal | Q52: Nehuma das opções acima | R52: Nacional | S52: 100000 | U52: 90000 | W52: Prefeitura Municipal de Itupeva | Y52: turismo@itupeva.sp.gov.br | Z52: Deficiência Fisica | AA52: Rampa, Banheiro Acessível | AB52: Não possui | AC52: Livre | AD52: =IFERROR(VLOOKUP(B52,'Regiões Administrativas'!$A$1:$B$646,2,0),"") -> Campinas | AE52: =IFERROR(VLOOKUP(Form_Responses[[#This Row],[Município]],'Regiões Administrativas'!$A$1:$I$646,3,0),"") -> 16193 | AF52: =IFERROR(VLOOKUP(Form_Responses[[#This Row],[Município]],'Regiões Administrativas'!$A$1:$I$646,4,0),"") -> 352400605000001 | AG52: =IFERROR(VLOOKUP(Form_Responses[[#This Row],[Município]],'Regiões Administrativas'!$A$1:$I$646,4,0),"") -> 352400605000001 | AH52: =IFERROR(VLOOKUP(B52,'Regiões Administrativas'!$A$1:$I$646,5,0),"") -> 3524006 | AI52: =IFERROR(VLOOKUP(B52,'Regiões Administrativas'!$A$1:$I$646,6,0),"") -> -47.055701 | AJ52: =IFERROR(VLOOKUP(B52,'Regiões Administrativas'!$A$1:$I$646,8,0),"") -> 672.32715 | AK52: =IFERROR(VLOOKUP(Form_Responses[[#This Row],[Município]],'Regiões Administrativas'!$A$1:$I$646,9,0),"") -> 1J6tLR+<QWRf
A53: 46006.702 | B53: TEODORO SAMPAIO | C53: Pontal Paulista | D53: 3 °Ciclo Turismo de Teodoro Sampaio- SP | E53: Passeio ciclístico realizado a 3 anos consecutivos, na área urbana e ecológica - Sede do parque Estadual Morro do Diabo | G53: Praça Antonio Evangelista da Silva- Praça da prefeitura | I53: Março | K53: 46101 | N53: Campeonato/Torneio/Concurso | O53: Esportivo | P53: Social/Cívico/Histórico | Q53: Nehuma das opções acima | R53: Nacional | S53: 2000 | T53: 1000 | U53: 500 | W53: mountain bike, Secretaria de Turismo e Cultura e Secretaria de Esporte e lazer de Teodoro Sampaio | Y53: turismo@pmteodorosampaio.sp.gov.br | Z53: Não possui | AA53: Banheiro Acessível, Portas Largas para PCR (Pessoa com cadeira de rodas) | AB53: Não possui | AC53: Indicado para maiores de 12 anos | AD53: =IFERROR(VLOOKUP(B53,'Regiões Administrativas'!$A$1:$B$646,2,0),"") -> Presidente Prudente | AE53: =IFERROR(VLOOKUP(Form_Responses[[#This Row],[Município]],'Regiões Administrativas'!$A$1:$I$646,3,0),"") -> 17369 | AF53: =IFERROR(VLOOKUP(Form_Responses[[#This Row],[Município]],'Regiões Administrativas'!$A$1:$I$646,4,0),"") -> 355430005000001 | AG53: =IFERROR(VLOOKUP(Form_Responses[[#This Row],[Município]],'Regiões Administrativas'!$A$1:$I$646,4,0),"") -> 355430005000001 | AH53: =IFERROR(VLOOKUP(B53,'Regiões Administrativas'!$A$1:$I$646,5,0),"") -> 3554300 | AI53: =IFERROR(VLOOKUP(B53,'Regiões Administrativas'!$A$1:$I$646,6,0),"") -> -52.171195 | AJ53: =IFERROR(VLOOKUP(B53,'Regiões Administrativas'!$A$1:$I$646,8,0),"") -> 352.74983 | AK53: =IFERROR(VLOOKUP(Form_Responses[[#This Row],[Município]],'Regiões Administrativas'!$A$1:$I$646,9,0),"") -> 1J6RhG:@,eW>
A54: 46006.716 | B54: TEODORO SAMPAIO | C54: Pontal Paulista | D54: Natal Iluminado 2026 | E54: É um evento Tradicional realizado no mês de dezembro, onde celebra o espirito natalino por meio das luzes, decorações especiais, programação cultural, show ao vivo, praça de alimentação, feira de artesanato, transformando a cidade em um grande cenário festivo para moradores e visitantes. Fomenta as vendas no comercio local. | G54: Praça Antonio Evangelista da Silva, avenida Cuiaba, 1544 | H54: sites.google.com/view/sec-turismocultura | I54: Dezembro | J54: 46357 | K54: 46387 | L54: 0.79166667 | M54: 0.91666667 | N54: Festa | O54: Comercial/Promocional | P54: Natal | Q54: Nehuma das opções acima | R54: Nacional | S54: 15000 | W54: Prefeeitura municipal e Associação Comercial | Y54: turismo@pmteodorosampaio.sp.gov.br | Z54: Deficiência Fisica, Deficiência Auditiva, Deficiência Intelectual | AA54: Banheiro Acessível, Portas Largas para PCR (Pessoa com cadeira de rodas) | AB54: Não possui | AC54: Livre | AD54: =IFERROR(VLOOKUP(B54,'Regiões Administrativas'!$A$1:$B$646,2,0),"") -> Presidente Prudente | AE54: =IFERROR(VLOOKUP(Form_Responses[[#This Row],[Município]],'Regiões Administrativas'!$A$1:$I$646,3,0),"") -> 17369 | AF54: =IFERROR(VLOOKUP(Form_Responses[[#This Row],[Município]],'Regiões Administrativas'!$A$1:$I$646,4,0),"") -> 355430005000001 | AG54: =IFERROR(VLOOKUP(Form_Responses[[#This Row],[Município]],'Regiões Administrativas'!$A$1:$I$646,4,0),"") -> 355430005000001 | AH54: =IFERROR(VLOOKUP(B54,'Regiões Administrativas'!$A$1:$I$646,5,0),"") -> 3554300 | AI54: =IFERROR(VLOOKUP(B54,'Regiões Administrativas'!$A$1:$I$646,6,0),"") -> -52.171195 | AJ54: =IFERROR(VLOOKUP(B54,'Regiões Administrativas'!$A$1:$I$646,8,0),"") -> 352.74983 | AK54: =IFERROR(VLOOKUP(Form_Responses[[#This Row],[Município]],'Regiões Administrativas'!$A$1:$I$646,9,0),"") -> 1J6RhG:@,eW>
A55: 46007.332 | B55: SÃO MANUEL | C55: Cuesta Paulista | D55: Corpus Christi | E55: A Festa de Corpus Christi em São Manuel é uma celebração tradicional com 77 anos de devoção, fé e arte, conhecido pelos belos tapetes e passadeiras coloridos nas ruas, missas, procissão, shows, feiras e praça de alimentação, envolvendo toda a comunidade e atraindo muitos fiéis e turistas para a cidade. | G55: Trajeto de Corpus Christi, que liga o Santuário de Santa Terezinha à Igreja Matriz | H55: https://www.saomanuel.sp.gov.br/ | I55: Junho | J55: 46176 | K55: 46177 | L55: 0.79166667 | M55: 0.95833333 | N55: Festa | O55: Religioso | P55: Corpus Christi | Q55: Nehuma das opções acima | R55: Regional | S55: 20000 | T55: 15000 | W55: Secretaria Municipal de Turismo - Prefeitura Municipal de São Manuel | Y55: turismo@saomanuel.sp.gov.br | Z55: Deficiência Fisica, Deficiência Visual, Deficiência Auditiva, Deficiência Intelectual | AA55: Rampa, Banheiro Acessível | AB55: Intérprete de Libras no site do evento, Áudio Descrição no site do evento, Legenda no site do evento | AC55: Livre | AD55: =IFERROR(VLOOKUP(B55,'Regiões Administrativas'!$A$1:$B$646,2,0),"") -> Sorocaba | AE55: =IFERROR(VLOOKUP(Form_Responses[[#This Row],[Município]],'Regiões Administrativas'!$A$1:$I$646,3,0),"") -> 17188 | AF55: =IFERROR(VLOOKUP(Form_Responses[[#This Row],[Município]],'Regiões Administrativas'!$A$1:$I$646,4,0),"") -> 355010005000001 | AG55: =IFERROR(VLOOKUP(Form_Responses[[#This Row],[Município]],'Regiões Administrativas'!$A$1:$I$646,4,0),"") -> 355010005000001 | AH55: =IFERROR(VLOOKUP(B55,'Regiões Administrativas'!$A$1:$I$646,5,0),"") -> 3550100 | AI55: =IFERROR(VLOOKUP(B55,'Regiões Administrativas'!$A$1:$I$646,6,0),"") -> -48.568763 | AJ55: =IFERROR(VLOOKUP(B55,'Regiões Administrativas'!$A$1:$I$646,8,0),"") -> 733.95771 | AK55: =IFERROR(VLOOKUP(Form_Responses[[#This Row],[Município]],'Regiões Administrativas'!$A$1:$I$646,9,0),"") -> 1J6RuLn*],T-
A56: 46007.348 | B56: SÃO MANUEL | C56: Cuesta Paulista | D56: Festa da Assunção de Nossa Senhora ao Céu | E56: O Santuário Nossa Senhora Aparecida de São Manuel é o mais antigo dedicado à Padroeira do Brasil e o segundo construído no país com este título, concedido em 1913. Celebra a 168ª Festa da Assunção de Nossa Senhora, com início logo na madrugada, com Missas de hora em hora para acolher romeiros e devotos vindos de diversas regiões. Ao fim da tarde, a celebração da Santa Missa Solene de Encerramento reunirá a maior concentração de fiéis, seguida da tradicional Procissão Luminosa com a imagem de Nossa Senhora, que todos os anos leva milhares de pessoas às ruas em clima de profunda devoção. A festa recorda o dogma da Assunção de Maria, no qual a Igreja crê que, ao fim de sua vida terrena, a Mãe de Jesus foi elevada ao Céu em corpo e alma. | G56: Santuário de Aparecida, no Distrito de Aparecida de São Manuel | H56: https://www.facebook.com/santuariodamaeaparecida | I56: Agosto | J56: 46248 | K56: 46249 | L56: 0.20833333 | M56: 0.83333333 | N56: Festa | O56: Religioso | P56: Religioso | Q56: Nehuma das opções acima | R56: Nacional | S56: 20000 | W56: Santuário de Aparecida, de São Manuel | Y56: santuarionossasenhoraaparecida@gmail.com | Z56: Deficiência Fisica, Deficiência Visual, Deficiência Auditiva, Deficiência Intelectual | AA56: Rampa, Banheiro Acessível | AB56: Legenda no site do evento | AC56: Livre | AD56: =IFERROR(VLOOKUP(B56,'Regiões Administrativas'!$A$1:$B$646,2,0),"") -> Sorocaba | AE56: =IFERROR(VLOOKUP(Form_Responses[[#This Row],[Município]],'Regiões Administrativas'!$A$1:$I$646,3,0),"") -> 17188 | AF56: =IFERROR(VLOOKUP(Form_Responses[[#This Row],[Município]],'Regiões Administrativas'!$A$1:$I$646,4,0),"") -> 355010005000001 | AG56: =IFERROR(VLOOKUP(Form_Responses[[#This Row],[Município]],'Regiões Administrativas'!$A$1:$I$646,4,0),"") -> 355010005000001 | AH56: =IFERROR(VLOOKUP(B56,'Regiões Administrativas'!$A$1:$I$646,5,0),"") -> 3550100 | AI56: =IFERROR(VLOOKUP(B56,'Regiões Administrativas'!$A$1:$I$646,6,0),"") -> -48.568763 | AJ56: =IFERROR(VLOOKUP(B56,'Regiões Administrativas'!$A$1:$I$646,8,0),"") -> 733.95771 | AK56: =IFERROR(VLOOKUP(Form_Responses[[#This Row],[Município]],'Regiões Administrativas'!$A$1:$I$646,9,0),"") -> 1J6RuLn*],T-
A57: 46007.385 | B57: CACHOEIRA PAULISTA | C57: Fé | D57: Carnaval das cores | E57: Carnaval das cores , com vários blocos e trio elétrico . | G57: Praça Prado Filho | I57: Fevereiro | J57: 46069 | K57: 46070 | L57: 0.79166667 | M57: 0.083333333 | N57: Desfile | O57: Artístico/Cultural/Folclórico | P57: Carnaval | Q57: Nehuma das opções acima | R57: Regional | S57: 10000 | T57: 10000 | U57: 9000 | W57: Secretaria de Cultura , Turismo e Eventos | X57: Evento gratuito | Y57: culturaeventos@cachoeirapaulista.sp.gov.br | Z57: Deficiência Fisica | AA57: Piso Tátil, Rampa, Banheiro Acessível | AB57: Não possui | AC57: Livre | AD57: =IFERROR(VLOOKUP(B57,'Regiões Administrativas'!$A$1:$B$646,2,0),"") -> São José dos Campos | AE57: =IFERROR(VLOOKUP(Form_Responses[[#This Row],[Município]],'Regiões Administrativas'!$A$1:$I$646,3,0),"") -> 15670 | AF57: =IFERROR(VLOOKUP(Form_Responses[[#This Row],[Município]],'Regiões Administrativas'!$A$1:$I$646,4,0),"") -> 350860305000001 | AG57: =IFERROR(VLOOKUP(Form_Responses[[#This Row],[Município]],'Regiões Administrativas'!$A$1:$I$646,4,0),"") -> 350860305000001 | AH57: =IFERROR(VLOOKUP(B57,'Regiões Administrativas'!$A$1:$I$646,5,0),"") -> 3508603 | AI57: =IFERROR(VLOOKUP(B57,'Regiões Administrativas'!$A$1:$I$646,6,0),"") -> -45.01063 | AJ57: =IFERROR(VLOOKUP(B57,'Regiões Administrativas'!$A$1:$I$646,8,0),"") -> 524.07166 | AK57: =IFERROR(VLOOKUP(Form_Responses[[#This Row],[Município]],'Regiões Administrativas'!$A$1:$I$646,9,0),"") -> 1J6tSHW_@{Tp
A58: 46007.406 | B58: SUD MENNUCCI | C58: Pantanal Paulista | D58: Festa do Peão de Sud Mennucci | E58: É o maior evento da cidade, celebrando o aniversário do município com rodeios em touros, shows de artistas sertanejos renomados, queima do alho tradicional, praça de alimentação e parque de diversões, atraindo público da região com entrada franca em muitas edições, destacando a cultura sertaneja e o turismo local. | G58: R. José Benigo Gomes, 2 - Sud Mennucci, SP, 15360-000 | I58: Setembro | L58: 0.83333333 | M58: 0.125 | N58: Festa | O58: Artístico/Cultural/Folclórico | P58: Rodeio | Q58: Nehuma das opções acima | R58: Regional | S58: 10000 | T58: 0 | U58: 7000 | V58: 6500 | W58: Prefeitura Municipal de Sud Mennucci e COEM - Comissão Organizadora de Eventos | X58: Gratuito | Y58: turismo.meioambiente@sudmennucci.sp.gov.br | Z58: Não possui | AA58: Banheiro Acessível | AB58: Não possui | AC58: Livre | AD58: =IFERROR(VLOOKUP(B58,'Regiões Administrativas'!$A$1:$B$646,2,0),"") -> Araçatuba | AE58: =IFERROR(VLOOKUP(Form_Responses[[#This Row],[Município]],'Regiões Administrativas'!$A$1:$I$646,3,0),"") -> 17317 | AF58: =IFERROR(VLOOKUP(Form_Responses[[#This Row],[Município]],'Regiões Administrativas'!$A$1:$I$646,4,0),"") -> 355230405000001 | AG58: =IFERROR(VLOOKUP(Form_Responses[[#This Row],[Município]],'Regiões Administrativas'!$A$1:$I$646,4,0),"") -> 355230405000001 | AH58: =IFERROR(VLOOKUP(B58,'Regiões Administrativas'!$A$1:$I$646,5,0),"") -> 3552304 | AI58: =IFERROR(VLOOKUP(B58,'Regiões Administrativas'!$A$1:$I$646,6,0),"") -> -50.920527 | AJ58: =IFERROR(VLOOKUP(B58,'Regiões Administrativas'!$A$1:$I$646,8,0),"") -> 376.22166 | AK58: =IFERROR(VLOOKUP(Form_Responses[[#This Row],[Município]],'Regiões Administrativas'!$A$1:$I$646,9,0),"") -> 1J6R+_TAy1mp
A59: 46007.411 | B59: SUD MENNUCCI | C59: Pantanal Paulista | D59: CAMPEONATO DE PESCA ESPORTIVA | E59: O Campeonato de Pesca Esportiva de Sud Mennucci, conhecido como TUCUNASUD, é um evento anual que atrai pescadores de todo o Brasil para o Rio Tietê, focando no Tucunaré e também com categorias para caiaque, promovendo o turismo local e a preservação ambiental com a prática "pesque e solte". A competição ocorre geralmente nos Quiosques Públicos (Recanto das Águas) e envolve premiações, estrutura para famílias e uma atmosfera competitiva, destacando a cidade como polo da pesca esportiva. | G59: Sitio Santo Antonio - Cateto, Sud Mennucci - SP, 15360-000 | I59: Abril | N59: Campeonato/Torneio/Concurso | O59: Pesca e Náutico | P59: Nenhuma das opções acima | Q59: Nehuma das opções acima | R59: Nacional | S59: 1000 | T59: 0 | U59: 1500 | V59: 1000 | W59: Prefeitura Municipal de Sud Mennucci e a Comissão de Pescadores | X59: Gratuito o evento e o valor da inscrição é estipulado quando lançado o torneio. | Y59: turismo.meioambiente@sudmennucci.sp.gov.br | Z59: Deficiência Fisica | AA59: Banheiro Acessível | AB59: Não possui | AC59: Livre | AD59: =IFERROR(VLOOKUP(B59,'Regiões Administrativas'!$A$1:$B$646,2,0),"") -> Araçatuba | AE59: =IFERROR(VLOOKUP(Form_Responses[[#This Row],[Município]],'Regiões Administrativas'!$A$1:$I$646,3,0),"") -> 17317 | AF59: =IFERROR(VLOOKUP(Form_Responses[[#This Row],[Município]],'Regiões Administrativas'!$A$1:$I$646,4,0),"") -> 355230405000001 | AG59: =IFERROR(VLOOKUP(Form_Responses[[#This Row],[Município]],'Regiões Administrativas'!$A$1:$I$646,4,0),"") -> 355230405000001 | AH59: =IFERROR(VLOOKUP(B59,'Regiões Administrativas'!$A$1:$I$646,5,0),"") -> 3552304 | AI59: =IFERROR(VLOOKUP(B59,'Regiões Administrativas'!$A$1:$I$646,6,0),"") -> -50.920527 | AJ59: =IFERROR(VLOOKUP(B59,'Regiões Administrativas'!$A$1:$I$646,8,0),"") -> 376.22166 | AK59: =IFERROR(VLOOKUP(Form_Responses[[#This Row],[Município]],'Regiões Administrativas'!$A$1:$I$646,9,0),"") -> 1J6R+_TAy1mp
A60: 46007.422 | B60: SUD MENNUCCI | C60: Pantanal Paulista | D60: CARNA SUD | E60: O Carna Sud é uma celebração popular realizada tradicionalmente na Praça da Matriz, reunindo um público regional diversificado, com apresentações de blocos carnavalescos e shows musicais, promovendo lazer, integração social e a valorização das tradições locais. | G60: Praça da Matriz de Sud Mennucci | I60: Fevereiro | L60: 0.91666667 | M60: 0.91666667 | N60: Festa | O60: Artístico/Cultural/Folclórico | P60: Carnaval | Q60: Nehuma das opções acima | R60: Regional | S60: 2000 | T60: 1000 | U60: 2000 | V60: 2000 | W60: Prefeitura Municipal de Sud Mennucci e COMTUR - Conselho Municipal de Turismo | X60: Gratuito | Y60: turismo.meioambiente@sudmennucci.sp.gov.br | Z60: Deficiência Fisica | AA60: Não possui | AB60: Não possui | AC60: Livre | AD60: =IFERROR(VLOOKUP(B60,'Regiões Administrativas'!$A$1:$B$646,2,0),"") -> Araçatuba | AE60: =IFERROR(VLOOKUP(Form_Responses[[#This Row],[Município]],'Regiões Administrativas'!$A$1:$I$646,3,0),"") -> 17317 | AF60: =IFERROR(VLOOKUP(Form_Responses[[#This Row],[Município]],'Regiões Administrativas'!$A$1:$I$646,4,0),"") -> 355230405000001 | AG60: =IFERROR(VLOOKUP(Form_Responses[[#This Row],[Município]],'Regiões Administrativas'!$A$1:$I$646,4,0),"") -> 355230405000001 | AH60: =IFERROR(VLOOKUP(B60,'Regiões Administrativas'!$A$1:$I$646,5,0),"") -> 3552304 | AI60: =IFERROR(VLOOKUP(B60,'Regiões Administrativas'!$A$1:$I$646,6,0),"") -> -50.920527 | AJ60: =IFERROR(VLOOKUP(B60,'Regiões Administrativas'!$A$1:$I$646,8,0),"") -> 376.22166 | AK60: =IFERROR(VLOOKUP(Form_Responses[[#This Row],[Município]],'Regiões Administrativas'!$A$1:$I$646,9,0),"") -> 1J6R+_TAy1mp
A61: 46007.425 | B61: SUD MENNUCCI | C61: Pantanal Paulista | D61: Escolha da Rainha de Sud Mennucci | E61: A Escolha da Rainha de Sud Mennucci é um evento tradicional ligado à Festa do Peão do município, onde candidatas locais concorrem ao título em um baile, com a vencedora (como Paula Daniele em uma edição recente) sendo coroada para representar a festa e a cidade, um evento que envolve desfiles, patrocinadores e a organização da COEM (Comissão Organizadora de Eventos Municipais). | G61: Pavilhão de Eventos do Recinto de Exposições de Sud Mennucci | I61: Agosto | L61: 0.83333333 | N61: Desfile | O61: Artístico/Cultural/Folclórico | P61: Rodeio | Q61: Nehuma das opções acima | R61: Regional | S61: 2000 | T61: 0 | U61: 2200 | V61: 2200 | W61: Prefeitura Municipal de Sud Mennucci e COEM | X61: Gratuito | Y61: turismo.meioambiente@sudmennucci.sp.gov.br | Z61: Não possui | AA61: Não possui | AB61: Não possui | AC61: Livre | AD61: =IFERROR(VLOOKUP(B61,'Regiões Administrativas'!$A$1:$B$646,2,0),"") -> Araçatuba | AE61: =IFERROR(VLOOKUP(Form_Responses[[#This Row],[Município]],'Regiões Administrativas'!$A$1:$I$646,3,0),"") -> 17317 | AF61: =IFERROR(VLOOKUP(Form_Responses[[#This Row],[Município]],'Regiões Administrativas'!$A$1:$I$646,4,0),"") -> 355230405000001 | AG61: =IFERROR(VLOOKUP(Form_Responses[[#This Row],[Município]],'Regiões Administrativas'!$A$1:$I$646,4,0),"") -> 355230405000001 | AH61: =IFERROR(VLOOKUP(B61,'Regiões Administrativas'!$A$1:$I$646,5,0),"") -> 3552304 | AI61: =IFERROR(VLOOKUP(B61,'Regiões Administrativas'!$A$1:$I$646,6,0),"") -> -50.920527 | AJ61: =IFERROR(VLOOKUP(B61,'Regiões Administrativas'!$A$1:$I$646,8,0),"") -> 376.22166 | AK61: =IFERROR(VLOOKUP(Form_Responses[[#This Row],[Município]],'Regiões Administrativas'!$A$1:$I$646,9,0),"") -> 1J6R+_TAy1mp
A62: 46007.635 | B62: AREALVA | C62: Caminhos do Tietê | D62: CARNAVAL: DE VOLTA ÀS RAIZES | E62: EVENTO POPULAR TRADICIONAL, REALIZADO NA PRAIA MUNICIPAL, REPORTA AO APELO POPULAR DE MOMENTOS DE LAZER ONDE TODA A FAMÍLIA POSSA USUFUIR DAS FESTIVIDADES DO CARNAVAL COM MUITA MÚSICA E APRESENTAÇÕES DE BLOCOS E FOLIÕES. GERALMENTE É COMPOSTO POR APRESENTAÇÃO MUSICAL (BANDA E DJ) EM TRIO ELÉTRICO. | G62: PRAIA MUNICIPAL PREFEITO JOSÉ RUIZ | I62: Fevereiro | J62: 46067 | K62: 46070 | L62: 0.875 | M62: 0.125 | N62: Festa | O62: Artístico/Cultural/Folclórico | P62: Carnaval | Q62: Nehuma das opções acima | R62: Regional | S62: 2000 | T62: 0 | U62: 0 | V62: 0 | W62: PREFEITURA MUNICIPAL DE AREALVA | Y62: turismo@arealva.sp.gov.br | Z62: Não possui | AA62: Banheiro Acessível, Outro: | AB62: Não possui | AC62: Indicado para maiores de 18 anos | AD62: =IFERROR(VLOOKUP(B62,'Regiões Administrativas'!$A$1:$B$646,2,0),"") -> Bauru | AE62: =IFERROR(VLOOKUP(Form_Responses[[#This Row],[Município]],'Regiões Administrativas'!$A$1:$I$646,3,0),"") -> 15458 | AF62: =IFERROR(VLOOKUP(Form_Responses[[#This Row],[Município]],'Regiões Administrativas'!$A$1:$I$646,4,0),"") -> 350340605000001 | AG62: =IFERROR(VLOOKUP(Form_Responses[[#This Row],[Município]],'Regiões Administrativas'!$A$1:$I$646,4,0),"") -> 350340605000001 | AH62: =IFERROR(VLOOKUP(B62,'Regiões Administrativas'!$A$1:$I$646,5,0),"") -> 3503406 | AI62: =IFERROR(VLOOKUP(B62,'Regiões Administrativas'!$A$1:$I$646,6,0),"") -> -48.920415 | AJ62: =IFERROR(VLOOKUP(B62,'Regiões Administrativas'!$A$1:$I$646,8,0),"") -> 447.9803 | AK62: =IFERROR(VLOOKUP(Form_Responses[[#This Row],[Município]],'Regiões Administrativas'!$A$1:$I$646,9,0),"") -> 1J6RtrA4O2jf
A63: 46007.644 | B63: SANTANA DE PARNAÍBA | C63: Roteiro dos Bandeirantes | D63: FOLIA DE REIS | E63: Encerramento das festividades natalinas. No dia 06 de janeiro - Dia de Reis, é realizado o evento com apresentação de grupo folclórico que resgata a tradição da Folia de Reis, com encenação teatral, apresentação de bonecões, levantamento de mastro com pedidos, danças e muita música. | G63: Praça 14 de Novembro - Centro Histórico - Santana de Parnaíba | H63: https://prefeitura.santanadeparnaiba.sp.gov.br/Plataforma/smct/eventos | I63: Janeiro | J63: 46028 | L63: 0.83333333 | N63: Festa | O63: Artístico/Cultural/Folclórico | P63: Nenhuma das opções acima | Q63: Nehuma das opções acima | R63: Regional | S63: 1000 | T63: 1000 | U63: 1000 | V63: 1000 | W63: Secretaria Municipal de Cultura e Turismo de Santana de Parnaíba | Y63: smct@santanadeparnaiba.sp.gov.br | Z63: Deficiência Fisica | AA63: Piso Tátil, Rampa | AB63: Não possui | AC63: Livre | AD63: =IFERROR(VLOOKUP(B63,'Regiões Administrativas'!$A$1:$B$646,2,0),"") -> RMSP | AE63: =IFERROR(VLOOKUP(Form_Responses[[#This Row],[Município]],'Regiões Administrativas'!$A$1:$I$646,3,0),"") -> 17098 | AF63: =IFERROR(VLOOKUP(Form_Responses[[#This Row],[Município]],'Regiões Administrativas'!$A$1:$I$646,4,0),"") -> 354730405000001 | AG63: =IFERROR(VLOOKUP(Form_Responses[[#This Row],[Município]],'Regiões Administrativas'!$A$1:$I$646,4,0),"") -> 354730405000001 | AH63: =IFERROR(VLOOKUP(B63,'Regiões Administrativas'!$A$1:$I$646,5,0),"") -> 3547304 | AI63: =IFERROR(VLOOKUP(B63,'Regiões Administrativas'!$A$1:$I$646,6,0),"") -> -46.922092 | AJ63: =IFERROR(VLOOKUP(B63,'Regiões Administrativas'!$A$1:$I$646,8,0),"") -> 769.83484 | AK63: =IFERROR(VLOOKUP(Form_Responses[[#This Row],[Município]],'Regiões Administrativas'!$A$1:$I$646,9,0),"") -> 1J6tM7.wP3d>
A64: 46007.65 | B64: SANTANA DE PARNAÍBA | C64: Roteiro dos Bandeirantes | D64: CARNAVAL | E64: Em Santana de Parnaíba, Carnaval é festa de rua. Tradicionalmente, os moradores e visitantes caem na folia do Centro Histórico. O Grito da Noite, manifestação secular, marca a abertura do carnaval parnaibano (sexta-feira). Nos demais dias de festa temos os tradicionais blocos com vasta programação, que inclusive já antecedem o Carnaval. | F64: LEI Nº 11.140, DE 24 DE ABRIL DE 2002 | G64: CENTRO HISTÓRICO | H64: https://prefeitura.santanadeparnaiba.sp.gov.br/Plataforma/smct/eventos | I64: Fevereiro | J64: 46066 | K64: 46070 | N64: Festa | O64: Artístico/Cultural/Folclórico | P64: Carnaval | Q64: Nehuma das opções acima | R64: Regional | S64: 30000 | T64: 30000 | U64: 30000 | W64: SECRETARIA MUNICIPAL DE CULTURA E TURISMO DE SANTANA DE PARNAÍBA | Y64: smct@santanadeparnaiba.sp.gov.br | Z64: Não possui | AA64: Não possui | AB64: Não possui | AC64: Livre | AD64: =IFERROR(VLOOKUP(B64,'Regiões Administrativas'!$A$1:$B$646,2,0),"") -> RMSP | AE64: =IFERROR(VLOOKUP(Form_Responses[[#This Row],[Município]],'Regiões Administrativas'!$A$1:$I$646,3,0),"") -> 17098 | AF64: =IFERROR(VLOOKUP(Form_Responses[[#This Row],[Município]],'Regiões Administrativas'!$A$1:$I$646,4,0),"") -> 354730405000001 | AG64: =IFERROR(VLOOKUP(Form_Responses[[#This Row],[Município]],'Regiões Administrativas'!$A$1:$I$646,4,0),"") -> 354730405000001 | AH64: =IFERROR(VLOOKUP(B64,'Regiões Administrativas'!$A$1:$I$646,5,0),"") -> 3547304 | AI64: =IFERROR(VLOOKUP(B64,'Regiões Administrativas'!$A$1:$I$646,6,0),"") -> -46.922092 | AJ64: =IFERROR(VLOOKUP(B64,'Regiões Administrativas'!$A$1:$I$646,8,0),"") -> 769.83484 | AK64: =IFERROR(VLOOKUP(Form_Responses[[#This Row],[Município]],'Regiões Administrativas'!$A$1:$I$646,9,0),"") -> 1J6tM7.wP3d>
A65: 46007.897 | B65: RUBINÉIA | C65: Entre Rios | D65: 1º Torneio Familia | E65: Campeonato de pesca, onde os trios tem que ser da mesma familia, exemplo, pais, filhos, tios, primos e sobrinhos | G65: Praia do Sol | I65: Janeiro | J65: 46046 | K65: 46046 | L65: 0.29166667 | M65: 0.99930556 | N65: Campeonato/Torneio/Concurso | O65: Pesca e Náutico | P65: Nenhuma das opções acima | Q65: Nehuma das opções acima | R65: Nacional | S65: 2500 | W65: Casa Esporte Camping | Y65: turismo@rubineia.sp.gov.br | Z65: Deficiência Fisica, Deficiência Intelectual | AA65: Rampa, Banheiro Acessível, Portas Largas para PCR (Pessoa com cadeira de rodas), Outro: | AB65: Não possui | AC65: Livre | AD65: =IFERROR(VLOOKUP(B65,'Regiões Administrativas'!$A$1:$B$646,2,0),"") -> São José do Rio Preto | AE65: =IFERROR(VLOOKUP(Form_Responses[[#This Row],[Município]],'Regiões Administrativas'!$A$1:$I$646,3,0),"") -> 16991 | AF65: =IFERROR(VLOOKUP(Form_Responses[[#This Row],[Município]],'Regiões Administrativas'!$A$1:$I$646,4,0),"") -> 354450905000001 | AG65: =IFERROR(VLOOKUP(Form_Responses[[#This Row],[Município]],'Regiões Administrativas'!$A$1:$I$646,4,0),"") -> 354450905000001 | AH65: =IFERROR(VLOOKUP(B65,'Regiões Administrativas'!$A$1:$I$646,5,0),"") -> 3544509 | AI65: =IFERROR(VLOOKUP(B65,'Regiões Administrativas'!$A$1:$I$646,6,0),"") -> -50.997485 | AJ65: =IFERROR(VLOOKUP(B65,'Regiões Administrativas'!$A$1:$I$646,8,0),"") -> 343.1479 | AK65: =IFERROR(VLOOKUP(Form_Responses[[#This Row],[Município]],'Regiões Administrativas'!$A$1:$I$646,9,0),"") -> 1J6R@gTOiZS>
A66: 46008.385 | B66: SANTANA DE PARNAÍBA | C66: Roteiro dos Bandeirantes | D66: DRAMA DA PAIXÃO | E66: Na Semana Santa (02, 03 e 04 de abril de 2026), com mais de 30 anos de tradição, acontece a encenação teatral conhecida como Drama da Paixão, um espetáculo consagrado como um dos maiores do Brasil, que retrata a trajetória do nascimento, da vida, da morte e da ressurreição de Jesus Cristo. O espetáculo revive uma das histórias mais emocionantes da humanidade e, a cada ano, apresenta uma passagem bíblica diferente, o que o torna sempre inédito. Ambientado em um espaço cenográfico de 15.000 m², o evento mobiliza mais de 1.000 pessoas, entre atores e equipe de produção. | F66: LEI Nº 11.141, DE 24 DE ABRIL DE 2002 | G66: Barragem Edgard de Souza - Estrada dos Romeiros, km 40 | H66: https://prefeitura.santanadeparnaiba.sp.gov.br/Plataforma/smct/eventos | I66: Abril | J66: 46114 | K66: 46116 | L66: 0.83333333 | N66: Festa | O66: Religioso | P66: Páscoa | Q66: Nehuma das opções acima | R66: Regional | S66: 35000 | T66: 30000 | U66: 30000 | V66: 30000 | W66: SECRETARIA MUNICIPAL DE CULTURA E TURISMO DE SANTANA DE PARNAÍBA | Y66: smct@santanadeparnaiba.sp.gov.br | Z66: Deficiência Fisica | AA66: Rampa, Banheiro Acessível | AB66: Não possui | AC66: Livre | AD66: =IFERROR(VLOOKUP(B66,'Regiões Administrativas'!$A$1:$B$646,2,0),"") -> RMSP | AE66: =IFERROR(VLOOKUP(Form_Responses[[#This Row],[Município]],'Regiões Administrativas'!$A$1:$I$646,3,0),"") -> 17098 | AF66: =IFERROR(VLOOKUP(Form_Responses[[#This Row],[Município]],'Regiões Administrativas'!$A$1:$I$646,4,0),"") -> 354730405000001 | AG66: =IFERROR(VLOOKUP(Form_Responses[[#This Row],[Município]],'Regiões Administrativas'!$A$1:$I$646,4,0),"") -> 354730405000001 | AH66: =IFERROR(VLOOKUP(B66,'Regiões Administrativas'!$A$1:$I$646,5,0),"") -> 3547304 | AI66: =IFERROR(VLOOKUP(B66,'Regiões Administrativas'!$A$1:$I$646,6,0),"") -> -46.922092 | AJ66: =IFERROR(VLOOKUP(B66,'Regiões Administrativas'!$A$1:$I$646,8,0),"") -> 769.83484 | AK66: =IFERROR(VLOOKUP(Form_Responses[[#This Row],[Município]],'Regiões Administrativas'!$A$1:$I$646,9,0),"") -> 1J6tM7.wP3d>
A67: 46008.387 | B67: SANTANA DE PARNAÍBA | C67: Roteiro dos Bandeirantes | D67: DRAMA DA PAIXÃO | E67: Na Semana Santa (02, 03 e 04 de abril de 2026), com mais de 30 anos de tradição, acontece a encenação teatral conhecida como Drama da Paixão, um espetáculo consagrado como um dos maiores do Brasil, que retrata a trajetória do nascimento, da vida, da morte e da ressurreição de Jesus Cristo. O espetáculo revive uma das histórias mais emocionantes da humanidade e, a cada ano, apresenta uma passagem bíblica diferente, o que o torna sempre inédito. Ambientado em um espaço cenográfico de 15.000 m², o evento mobiliza mais de 1.000 pessoas, entre atores e equipe de produção. | F67: LEI Nº 11.141, DE 24 DE ABRIL DE 2002 | G67: Barragem Edgard de Souza - Estrada dos Romeiros, km 40 | H67: https://prefeitura.santanadeparnaiba.sp.gov.br/Plataforma/smct/eventos | I67: Abril | J67: 46114 | K67: 46116 | L67: 0.83333333 | N67: Festa | O67: Religioso | P67: Páscoa | Q67: Nehuma das opções acima | R67: Regional | S67: 35000 | T67: 30000 | U67: 30000 | V67: 30000 | W67: SECRETARIA MUNICIPAL DE CULTURA E TURISMO DE SANTANA DE PARNAÍBA | Y67: smct@santanadeparnaiba.sp.gov.br | Z67: Deficiência Fisica | AA67: Rampa, Banheiro Acessível | AB67: Não possui | AC67: Livre | AD67: =IFERROR(VLOOKUP(B67,'Regiões Administrativas'!$A$1:$B$646,2,0),"") -> RMSP | AE67: =IFERROR(VLOOKUP(Form_Responses[[#This Row],[Município]],'Regiões Administrativas'!$A$1:$I$646,3,0),"") -> 17098 | AF67: =IFERROR(VLOOKUP(Form_Responses[[#This Row],[Município]],'Regiões Administrativas'!$A$1:$I$646,4,0),"") -> 354730405000001 | AG67: =IFERROR(VLOOKUP(Form_Responses[[#This Row],[Município]],'Regiões Administrativas'!$A$1:$I$646,4,0),"") -> 354730405000001 | AH67: =IFERROR(VLOOKUP(B67,'Regiões Administrativas'!$A$1:$I$646,5,0),"") -> 3547304 | AI67: =IFERROR(VLOOKUP(B67,'Regiões Administrativas'!$A$1:$I$646,6,0),"") -> -46.922092 | AJ67: =IFERROR(VLOOKUP(B67,'Regiões Administrativas'!$A$1:$I$646,8,0),"") -> 769.83484 | AK67: =IFERROR(VLOOKUP(Form_Responses[[#This Row],[Município]],'Regiões Administrativas'!$A$1:$I$646,9,0),"") -> 1J6tM7.wP3d>
A68: 46008.397 | B68: SANTANA DE PARNAÍBA | C68: Roteiro dos Bandeirantes | D68: CORPUS CHRISTI | E68: No feriado de Corpus Christi, Santana de Parnaíba transforma as ruas do Centro Histórico em um grande cenário de fé e arte com a confecção dos tradicionais tapetes de serragem, que atraem milhares de fiéis e visitantes. Considerado uma das maiores manifestações religiosas do Estado de São Paulo, o evento encanta pelas ilustrações de motivos religiosos, que impressionam pelo capricho, riqueza de detalhes e perfeição artística. Os tapetes são confeccionados com serragem colorida, pó de café e casca de ovo, cobrindo as ruas históricas da cidade. Ao longo do dia, são celebradas missas, culminando com a tradicional procissão no fim da tarde. O evento também conta com praça de alimentação e barracas de artes e artesanato, proporcionando uma experiência completa de fé, cultura e convivência comunitária | G68: Centro Histórico | H68: https://prefeitura.santanadeparnaiba.sp.gov.br/Plataforma/smct/eventos | I68: Junho | J68: 46177 | K68: 46177 | L68: 0.25 | N68: Festa | O68: Religioso | P68: Corpus Christi | Q68: Nehuma das opções acima | R68: Regional | S68: 30000 | T68: 30000 | U68: 30000 | V68: 30000 | W68: SECRETARIA MUNICIPAL DE CULTURA E TURISMO DE SANTANA DE PARNAÍBA | Y68: smct@santanadeparnaiba.sp.gov.br | Z68: Não possui | AA68: Não possui | AB68: Não possui | AC68: Livre | AD68: =IFERROR(VLOOKUP(B68,'Regiões Administrativas'!$A$1:$B$646,2,0),"") -> RMSP | AE68: =IFERROR(VLOOKUP(Form_Responses[[#This Row],[Município]],'Regiões Administrativas'!$A$1:$I$646,3,0),"") -> 17098 | AF68: =IFERROR(VLOOKUP(Form_Responses[[#This Row],[Município]],'Regiões Administrativas'!$A$1:$I$646,4,0),"") -> 354730405000001 | AG68: =IFERROR(VLOOKUP(Form_Responses[[#This Row],[Município]],'Regiões Administrativas'!$A$1:$I$646,4,0),"") -> 354730405000001 | AH68: =IFERROR(VLOOKUP(B68,'Regiões Administrativas'!$A$1:$I$646,5,0),"") -> 3547304 | AI68: =IFERROR(VLOOKUP(B68,'Regiões Administrativas'!$A$1:$I$646,6,0),"") -> -46.922092 | AJ68: =IFERROR(VLOOKUP(B68,'Regiões Administrativas'!$A$1:$I$646,8,0),"") -> 769.83484 | AK68: =IFERROR(VLOOKUP(Form_Responses[[#This Row],[Município]],'Regiões Administrativas'!$A$1:$I$646,9,0),"") -> 1J6tM7.wP3d>
A69: 46008.413 | B69: SANTANA DE PARNAÍBA | C69: Roteiro dos Bandeirantes | D69: Encontro de Antigomobilismo | E69: Em julho é promovido o Encontro de Antigomobilismo. As ruas do Centro Histórico são ocupadas por centenas de veículos antigos. É possível através desses automóveis clássicos, ver a evolução dos carros na história, raridades que marcaram gerações, presentes nas décadas de 1950, 1960, 1970 e 1980, além de caminhões e jeeps do exército. No evento, mercado de pulgas e barracas de artesanato e alimentação. Shows de rock e rockabilly na programação musical. | G69: Centro Histórico | H69: https://prefeitura.santanadeparnaiba.sp.gov.br/Plataforma/smct/eventos | I69: Julho | J69: 46215 | K69: 46215 | L69: 0.41666667 | N69: Festival | O69: Artístico/Cultural/Folclórico | P69: Nenhuma das opções acima | Q69: Nehuma das opções acima | R69: Regional | S69: 20000 | T69: 20000 | U69: 20000 | V69: 20000 | W69: SECRETARIA MUNICIPAL DE CULTURA E TURISMO DE SANTANA DE PARNAÍBA | Y69: SECRETARIA MUNICIPAL DE CULTURA E TURISMO DE SANTANA DE PARNAÍBA | Z69: Deficiência Fisica | AA69: Rampa, Banheiro Acessível | AB69: Não possui | AC69: Livre | AD69: =IFERROR(VLOOKUP(B69,'Regiões Administrativas'!$A$1:$B$646,2,0),"") -> RMSP | AE69: =IFERROR(VLOOKUP(Form_Responses[[#This Row],[Município]],'Regiões Administrativas'!$A$1:$I$646,3,0),"") -> 17098 | AF69: =IFERROR(VLOOKUP(Form_Responses[[#This Row],[Município]],'Regiões Administrativas'!$A$1:$I$646,4,0),"") -> 354730405000001 | AG69: =IFERROR(VLOOKUP(Form_Responses[[#This Row],[Município]],'Regiões Administrativas'!$A$1:$I$646,4,0),"") -> 354730405000001 | AH69: =IFERROR(VLOOKUP(B69,'Regiões Administrativas'!$A$1:$I$646,5,0),"") -> 3547304 | AI69: =IFERROR(VLOOKUP(B69,'Regiões Administrativas'!$A$1:$I$646,6,0),"") -> -46.922092 | AJ69: =IFERROR(VLOOKUP(B69,'Regiões Administrativas'!$A$1:$I$646,8,0),"") -> 769.83484 | AK69: =IFERROR(VLOOKUP(Form_Responses[[#This Row],[Município]],'Regiões Administrativas'!$A$1:$I$646,9,0),"") -> 1J6tM7.wP3d>
A70: 46008.414 | B70: OLÍMPIA | C70: Águas Sertanejas | D70: Juninão de São João Batista | E70: A tradicional festa junina toma conta da Praça da Matriz “Monsenhor Antônio”, no coração da Estância Turística de Olímpia. Entre os dias 19 e 23 de junho, acontece o Juninão de São João, evento realizado pela Paróquia São João Batista, em parceria com a Prefeitura de Olímpia, por meio da Secretaria de Cultura e Defesa do Folclore. Durante todas as noites, moradores e visitantes poderão saborear uma grande variedade de comidas típicas, como kafta, pastel, caldos, milho verde e a tradicional barraca do vinho do Rotary Club, além de outras bebidas e quitutes. O público também poderá aproveitar uma programação cultural gratuita, garantindo diversão para toda a família. | G70: PRAÇA DA MATRIZ “MONSENHOR ANTÔNIO SANTCLIMENTS TORRAS | H70: olimpia.sp.gov.br | I70: Junho | J70: 46192 | K70: 46196 | L70: 0.75 | M70: 0.99930556 | N70: Festa | O70: Religioso | P70: Festa Junina | Q70: Nehuma das opções acima | R70: Municipal | S70: 10000 | T70: 10000 | U70: 10000 | V70: 10000 | W70: Paróquia de São João Batista em parceira com a Prefeitura da Estância Turística de Olímpia | Y70: prefeitura@olimpia.sp.gov.br | Z70: Deficiência Fisica | AA70: Rampa, Banheiro Acessível, Balcão de atendimento com altura reduzida, Portas Largas para PCR (Pessoa com cadeira de rodas) | AB70: Áudio Descrição no site do evento | AC70: Livre | AD70: =IFERROR(VLOOKUP(B70,'Regiões Administrativas'!$A$1:$B$646,2,0),"") -> Barretos | AE70: =IFERROR(VLOOKUP(Form_Responses[[#This Row],[Município]],'Regiões Administrativas'!$A$1:$I$646,3,0),"") -> 16671 | AF70: =IFERROR(VLOOKUP(Form_Responses[[#This Row],[Município]],'Regiões Administrativas'!$A$1:$I$646,4,0),"") -> 353390805000001 | AG70: =IFERROR(VLOOKUP(Form_Responses[[#This Row],[Município]],'Regiões Administrativas'!$A$1:$I$646,4,0),"") -> 353390805000001 | AH70: =IFERROR(VLOOKUP(B70,'Regiões Administrativas'!$A$1:$I$646,5,0),"") -> 3533908 | AI70: =IFERROR(VLOOKUP(B70,'Regiões Administrativas'!$A$1:$I$646,6,0),"") -> -48.913492 | AJ70: =IFERROR(VLOOKUP(B70,'Regiões Administrativas'!$A$1:$I$646,8,0),"") -> 500.31554 | AK70: =IFERROR(VLOOKUP(Form_Responses[[#This Row],[Município]],'Regiões Administrativas'!$A$1:$I$646,9,0),"") -> 1J6RdQ4;ieE-
A71: 46008.415 | B71: IGUAPE | C71: Lagamar | D71: Festa em Louvor ao Senhor Bom Jesus de Iguape | E71: A Festa do Senhor Bom Jesus de Iguape, que em 2025 completa 378 anos de história (iniciada em 1647), é uma das celebrações religiosas mais antigas e tradicionais do Brasil. O evento ocorre anualmente entre 28 de julho e 6 de agosto no município de Iguape. Principais Características da Festa: Significado Religioso: Celebra o encontro da imagem do Senhor Bom Jesus de Iguape por indígenas na Praia do Leste em 1647. O ápice ocorre em 6 de agosto, considerado um dia santo e milagroso pelos fiéis. Romarias e Procissões: Atrai milhares de devotos (estimados em 250 mil em edições recentes) que realizam caminhadas de fé, como a romarias com a duração de dias na estrada para a conclusão do percurso até Iguape, sendo estas realizadas principalmente a cavalo e a pé. A procissão solene pelas ruas da cidade com a imagem original do Senhor Bom Jesus de Iguape e Nossa Senhora das Neves realizadas nos dias 05 e 06/08 são os momentos de maior comoção. Programação Cultural: Além das novenas e missas no Santuário Basílica, a festa inclui: Shows musicais: Apresentações gratuitas no Palco Mar Pequeno e na Praça da Basílica Feira Popular: Montagem de mais de 300 tendas com artesanato, vestuário, gastronomia e produtos variados. Edição de 2025: Marcada como uma das maiores da história, a edição de 2025 registrou recorde de público e o retorno pleno das celebrações à orla da cidade após anos de restrições. A celebração é considerada o segundo maior evento religioso do estado de São Paulo. | G71: Orla do Mar Pequeno Largo da Basílica | I71: Agosto | J71: 46231 | K71: 46240 | N71: Festa | O71: Religioso | P71: Religioso | Q71: Nehuma das opções acima | R71: Nacional | S71: 280000 | T71: 250000 | U71: 250000 | V71: 220000 | W71: Prefeitura Municipal de Iguape | Y71: 41 99234 5538 | Z71: Deficiência Fisica | AA71: Rampa, Banheiro Acessível | AB71: Não possui | AC71: Livre | AD71: =IFERROR(VLOOKUP(B71,'Regiões Administrativas'!$A$1:$B$646,2,0),"") -> Registro | AE71: =IFERROR(VLOOKUP(Form_Responses[[#This Row],[Município]],'Regiões Administrativas'!$A$1:$I$646,3,0),"") -> 16026 | AF71: =IFERROR(VLOOKUP(Form_Responses[[#This Row],[Município]],'Regiões Administrativas'!$A$1:$I$646,4,0),"") -> 352030105000001 | AG71: =IFERROR(VLOOKUP(Form_Responses[[#This Row],[Município]],'Regiões Administrativas'!$A$1:$I$646,4,0),"") -> 352030105000001 | AH71: =IFERROR(VLOOKUP(B71,'Regiões Administrativas'!$A$1:$I$646,5,0),"") -> 3520301 | AI71: =IFERROR(VLOOKUP(B71,'Regiões Administrativas'!$A$1:$I$646,6,0),"") -> -47.553137 | AJ71: =IFERROR(VLOOKUP(B71,'Regiões Administrativas'!$A$1:$I$646,8,0),"") -> 4.781489 | AK71: =IFERROR(VLOOKUP(Form_Responses[[#This Row],[Município]],'Regiões Administrativas'!$A$1:$I$646,9,0),"") -> 1J6U,6ZoR<B>
A72: 46008.418 | B72: SANTANA DE PARNAÍBA | C72: Roteiro dos Bandeirantes | D72: FESTA DA PADROEIRA - DIA DE SANTA ANA | E72: Em 26 de julho - Dia dos Avós - Santa Ana (mãe de Maria e avó de Jesus) é festejada em Santana de Parnaíba. A festa religiosa em louvor à padroeira da cidade acontece com alvorada, missas, procissão, apresentações musicais, quermesse e fogos. | G72: CENTRO HISTÓRICO | H72: https://prefeitura.santanadeparnaiba.sp.gov.br/Plataforma/smct/eventos | I72: Julho | J72: 46229 | K72: 46229 | L72: 0.83333333 | N72: Festa | O72: Religioso | P72: Religioso | Q72: Nehuma das opções acima | R72: Regional | S72: 1000 | T72: 1000 | U72: 1000 | V72: 1000 | W72: SECRETARIA MUNICIPAL DE CULTURA E TURISMO DE SANTANA DE PARNAÍBA | Y72: smct@santanadeparnaiba.sp.gov.br | Z72: Deficiência Fisica | AA72: Rampa | AB72: Não possui | AC72: Livre | AD72: =IFERROR(VLOOKUP(B72,'Regiões Administrativas'!$A$1:$B$646,2,0),"") -> RMSP | AE72: =IFERROR(VLOOKUP(Form_Responses[[#This Row],[Município]],'Regiões Administrativas'!$A$1:$I$646,3,0),"") -> 17098 | AF72: =IFERROR(VLOOKUP(Form_Responses[[#This Row],[Município]],'Regiões Administrativas'!$A$1:$I$646,4,0),"") -> 354730405000001 | AG72: =IFERROR(VLOOKUP(Form_Responses[[#This Row],[Município]],'Regiões Administrativas'!$A$1:$I$646,4,0),"") -> 354730405000001 | AH72: =IFERROR(VLOOKUP(B72,'Regiões Administrativas'!$A$1:$I$646,5,0),"") -> 3547304 | AI72: =IFERROR(VLOOKUP(B72,'Regiões Administrativas'!$A$1:$I$646,6,0),"") -> -46.922092 | AJ72: =IFERROR(VLOOKUP(B72,'Regiões Administrativas'!$A$1:$I$646,8,0),"") -> 769.83484 | AK72: =IFERROR(VLOOKUP(Form_Responses[[#This Row],[Município]],'Regiões Administrativas'!$A$1:$I$646,9,0),"") -> 1J6tM7.wP3d>
A73: 46008.437 | B73: SANTANA DE PARNAÍBA | C73: Roteiro dos Bandeirantes | D73: SHOW DE ANIVERSÁRIO DA CIDADE | E73: No dia 14 de novembro Santana de Parnaíba comemora seu aniversário. A festa inclui alvorada, missas e diversas atividades culturais tendo como auge grande show (musical e pirotécnico). | G73: Barragem Edgard de Souza - Estrada dos Romeiros, km 40 | H73: https://prefeitura.santanadeparnaiba.sp.gov.br/Plataforma/smct/eventos | I73: Novembro | J73: 46340 | K73: 46340 | L73: 0.83333333 | N73: Aniversário | O73: Artístico/Cultural/Folclórico | P73: Nenhuma das opções acima | Q73: Nehuma das opções acima | R73: Regional | S73: 30000 | T73: 30000 | U73: 30000 | V73: 30000 | W73: SECRETARIA MUNICIPAL DE CULTURA E TURISMO DE SANTANA DE PARNAÍBA | Y73: smct@santanadeparnaiba.sp.gov.br | Z73: Deficiência Fisica | AA73: Rampa, Banheiro Acessível | AB73: Não possui | AC73: Livre | AD73: =IFERROR(VLOOKUP(B73,'Regiões Administrativas'!$A$1:$B$646,2,0),"") -> RMSP | AE73: =IFERROR(VLOOKUP(Form_Responses[[#This Row],[Município]],'Regiões Administrativas'!$A$1:$I$646,3,0),"") -> 17098 | AF73: =IFERROR(VLOOKUP(Form_Responses[[#This Row],[Município]],'Regiões Administrativas'!$A$1:$I$646,4,0),"") -> 354730405000001 | AG73: =IFERROR(VLOOKUP(Form_Responses[[#This Row],[Município]],'Regiões Administrativas'!$A$1:$I$646,4,0),"") -> 354730405000001 | AH73: =IFERROR(VLOOKUP(B73,'Regiões Administrativas'!$A$1:$I$646,5,0),"") -> 3547304 | AI73: =IFERROR(VLOOKUP(B73,'Regiões Administrativas'!$A$1:$I$646,6,0),"") -> -46.922092 | AJ73: =IFERROR(VLOOKUP(B73,'Regiões Administrativas'!$A$1:$I$646,8,0),"") -> 769.83484 | AK73: =IFERROR(VLOOKUP(Form_Responses[[#This Row],[Município]],'Regiões Administrativas'!$A$1:$I$646,9,0),"") -> 1J6tM7.wP3d>
A74: 46008.441 | B74: SANTANA DE PARNAÍBA | C74: Roteiro dos Bandeirantes | D74: NATAL DE LUZ | E74: Durante o mês de dezembro o Centro Histórico ganha decoração e iluminação natalina. São cerca de 500 mil lâmpadas de led, além de adereços, túneis, árvores, pórticos e o maior presépio articulado do Estado, que enfeitam ruas, praças, ponte, monumentos, fachadas de casas e os principais pontos turísticos como Igreja, Coreto e muito mais, atraindo milhares de turistas nesse período. O evento também conta com apresentações de Cantatas de Natal e a presença do Bom Velhinho aos fins de semana. | G74: Praça 14 de Novembro, Centro Histórico e Bolsão de Estacionamento | H74: https://prefeitura.santanadeparnaiba.sp.gov.br/Plataforma/smct/eventos | I74: Dezembro | J74: 46360 | K74: 46393 | N74: Festa | O74: Religioso | P74: Natal | Q74: Nehuma das opções acima | R74: Regional | S74: 150000 | T74: 150000 | U74: 150000 | V74: 150000 | W74: SECRETARIA MUNICIPAL DE CULTURA E TURISMO DE SANTANA DE PARNAÍBA | Y74: smct@santanadeparnaiba.sp.gov.br | Z74: Deficiência Fisica | AA74: Rampa | AB74: Não possui | AC74: Livre | AD74: =IFERROR(VLOOKUP(B74,'Regiões Administrativas'!$A$1:$B$646,2,0),"") -> RMSP | AE74: =IFERROR(VLOOKUP(Form_Responses[[#This Row],[Município]],'Regiões Administrativas'!$A$1:$I$646,3,0),"") -> 17098 | AF74: =IFERROR(VLOOKUP(Form_Responses[[#This Row],[Município]],'Regiões Administrativas'!$A$1:$I$646,4,0),"") -> 354730405000001 | AG74: =IFERROR(VLOOKUP(Form_Responses[[#This Row],[Município]],'Regiões Administrativas'!$A$1:$I$646,4,0),"") -> 354730405000001 | AH74: =IFERROR(VLOOKUP(B74,'Regiões Administrativas'!$A$1:$I$646,5,0),"") -> 3547304 | AI74: =IFERROR(VLOOKUP(B74,'Regiões Administrativas'!$A$1:$I$646,6,0),"") -> -46.922092 | AJ74: =IFERROR(VLOOKUP(B74,'Regiões Administrativas'!$A$1:$I$646,8,0),"") -> 769.83484 | AK74: =IFERROR(VLOOKUP(Form_Responses[[#This Row],[Município]],'Regiões Administrativas'!$A$1:$I$646,9,0),"") -> 1J6tM7.wP3d>
A75: 46008.448 | B75: OLÍMPIA | C75: Águas Sertanejas | D75: Reveillon de Encantos Olímpia 2026 | E75: O Réveillon de Encantos em Olímpia é a grande festa de virada de ano da cidade, um evento público que celebra a chegada de 2026 com muita música, alegria e energia positiva. Em 2026, especificamente, destaca-se o show do cantor Mumuzinho, tradicional queima de fogos, e atrações variadas para moradores e turistas, sendo um evento que mescla lazer e solidariedade com pista solidária (troca por alimentos) e camarotes, consolidando Olímpia como destino de fim de ano. | G75: Estacionamento do Parque Aquático Thermas dos Laranjais | H75: olimpia.sp.gov.br | I75: Janeiro | J75: 46023 | K75: 46023 | L75: 0.95833333 | M75: 0.16666667 | N75: Festa | O75: Artístico/Cultural/Folclórico | P75: Réveillon (Ano Novo) | Q75: Nehuma das opções acima | R75: Regional | S75: 15000 | T75: 10000 | U75: 15000 | V75: 10000 | W75: Prefeitura da Estância Turística de Olímpia | Y75: prefeitura@olimpia.sp.gov.br | Z75: Deficiência Fisica | AA75: Rampa, Elevador, Banheiro Acessível, Balcão de atendimento com altura reduzida, Portas Largas para PCR (Pessoa com cadeira de rodas) | AB75: Áudio Descrição no site do evento, Legenda no site do evento | AC75: Livre | AD75: =IFERROR(VLOOKUP(B75,'Regiões Administrativas'!$A$1:$B$646,2,0),"") -> Barretos | AE75: =IFERROR(VLOOKUP(Form_Responses[[#This Row],[Município]],'Regiões Administrativas'!$A$1:$I$646,3,0),"") -> 16671 | AF75: =IFERROR(VLOOKUP(Form_Responses[[#This Row],[Município]],'Regiões Administrativas'!$A$1:$I$646,4,0),"") -> 353390805000001 | AG75: =IFERROR(VLOOKUP(Form_Responses[[#This Row],[Município]],'Regiões Administrativas'!$A$1:$I$646,4,0),"") -> 353390805000001 | AH75: =IFERROR(VLOOKUP(B75,'Regiões Administrativas'!$A$1:$I$646,5,0),"") -> 3533908 | AI75: =IFERROR(VLOOKUP(B75,'Regiões Administrativas'!$A$1:$I$646,6,0),"") -> -48.913492 | AJ75: =IFERROR(VLOOKUP(B75,'Regiões Administrativas'!$A$1:$I$646,8,0),"") -> 500.31554 | AK75: =IFERROR(VLOOKUP(Form_Responses[[#This Row],[Município]],'Regiões Administrativas'!$A$1:$I$646,9,0),"") -> 1J6RdQ4;ieE-
A76: 46008.449 | B76: SANTANA DE PARNAÍBA | C76: Roteiro dos Bandeirantes | D76: Festa do Cururuquara | E76: Em comemoração a abolição da escravatura, que aconteceu em 13 de maio de 1888, os escravos libertos cantaram e dançaram durante três dias. Anualmente acontece a festa que leva o nome do bairro e objetiva resgatar as raízes dos negros, através de seus descendentes. O evento tem missa com reza cabocla, procissão e muito samba de bumbo. | F76: Lei nº 946/14, publicada em 22/04/15 | G76: Largo das Palmeiras, s/nº - Bairro Cururuquara | H76: https://prefeitura.santanadeparnaiba.sp.gov.br/Plataforma/smct/eventos | I76: Maio | J76: 46158 | L76: 0.83333333 | N76: Festa | O76: Artístico/Cultural/Folclórico | P76: Religioso | Q76: Nehuma das opções acima | R76: Regional | S76: 1000 | T76: 1000 | U76: 1000 | V76: 1000 | W76: SECRETARIA MUNICIPAL DE CULTURA E TURISMO DE SANTANA DE PARNAÍBA | Y76: smct@santanadeparnaiba.sp.gov.br | Z76: Não possui | AA76: Não possui | AB76: Não possui | AC76: Livre | AD76: =IFERROR(VLOOKUP(B76,'Regiões Administrativas'!$A$1:$B$646,2,0),"") -> RMSP | AE76: =IFERROR(VLOOKUP(Form_Responses[[#This Row],[Município]],'Regiões Administrativas'!$A$1:$I$646,3,0),"") -> 17098 | AF76: =IFERROR(VLOOKUP(Form_Responses[[#This Row],[Município]],'Regiões Administrativas'!$A$1:$I$646,4,0),"") -> 354730405000001 | AG76: =IFERROR(VLOOKUP(Form_Responses[[#This Row],[Município]],'Regiões Administrativas'!$A$1:$I$646,4,0),"") -> 354730405000001 | AH76: =IFERROR(VLOOKUP(B76,'Regiões Administrativas'!$A$1:$I$646,5,0),"") -> 3547304 | AI76: =IFERROR(VLOOKUP(B76,'Regiões Administrativas'!$A$1:$I$646,6,0),"") -> -46.922092 | AJ76: =IFERROR(VLOOKUP(B76,'Regiões Administrativas'!$A$1:$I$646,8,0),"") -> 769.83484 | AK76: =IFERROR(VLOOKUP(Form_Responses[[#This Row],[Município]],'Regiões Administrativas'!$A$1:$I$646,9,0),"") -> 1J6tM7.wP3d>
A77: 46008.453 | B77: SANTANA DE PARNAÍBA | C77: Roteiro dos Bandeirantes | D77: ROMARIA DO SURU | E77: Em louvor a Santo Antônio, é realizada na cidade, há quase um século, no mês de junho, a Festa do Surú. É o momento em que a comunidade reverencia a santidade por meio de romaria a cavalo, missa e quermesse. O evento faz parte da política de preservação das tradições do município e é realizado pela Secretaria Municipal de Cultura e Turismo, em parceria com a comunidade católica da cidade. A Romaria sai do Centro Histórico em direção à Capela de Santo Antônio do Suru. | G77: Capela do Surú - Estrada Ecoturística do Surú | H77: https://prefeitura.santanadeparnaiba.sp.gov.br/Plataforma/smct/eventos | I77: Junho | J77: 46187 | K77: 46187 | L77: 0.41666667 | N77: Festa | O77: Religioso | P77: Religioso | Q77: Nehuma das opções acima | R77: Regional | S77: 1000 | T77: 1000 | U77: 1000 | V77: 1000 | W77: SECRETARIA MUNICIPAL DE CULTURA E TURISMO DE SANTANA DE PARNAÍBA | Y77: smct@santanadeparnaiba.sp.gov.br | Z77: Não possui | AA77: Não possui | AB77: Não possui | AC77: Livre | AD77: =IFERROR(VLOOKUP(B77,'Regiões Administrativas'!$A$1:$B$646,2,0),"") -> RMSP | AE77: =IFERROR(VLOOKUP(Form_Responses[[#This Row],[Município]],'Regiões Administrativas'!$A$1:$I$646,3,0),"") -> 17098 | AF77: =IFERROR(VLOOKUP(Form_Responses[[#This Row],[Município]],'Regiões Administrativas'!$A$1:$I$646,4,0),"") -> 354730405000001 | AG77: =IFERROR(VLOOKUP(Form_Responses[[#This Row],[Município]],'Regiões Administrativas'!$A$1:$I$646,4,0),"") -> 354730405000001 | AH77: =IFERROR(VLOOKUP(B77,'Regiões Administrativas'!$A$1:$I$646,5,0),"") -> 3547304 | AI77: =IFERROR(VLOOKUP(B77,'Regiões Administrativas'!$A$1:$I$646,6,0),"") -> -46.922092 | AJ77: =IFERROR(VLOOKUP(B77,'Regiões Administrativas'!$A$1:$I$646,8,0),"") -> 769.83484 | AK77: =IFERROR(VLOOKUP(Form_Responses[[#This Row],[Município]],'Regiões Administrativas'!$A$1:$I$646,9,0),"") -> 1J6tM7.wP3d>
A78: 46008.468 | B78: OLÍMPIA | C78: Águas Sertanejas | D78: Natal Encantado Olímpia | E78: O Natal em Olímpia, SP, é marcado pelo evento "Natal Encantado", com programação gratuita que inclui shows da Orquestra Sinfônica, chegada do Papai Noel, cortejos temáticos com folclore (Lendas em Festa), decoração especial na Praça da Matriz, mercado de artesanato e atividades nos parques aquáticos como o Hot Beach, oferecendo atrações como pintura corporal, oficinas e desfile, com horários especiais de funcionamento para serviços públicos durante o período festivo. | G78: PRAÇA DA MATRIZ “MONSENHOR ANTÔNIO SANTCLIMENTS TORRAS | H78: olimpia.sp.gob.br | I78: Dezembro | J78: 45995 | K78: 46014 | L78: 0.83333333 | M78: 0.99930556 | N78: Festa | O78: Artístico/Cultural/Folclórico | P78: Natal | Q78: Nehuma das opções acima | R78: Regional | S78: 3000 | T78: 2000 | U78: 3000 | V78: 2000 | W78: Prefeitura da Estância Turística de Olímpia | X78: olimpia.sp.gov.br | Y78: prefeitura@olimpia.sp.gov.br | Z78: Deficiência Fisica | AA78: Rampa, Banheiro Acessível, Balcão de atendimento com altura reduzida, Portas Largas para PCR (Pessoa com cadeira de rodas) | AB78: Áudio Descrição no site do evento, Legenda no site do evento | AC78: Livre | AD78: =IFERROR(VLOOKUP(B78,'Regiões Administrativas'!$A$1:$B$646,2,0),"") -> Barretos | AE78: =IFERROR(VLOOKUP(Form_Responses[[#This Row],[Município]],'Regiões Administrativas'!$A$1:$I$646,3,0),"") -> 16671 | AF78: =IFERROR(VLOOKUP(Form_Responses[[#This Row],[Município]],'Regiões Administrativas'!$A$1:$I$646,4,0),"") -> 353390805000001 | AG78: =IFERROR(VLOOKUP(Form_Responses[[#This Row],[Município]],'Regiões Administrativas'!$A$1:$I$646,4,0),"") -> 353390805000001 | AH78: =IFERROR(VLOOKUP(B78,'Regiões Administrativas'!$A$1:$I$646,5,0),"") -> 3533908 | AI78: =IFERROR(VLOOKUP(B78,'Regiões Administrativas'!$A$1:$I$646,6,0),"") -> -48.913492 | AJ78: =IFERROR(VLOOKUP(B78,'Regiões Administrativas'!$A$1:$I$646,8,0),"") -> 500.31554 | AK78: =IFERROR(VLOOKUP(Form_Responses[[#This Row],[Município]],'Regiões Administrativas'!$A$1:$I$646,9,0),"") -> 1J6RdQ4;ieE-
A79: 46008.47 | B79: UCHOA | C79: Águas, Cultura e Negócios | D79: Festa das Nações | E79: Evento anual que conta com a participação de entidades do município comercializando pratos típicos de diversos países, sempre com a apresentação de grandes shows | G79: Recinto Antonio Dias Barreiras - Rua José Carlos Tridapalli | I79: Agosto | N79: Festa | O79: Gastronômico | P79: Nenhuma das opções acima | Q79: Nehuma das opções acima | R79: Regional | S79: 15000 | W79: Prefeitura Municipal de Uchoa | Y79: turismo@uchoa.sp.gov.br | Z79: Deficiência Fisica | AA79: Rampa, Balcão de atendimento com altura reduzida | AB79: Não possui | AC79: Livre | AD79: =IFERROR(VLOOKUP(B79,'Regiões Administrativas'!$A$1:$B$646,2,0),"") -> São José do Rio Preto | AE79: =IFERROR(VLOOKUP(Form_Responses[[#This Row],[Município]],'Regiões Administrativas'!$A$1:$I$646,3,0),"") -> 17413 | AF79: =IFERROR(VLOOKUP(Form_Responses[[#This Row],[Município]],'Regiões Administrativas'!$A$1:$I$646,4,0),"") -> 355560405000001 | AG79: =IFERROR(VLOOKUP(Form_Responses[[#This Row],[Município]],'Regiões Administrativas'!$A$1:$I$646,4,0),"") -> 355560405000001 | AH79: =IFERROR(VLOOKUP(B79,'Regiões Administrativas'!$A$1:$I$646,5,0),"") -> 3555604 | AI79: =IFERROR(VLOOKUP(B79,'Regiões Administrativas'!$A$1:$I$646,6,0),"") -> -49.17767 | AJ79: =IFERROR(VLOOKUP(B79,'Regiões Administrativas'!$A$1:$I$646,8,0),"") -> 504.43619 | AK79: =IFERROR(VLOOKUP(Form_Responses[[#This Row],[Município]],'Regiões Administrativas'!$A$1:$I$646,9,0),"") -> 1J6RdM*:heL>
A80: 46008.475 | B80: OLÍMPIA | C80: Águas Sertanejas | D80: Chegada do Papai Noel | E80: A chegada do Papai Noel em Olímpia é o ponto alto do evento gratuito "Natal Encantado", uma celebração anual da cidade que marca o início das festividades natalinas, com muita luz, música e personagens, culminando com a aparição do Bom Velhinho, que interage com o público e se instala na sua "Casinha" na Praça da Matriz para receber crianças e famílias durante todo o mês de dezembro, promovendo um clima mágico e cultural com espetáculos e decorações. | G80: PRAÇA DA MATRIZ “MONSENHOR ANTÔNIO SANTCLIMENTS TORRAS | H80: olimpia.sp.gov.br | I80: Dezembro | J80: 46001 | K80: 46001 | L80: 0.83333333 | M80: 0.99930556 | N80: Festa | O80: Artístico/Cultural/Folclórico | P80: Natal | Q80: Nehuma das opções acima | R80: Regional | S80: 3000 | T80: 2000 | U80: 3000 | V80: 2000 | W80: Prefeitura da Estância Turística de Olímpia | Y80: prefeitura@olimpia.sp.gov.br | Z80: Deficiência Fisica | AA80: Rampa, Banheiro Acessível, Balcão de atendimento com altura reduzida, Portas Largas para PCR (Pessoa com cadeira de rodas) | AB80: Áudio Descrição no site do evento, Legenda no site do evento | AC80: Livre | AD80: =IFERROR(VLOOKUP(B80,'Regiões Administrativas'!$A$1:$B$646,2,0),"") -> Barretos | AE80: =IFERROR(VLOOKUP(Form_Responses[[#This Row],[Município]],'Regiões Administrativas'!$A$1:$I$646,3,0),"") -> 16671 | AF80: =IFERROR(VLOOKUP(Form_Responses[[#This Row],[Município]],'Regiões Administrativas'!$A$1:$I$646,4,0),"") -> 353390805000001 | AG80: =IFERROR(VLOOKUP(Form_Responses[[#This Row],[Município]],'Regiões Administrativas'!$A$1:$I$646,4,0),"") -> 353390805000001 | AH80: =IFERROR(VLOOKUP(B80,'Regiões Administrativas'!$A$1:$I$646,5,0),"") -> 3533908 | AI80: =IFERROR(VLOOKUP(B80,'Regiões Administrativas'!$A$1:$I$646,6,0),"") -> -48.913492 | AJ80: =IFERROR(VLOOKUP(B80,'Regiões Administrativas'!$A$1:$I$646,8,0),"") -> 500.31554 | AK80: =IFERROR(VLOOKUP(Form_Responses[[#This Row],[Município]],'Regiões Administrativas'!$A$1:$I$646,9,0),"") -> 1J6RdQ4;ieE-
A81: 46008.476 | B81: SANTA CRUZ DO RIO PARDO | C81: Angra Paulista | D81: Rock Rio Pardo | E81: Criado em 2002, o então Rock in Rio Pardo, surgiu do anseio de alguns músicos principiantes e suas bandas de garagem. Em 2007, foi feita a parceria com a Secretaria de Cultura, uma melhor estrutura foi destinada ao evento, como som e palcos profissionais, divulgação, entre outros. Com o incremento, o evento ganhou força e entrou para o calendário de eventos da cidade.​ São três dias de evento, com apresentação de várias bandas por dia dos mais diversos lugares do Estado de São Paulo, além da apresentação de uma grande banda nacional no encerramento de cada dia. Nomes como Ira!, Raimundos, Ultraje a Rigor, Titãs, Sepultura, Matanza, Frejat, Nando Reis, Angra e Cachorro Grande já se apresentaram no evento. Em 2019, vieram CPM22, a volta aos palcos do festival da banda Sepultura - substituindo a banda Shaman pela fatalidade do falecimento do grande vocalista André Matos) - e a nova turnê chamada Matriz da cantora Pitty. O ingresso é apenas 1 kg de alimento não perecível, sendo o maior festival solidário do Brasil. Para o ano de 2026, teremos Samuel Rosa, Banda Glória e Biquíni (anteriormente conhecida como Biquini Cavadão). | G81: Recinto de Exposições José Rosso - Av. Antônio Bernadino Pereira de Lima - Vila Maristela | H81: https://www.rockriopardo.com.br/ | I81: Julho | J81: 46213 | K81: 46215 | L81: 0.79166667 | N81: Festival | O81: Artístico/Cultural/Folclórico | P81: Nenhuma das opções acima | Q81: Nehuma das opções acima | R81: Regional | S81: 30000 | T81: 28000 | W81: Prefeitura Municipal e Comissão de Bandas de Santa Cruz | Y81: turismo@santacruzdoriopardo.sp.gov.br | Z81: Deficiência Fisica, Deficiência Auditiva, Deficiência Intelectual | AA81: Atendimento em Línguas de Sinais, Rampa, Banheiro Acessível, Portas Largas para PCR (Pessoa com cadeira de rodas) | AB81: Não possui | AC81: Livre | AD81: =IFERROR(VLOOKUP(B81,'Regiões Administrativas'!$A$1:$B$646,2,0),"") -> Marília | AE81: =IFERROR(VLOOKUP(Form_Responses[[#This Row],[Município]],'Regiões Administrativas'!$A$1:$I$646,3,0),"") -> 17061 | AF81: =IFERROR(VLOOKUP(Form_Responses[[#This Row],[Município]],'Regiões Administrativas'!$A$1:$I$646,4,0),"") -> 354640505000001 | AG81: =IFERROR(VLOOKUP(Form_Responses[[#This Row],[Município]],'Regiões Administrativas'!$A$1:$I$646,4,0),"") -> 354640505000001 | AH81: =IFERROR(VLOOKUP(B81,'Regiões Administrativas'!$A$1:$I$646,5,0),"") -> 3546405 | AI81: =IFERROR(VLOOKUP(B81,'Regiões Administrativas'!$A$1:$I$646,6,0),"") -> -49.624609 | AJ81: =IFERROR(VLOOKUP(B81,'Regiões Administrativas'!$A$1:$I$646,8,0),"") -> 456.77152 | AK81: =IFERROR(VLOOKUP(Form_Responses[[#This Row],[Município]],'Regiões Administrativas'!$A$1:$I$646,9,0),"") -> 1J6RW@*2i4+p
A82: 46008.477 | B82: MARÍLIA | C82: Alto Cafezal | D82: Japan Fest | E82: Considerado um dos eventos mais tradicionais e importantes da colônia japonesa em todo o país, o Japan Fest iniciou em 2003 e é promovido pela Associação Cultural e Esportiva Nikkey de Marília em parceria com a Prefeitura Municipal e Governo do Estado. Com o principal objetivo de preservar e divulgar a cultural oriental e consolidar as relações entre descendentes e não descendentes, o Japan Fest ocorre uma vez por ano, em abril, tem duração de 04 dias oferecendo inúmeras atrações culturais, artísticas, gastronômicas e filantrópicas. Entrada gratuita, com a contribuição voluntária de alimentos. Em 2026 será realizada a 23ª edição. | G82: R. Benedito Alves Delfino, 2850 - Distrito Industrial, Marília - SP, 17512-043 | H82: https://www.instagram.com/japanfestmarilia/ https://www.nikkeymarilia.com.br/site/index.asp | I82: Abril | J82: 46129 | K82: 46133 | L82: 0.5 | M82: 0.95833333 | N82: Festa | O82: Artístico/Cultural/Folclórico | P82: Social/Cívico/Histórico | Q82: Nehuma das opções acima | R82: Internacional | S82: 70000 | T82: 70000 | U82: 70000 | V82: 70000 | W82: Associação Cultural e Esportiva Nikkey de Marília | X82: gratuito | Y82: secretaria@nikkeymarilia.com.br | Z82: Deficiência Fisica | AA82: Banheiro Acessível | AB82: Não possui | AC82: Livre | AD82: =IFERROR(VLOOKUP(B82,'Regiões Administrativas'!$A$1:$B$646,2,0),"") -> Marília | AE82: =IFERROR(VLOOKUP(Form_Responses[[#This Row],[Município]],'Regiões Administrativas'!$A$1:$I$646,3,0),"") -> 16464 | AF82: =IFERROR(VLOOKUP(Form_Responses[[#This Row],[Município]],'Regiões Administrativas'!$A$1:$I$646,4,0),"") -> 352900505000001 | AG82: =IFERROR(VLOOKUP(Form_Responses[[#This Row],[Município]],'Regiões Administrativas'!$A$1:$I$646,4,0),"") -> 352900505000001 | AH82: =IFERROR(VLOOKUP(B82,'Regiões Administrativas'!$A$1:$I$646,5,0),"") -> 3529005 | AI82: =IFERROR(VLOOKUP(B82,'Regiões Administrativas'!$A$1:$I$646,6,0),"") -> -49.951646 | AJ82: =IFERROR(VLOOKUP(B82,'Regiões Administrativas'!$A$1:$I$646,8,0),"") -> 657.30619 | AK82: =IFERROR(VLOOKUP(Form_Responses[[#This Row],[Município]],'Regiões Administrativas'!$A$1:$I$646,9,0),"") -> 1J6RQZYeWgj>
A83: 46008.506 | B83: MARÍLIA | C83: Alto Cafezal | D83: Festival Gastronômico | E83: O Festival Gastronômico de Marília é o maior evento de gastronomia da região. Em 2025 foi a 11ª edição e é organizado e promovido pelo Marília e Região Convention & Visitors Bureau e Sindicato de Hotéis, Bares e Restaurantes, em parceria com a Prefeitura Municipal. Os principais restaurantes da cidade, cerca de 20, participam desse evento, lançando novos pratos, a preço único que, como critério, devem homenagear pessoas, famílias, lugares ou empresas que fazem parte da história da cidade. Além disso, o festival premia os consumidores e uma característica importante do evento é a ação social: a cada ano a organização do Festival escolhe duas entidades para receber parte da renda arrecadada com a venda dos pratos. Tem duração de, em média, 45 dias. | G83: Cerca de 20 restaurantes | H83: https://www.instagram.com/festivalgastronomicodemarilia/ | I83: Setembro | J83: 45925 | K83: 45970 | L83: 0.5 | M83: 0.95833333 | N83: Festival | O83: Gastronômico | P83: Nenhuma das opções acima | Q83: Nehuma das opções acima | R83: Regional | S83: 10000 | T83: 9334 | U83: 6640 | V83: 5094 | W83: Marília e Região Convention & Visitors Bureau e Sindicato de Hotéis, Bares e Restaurantes | X83: sinhoresmarilia@gmail.com | Y83: sinhoresmarilia@gmail.com | Z83: Deficiência Fisica | AA83: Banheiro Acessível | AB83: Não possui | AC83: Livre | AD83: =IFERROR(VLOOKUP(B83,'Regiões Administrativas'!$A$1:$B$646,2,0),"") -> Marília | AE83: =IFERROR(VLOOKUP(Form_Responses[[#This Row],[Município]],'Regiões Administrativas'!$A$1:$I$646,3,0),"") -> 16464 | AF83: =IFERROR(VLOOKUP(Form_Responses[[#This Row],[Município]],'Regiões Administrativas'!$A$1:$I$646,4,0),"") -> 352900505000001 | AG83: =IFERROR(VLOOKUP(Form_Responses[[#This Row],[Município]],'Regiões Administrativas'!$A$1:$I$646,4,0),"") -> 352900505000001 | AH83: =IFERROR(VLOOKUP(B83,'Regiões Administrativas'!$A$1:$I$646,5,0),"") -> 3529005 | AI83: =IFERROR(VLOOKUP(B83,'Regiões Administrativas'!$A$1:$I$646,6,0),"") -> -49.951646 | AJ83: =IFERROR(VLOOKUP(B83,'Regiões Administrativas'!$A$1:$I$646,8,0),"") -> 657.30619 | AK83: =IFERROR(VLOOKUP(Form_Responses[[#This Row],[Município]],'Regiões Administrativas'!$A$1:$I$646,9,0),"") -> 1J6RQZYeWgj>
A84: 46008.539 | B84: OLÍMPIA | C84: Águas Sertanejas | D84: Olímpia Rodeo Festival | E84: O Olímpia Rodeo Festival, também conhecido como Festa do Peão de Olímpia, é um grande evento anual em Olímpia, SP, que celebra a cultura sertaneja e o agronegócio, combinando competições de rodeio (montaria em touros, parte do circuito PBR Brasil), grandes shows de música sertaneja, estrutura completa com camarotes e uma feira agropecuária (Olímpia + Agro) que fortalece o setor local. É uma festa de tradição que une esporte, lazer, gastronomia e solidariedade, atraindo público da região e turistas. | G84: Recinto do Folclore de Olímpia - Avenida Menina Moça, nº 800, na Vila Hípica, CEP 15407-050 | H84: olimpia.sp.gov.br | I84: Maio | J84: 46149 | K84: 46151 | L84: 0.83333333 | M84: 0.99930556 | N84: Festa | O84: Rural | P84: Rodeio | Q84: Nehuma das opções acima | R84: Regional | S84: 30000 | T84: 30000 | U84: 25000 | V84: 20000 | W84: Prefeitura da Estância Turística de Olímpia | Y84: prefeitura@olimpia.sp.gov.br | Z84: Deficiência Fisica | AA84: Rampa, Elevador, Banheiro Acessível, Balcão de atendimento com altura reduzida, Portas Largas para PCR (Pessoa com cadeira de rodas) | AB84: Áudio Descrição no site do evento, Legenda no site do evento | AC84: Livre | AD84: =IFERROR(VLOOKUP(B84,'Regiões Administrativas'!$A$1:$B$646,2,0),"") -> Barretos | AE84: =IFERROR(VLOOKUP(Form_Responses[[#This Row],[Município]],'Regiões Administrativas'!$A$1:$I$646,3,0),"") -> 16671 | AF84: =IFERROR(VLOOKUP(Form_Responses[[#This Row],[Município]],'Regiões Administrativas'!$A$1:$I$646,4,0),"") -> 353390805000001 | AG84: =IFERROR(VLOOKUP(Form_Responses[[#This Row],[Município]],'Regiões Administrativas'!$A$1:$I$646,4,0),"") -> 353390805000001 | AH84: =IFERROR(VLOOKUP(B84,'Regiões Administrativas'!$A$1:$I$646,5,0),"") -> 3533908 | AI84: =IFERROR(VLOOKUP(B84,'Regiões Administrativas'!$A$1:$I$646,6,0),"") -> -48.913492 | AJ84: =IFERROR(VLOOKUP(B84,'Regiões Administrativas'!$A$1:$I$646,8,0),"") -> 500.31554 | AK84: =IFERROR(VLOOKUP(Form_Responses[[#This Row],[Município]],'Regiões Administrativas'!$A$1:$I$646,9,0),"") -> 1J6RdQ4;ieE-
A85: 46008.677 | B85: VOTUPORANGA | C85: Maravilhas do Rio Grande | D85: FLIV - Festival Literário de Votuporanga | E85: O Festival Literário de Votuporanga (Fliv) chegará à sua 16ª edição em 2026, consolidando-se como um dos maiores e mais importantes eventos multiculturais do Brasil. Reconhecido nacionalmente por sua relevância artística, social e educacional, o festival oferece uma ampla programação gratuita, com atividades que promovem a literatura, as artes e a cultura em suas mais diversas expressões. O evento será realizado na cidade de Votuporanga/SP, localizada a aproximadamente 530 km da capital paulista, no período de 8 a 16 de agosto de 2026. Durante esses dias, a cidade se transforma em um polo de efervescência cultural, reunindo escritores, artistas, educadores, editoras, livrarias e o público em geral, fomentando o acesso à leitura, à arte e ao conhecimento. Em 2021, o Fliv foi agraciado com o Prêmio Governador do Estado de São Paulo para as Artes, na categoria Livro, Leitura e Bibliotecas, destacando-se entre as principais iniciativas culturais do país. Já em 2023, foi novamente indicado ao mesmo prêmio, desta vez na categoria “Iniciativas Culturais – Terceiro Setor”, reafirmando seu papel como referência nacional no campo cultural e artístico. Em 2025, o festival foi reconhecido como Patrimônio Imaterial do Município de Votuporanga, reconhecimento que evidencia sua importância histórica, cultural e simbólica para a cidade e para o cenário cultural brasileiro. Por sua amplitude e impacto sociocultural, o Fliv depende de múltiplas fontes de financiamento para sua realização, incluindo recursos públicos e privados, editais e parcerias institucionais. Assim, o apoio por meio da Lei de Incentivo à Cultura mostra-se essencial para viabilizar o evento, uma vez que o recurso proveniente do Programa Bolsa Cultura, por si só, é insuficiente para garantir a execução integral da programação e da infraestrutura necessária para um festival dessa magnitude. Cabe ressaltar que o pagamento do responsável técnico pelo projeto será realizado por meio de outras fontes de financiamento, não sendo custeado com os recursos deste edital, assegurando a correta aplicação dos valores incentivados e o cumprimento das normas legais. | G85: Rua Francisco Ramalho de Mendonça, 3112 - Jardim Alvorada, Votuporanga/SP | H85: https://fliv.com.br | I85: Agosto | J85: 46242 | K85: 46250 | L85: 0.33333333 | M85: 0.95833333 | N85: Festival | O85: Artístico/Cultural/Folclórico | P85: Nenhuma das opções acima | Q85: Nehuma das opções acima | R85: Nacional | S85: 80000 | T85: 70000 | U85: 85000 | V85: 80000 | W85: Prefeitura Municipal de Votuporanga | X85: Entrada gratuita | Y85: cultura@votuporanga.sp.gov.br | Z85: Deficiência Fisica, Deficiência Visual, Deficiência Auditiva, Deficiência Intelectual | AA85: Piso Tátil, Rampa, Elevador, Banheiro Acessível, Portas Largas para PCR (Pessoa com cadeira de rodas) | AB85: Não possui | AC85: Livre | AD85: =IFERROR(VLOOKUP(B85,'Regiões Administrativas'!$A$1:$B$646,2,0),"") -> São José do Rio Preto | AE85: =IFERROR(VLOOKUP(Form_Responses[[#This Row],[Município]],'Regiões Administrativas'!$A$1:$I$646,3,0),"") -> 17450 | AF85: =IFERROR(VLOOKUP(Form_Responses[[#This Row],[Município]],'Regiões Administrativas'!$A$1:$I$646,4,0),"") -> 355710505000001 | AG85: =IFERROR(VLOOKUP(Form_Responses[[#This Row],[Município]],'Regiões Administrativas'!$A$1:$I$646,4,0),"") -> 355710505000001 | AH85: =IFERROR(VLOOKUP(B85,'Regiões Administrativas'!$A$1:$I$646,5,0),"") -> 3557105 | AI85: =IFERROR(VLOOKUP(B85,'Regiões Administrativas'!$A$1:$I$646,6,0),"") -> -49.974672 | AJ85: =IFERROR(VLOOKUP(B85,'Regiões Administrativas'!$A$1:$I$646,8,0),"") -> 518.33459 | AK85: =IFERROR(VLOOKUP(Form_Responses[[#This Row],[Município]],'Regiões Administrativas'!$A$1:$I$646,9,0),"") -> 1J6R3Zw@HH+p
A86: 46008.68 | B86: IGUAPE | C86: Lagamar | D86: Revelando São Paulo - Vale do Ribeira | E86: O Revelando SP é o maior festival de cultura tradicional paulista, que anualmente realiza uma de suas edições na cidade de Iguape. O evento celebra e valoriza as tradições do estado, com entrada gratuita, e geralmente ocorre no Centro de Eventos Prefeito Casimiro Teixeira. O festival é um encontro que valoriza as raízes culturais de São Paulo, reunindo manifestações do campo, da cidade, do litoral e de comunidades indígenas. O objetivo é promover o conhecimento e o respeito pela história e pelo modo de vida local. As principais atrações incluem culinária tradicional, incluindo barracas com comidas típicas de diversas regiões do estado. Exposição e venda de peças que carregam história e identidade, como trançados, cerâmicas, esculturas e bordados, bem como apresentações culturais que incluem música, dança, saberes populares, grupos rituais, seresteiros, sanfoneiros e violeiros. Edições recentes contaram com apresentações de artistas renomados como Almir Sater, 14 Bis, Bruna Viola, e outros. O evento possui espaços interativos com artesãos e exposições acessíveis, como a de arte sacra em 3D, que permite o toque nas peças. Em 2025, o evento ocorreu em Iguape de 19 a 22 de junho, como parte do calendário anual do festival que também passou por outras cidades como Barretos e São José dos Campos. O "Revelando SP" consolidou-se como um palco importante para o fortalecimento das tradições paulistas, atraindo milhares de visitantes interessados em vivenciar a riqueza da identidade cultural do estado. | G86: Centro de Eventos - Rua Ana Cândida Sandoval, s/n Triogo | H86: www.revelandosp.com.br | I86: Junho | J86: 46176 | K86: 46180 | N86: Feira/Exposição/Mostra | O86: Artístico/Cultural/Folclórico | P86: Nenhuma das opções acima | Q86: Nehuma das opções acima | R86: Nacional | S86: 60000 | T86: 64229 | U86: 60000 | V86: 56000 | W86: Secretaria de Cultura do Estado | Y86: cultura@iguape.sp.gov.br | Z86: Deficiência Fisica, Deficiência Visual | AA86: Rampa, Banheiro Acessível | AB86: Não possui | AC86: Livre | AD86: =IFERROR(VLOOKUP(B86,'Regiões Administrativas'!$A$1:$B$646,2,0),"") -> Registro | AE86: =IFERROR(VLOOKUP(Form_Responses[[#This Row],[Município]],'Regiões Administrativas'!$A$1:$I$646,3,0),"") -> 16026 | AF86: =IFERROR(VLOOKUP(Form_Responses[[#This Row],[Município]],'Regiões Administrativas'!$A$1:$I$646,4,0),"") -> 352030105000001 | AG86: =IFERROR(VLOOKUP(Form_Responses[[#This Row],[Município]],'Regiões Administrativas'!$A$1:$I$646,4,0),"") -> 352030105000001 | AH86: =IFERROR(VLOOKUP(B86,'Regiões Administrativas'!$A$1:$I$646,5,0),"") -> 3520301 | AI86: =IFERROR(VLOOKUP(B86,'Regiões Administrativas'!$A$1:$I$646,6,0),"") -> -47.553137 | AJ86: =IFERROR(VLOOKUP(B86,'Regiões Administrativas'!$A$1:$I$646,8,0),"") -> 4.781489 | AK86: =IFERROR(VLOOKUP(Form_Responses[[#This Row],[Município]],'Regiões Administrativas'!$A$1:$I$646,9,0),"") -> 1J6U,6ZoR<B>
A87: 46008.693 | B87: VOTUPORANGA | C87: Maravilhas do Rio Grande | D87: VOTU INTERNATIONAL RODEO | E87: O Votu International Rodeo é um grande festival de rodeio e entretenimento realizado em Votuporanga (SP), no Centro de Eventos Helder Henrique Galera. Sua primeira edição recente aconteceu entre 8 e 11 de maio de 2025, resgatando a tradição do rodeio na cidade após anos sem o evento e atraindo um público recorde de cerca de 80 mil pessoas com competição internacional de montarias em touros, shows sertanejos e atrações para toda a família. O evento combina desafios esportivos emocionantes com música ao vivo de grandes nomes do cenário nacional, estrutura de parque de diversões, opções de camarotes e entrada gratuita para a pista em todos os dias. Além do aspecto esportivo, o rodeio também teve impacto social e econômico significativo, movimentando milhões na economia local, gerando empregos e promovendo ações solidárias, como a arrecadação de R$ 200 mil para a Santa Casa de Votuporanga no Desafio do Bem. Após o sucesso de 2025, a organização já prepara uma edição ainda maior para 7 a 10 de maio de 2026, com premiação histórica anunciada e uma grade de atrações ampliada. | G87: "Centro de Eventos Helder Henrique Galera" - Angelo Comar - Rod. Vicinal, VTG 020 - Votuporanga/SP | I87: Maio | J87: 46149 | K87: 46152 | L87: 0.83333333 | M87: 0.25 | N87: Campeonato/Torneio/Concurso | O87: Esportivo | P87: Rodeio | Q87: Nehuma das opções acima | R87: Internacional | S87: 90000 | T87: 80000 | W87: Grupo Tércio Miranda, com apoio da Prefeitura Municipal de Votuporanga | X87: https://www.totalacesso.com/events/VotuInternationalRodeo?utm_source=ig&utm_medium=social&utm_content=link_in_bio&fbclid=PAdGRleAOv4wVleHRuA2FlbQIxMQBzcnRjBmFwcF9pZA8xMjQwMjQ1NzQyODc0MTQAAaeTDL7CqlMZhpQ9oaQnGDf4QBd2h4EhZdynF5Bj5N7Tj3L1DmW0okh1j--8gQ_aem_BFdiZ96lqeE0iZQyBV_HLw | Y87: cultura@votuporanga.sp.gov.br | Z87: Deficiência Fisica, Deficiência Visual, Deficiência Auditiva, Deficiência Intelectual | AA87: Piso Tátil, Rampa, Banheiro Acessível, Portas Largas para PCR (Pessoa com cadeira de rodas) | AB87: Não possui | AC87: Livre | AD87: =IFERROR(VLOOKUP(B87,'Regiões Administrativas'!$A$1:$B$646,2,0),"") -> São José do Rio Preto | AE87: =IFERROR(VLOOKUP(Form_Responses[[#This Row],[Município]],'Regiões Administrativas'!$A$1:$I$646,3,0),"") -> 17450 | AF87: =IFERROR(VLOOKUP(Form_Responses[[#This Row],[Município]],'Regiões Administrativas'!$A$1:$I$646,4,0),"") -> 355710505000001 | AG87: =IFERROR(VLOOKUP(Form_Responses[[#This Row],[Município]],'Regiões Administrativas'!$A$1:$I$646,4,0),"") -> 355710505000001 | AH87: =IFERROR(VLOOKUP(B87,'Regiões Administrativas'!$A$1:$I$646,5,0),"") -> 3557105 | AI87: =IFERROR(VLOOKUP(B87,'Regiões Administrativas'!$A$1:$I$646,6,0),"") -> -49.974672 | AJ87: =IFERROR(VLOOKUP(B87,'Regiões Administrativas'!$A$1:$I$646,8,0),"") -> 518.33459 | AK87: =IFERROR(VLOOKUP(Form_Responses[[#This Row],[Município]],'Regiões Administrativas'!$A$1:$I$646,9,0),"") -> 1J6R3Zw@HH+p
A88: 46008.707 | B88: VOTUPORANGA | C88: Maravilhas do Rio Grande | D88: OBA FESTIVAL | E88: O OBA Festival é um dos mais tradicionais e populares carnavais do interior paulista, nascido em Votuporanga (SP) há cerca de 20 anos como uma festa de Carnaval local e que, ao longo do tempo, ganhou projeção regional. Em 2022, o festival foi transferido para São José do Rio Preto, onde foi realizado por três edições, consolidando-se como um dos maiores carnavais do interior paulista. No entanto, em 2025 foi anunciado o retorno do OBA Festival à sua cidade de origem, Votuporanga, para a edição de 2026, após parceria entre poder público e iniciativa privada da cidade, que viabilizou melhorias na infraestrutura do evento, incluindo reforma de espaços, novos setores e maior capacidade de público. Esse retorno marca um novo ciclo para o festival, reforçando sua identidade com Votuporanga e ampliando sua atuação com novidades como a Pista Solidária, setores diferenciados e grandes atrações musicais confirmadas para a programação de 14 a 16 de fevereiro de 2026. | G88: Centro de Eventos “Helder Henrique Galera” - Angelo Comar - Rod. Vicinal, VTG 020 | H88: https://www.obafestival.com.br/ | I88: Fevereiro | J88: 46067 | K88: 46069 | L88: 0.70833333 | M88: 0.20833333 | N88: Festival | O88: Artístico/Cultural/Folclórico | P88: Carnaval | Q88: Nehuma das opções acima | R88: Nacional | S88: 100000 | T88: 100000 | U88: 100000 | V88: 100000 | W88: Oba Produções Ltda. com apoio da Prefeitura Municipal de Votuporanga | X88: https://www.guicheweb.com.br/oba-festival-2026_46590 | Y88: cultura@votuporanga.sp.gov.br | Z88: Deficiência Fisica, Deficiência Visual, Deficiência Auditiva, Deficiência Intelectual | AA88: Piso Tátil, Rampa, Banheiro Acessível, Portas Largas para PCR (Pessoa com cadeira de rodas) | AB88: Não possui | AC88: Indicado para maiores de 16 anos | AD88: =IFERROR(VLOOKUP(B88,'Regiões Administrativas'!$A$1:$B$646,2,0),"") -> São José do Rio Preto | AE88: =IFERROR(VLOOKUP(Form_Responses[[#This Row],[Município]],'Regiões Administrativas'!$A$1:$I$646,3,0),"") -> 17450 | AF88: =IFERROR(VLOOKUP(Form_Responses[[#This Row],[Município]],'Regiões Administrativas'!$A$1:$I$646,4,0),"") -> 355710505000001 | AG88: =IFERROR(VLOOKUP(Form_Responses[[#This Row],[Município]],'Regiões Administrativas'!$A$1:$I$646,4,0),"") -> 355710505000001 | AH88: =IFERROR(VLOOKUP(B88,'Regiões Administrativas'!$A$1:$I$646,5,0),"") -> 3557105 | AI88: =IFERROR(VLOOKUP(B88,'Regiões Administrativas'!$A$1:$I$646,6,0),"") -> -49.974672 | AJ88: =IFERROR(VLOOKUP(B88,'Regiões Administrativas'!$A$1:$I$646,8,0),"") -> 518.33459 | AK88: =IFERROR(VLOOKUP(Form_Responses[[#This Row],[Município]],'Regiões Administrativas'!$A$1:$I$646,9,0),"") -> 1J6R3Zw@HH+p
A89: 46009.192 | B89: SANTA ISABEL | C89: Coração Paulista | D89: 13° Volks Day - Encontro de Fuscas e Carros antigos | E89: Evento beneficente para público familiar, realizado todo terceiro domingo de junho de cada ano e participação de vários clubes de carros antigos vindos de várias cidades do estado, sendo que no último evento teve cerca de 600 carros expostos. | G89: Rua Eloy pessoa barros (espaço rodovia) | I89: Junho | J89: 46194 | K89: 46194 | L89: 0.33333333 | M89: 0.70833333 | N89: Feira/Exposição/Mostra | O89: Social/Cívico/Histórico | P89: Social/Cívico/Histórico | Q89: Nehuma das opções acima | R89: Regional | S89: 4000 | T89: 4000 | U89: 3000 | V89: 2000 | W89: Boxer Club Santa Isabel | Y89: rogeriopiscinas1234@gmail.com | Z89: Não possui | AA89: Banheiro Acessível | AB89: Não possui | AC89: Livre | AD89: =IFERROR(VLOOKUP(B89,'Regiões Administrativas'!$A$1:$B$646,2,0),"") -> RMSP | AE89: =IFERROR(VLOOKUP(Form_Responses[[#This Row],[Município]],'Regiões Administrativas'!$A$1:$I$646,3,0),"") -> 17077 | AF89: =IFERROR(VLOOKUP(Form_Responses[[#This Row],[Município]],'Regiões Administrativas'!$A$1:$I$646,4,0),"") -> 354680105000001 | AG89: =IFERROR(VLOOKUP(Form_Responses[[#This Row],[Município]],'Regiões Administrativas'!$A$1:$I$646,4,0),"") -> 354680105000001 | AH89: =IFERROR(VLOOKUP(B89,'Regiões Administrativas'!$A$1:$I$646,5,0),"") -> 3546801 | AI89: =IFERROR(VLOOKUP(B89,'Regiões Administrativas'!$A$1:$I$646,6,0),"") -> -46.227013 | AJ89: =IFERROR(VLOOKUP(B89,'Regiões Administrativas'!$A$1:$I$646,8,0),"") -> 646.60742 | AK89: =IFERROR(VLOOKUP(Form_Responses[[#This Row],[Município]],'Regiões Administrativas'!$A$1:$I$646,9,0),"") -> 1J6tOl=wZJb>
A90: 46009.353 | B90: MARÍLIA | C90: Alto Cafezal | D90: Festival de Cinema de Marília | E90: O Festival de Cinema de Marília é um evento de grande relevância no calendário nacional e referência no cenário cultural brasileiro. Com raízes na década de 1960, atrai cineastas, críticos, cinéfilos e entusiastas. Este evento não se resume apenas à exibição de filmes, ele representa uma celebração da sétima arte e da riqueza cultural brasileira, criando um espaço de networking, aprendizado e entretenimento. Realizado no Teatro Municipal “Waldir Silveira Mello”, a programação é intensa e diversificada, contando com oficinas, mostras competitivas, sessões de filmes (longas e curtas-metragens), entre outras atividades, abordando também temas essenciais como inclusão social, diversidade e sustentabilidade. O Festival tem realização do Clube de Cinema de Marília e Ministério da Cultura e conta com o apoio da Política Nacional PNAB – Aldir Blanc, Prefeitura de Marília, Produtora Cinegoria e Produtora Alumiar Filmes. Entrada gratuita e duração de 8 dias, em média. | G90: Teatro Municipal Waldir Silveira Mello, avenida Rio Branco, 51 - Centro, Marília/SP | H90: www.festivalcinemamarilia.com.br www.instagram.com/festivalcinemamarilia. | I90: Setembro | J90: 46269 | K90: 46278 | L90: 0.58333333 | M90: 0.91666667 | N90: Festival | O90: Artístico/Cultural/Folclórico | P90: Nenhuma das opções acima | Q90: Nehuma das opções acima | R90: Nacional | S90: 3000 | T90: 2500 | U90: 2000 | V90: 2000 | W90: Clube de Cinema de Marília | X90: www.festivalcinemamarilia.com.br // www.instagram.com/festivalcinemamarilia. | Y90: https://www.festivalcinemamarilia.com.br/contato | Z90: Deficiência Fisica | AA90: Rampa, Elevador, Banheiro Acessível | AB90: Não possui | AC90: Livre | AD90: =IFERROR(VLOOKUP(B90,'Regiões Administrativas'!$A$1:$B$646,2,0),"") -> Marília | AE90: =IFERROR(VLOOKUP(Form_Responses[[#This Row],[Município]],'Regiões Administrativas'!$A$1:$I$646,3,0),"") -> 16464 | AF90: =IFERROR(VLOOKUP(Form_Responses[[#This Row],[Município]],'Regiões Administrativas'!$A$1:$I$646,4,0),"") -> 352900505000001 | AG90: =IFERROR(VLOOKUP(Form_Responses[[#This Row],[Município]],'Regiões Administrativas'!$A$1:$I$646,4,0),"") -> 352900505000001 | AH90: =IFERROR(VLOOKUP(B90,'Regiões Administrativas'!$A$1:$I$646,5,0),"") -> 3529005 | AI90: =IFERROR(VLOOKUP(B90,'Regiões Administrativas'!$A$1:$I$646,6,0),"") -> -49.951646 | AJ90: =IFERROR(VLOOKUP(B90,'Regiões Administrativas'!$A$1:$I$646,8,0),"") -> 657.30619 | AK90: =IFERROR(VLOOKUP(Form_Responses[[#This Row],[Município]],'Regiões Administrativas'!$A$1:$I$646,9,0),"") -> 1J6RQZYeWgj>
A91: 46009.362 | B91: MARÍLIA | C91: Alto Cafezal | D91: Festival do Café | E91: O Festival do Café celebra a centenária Fazenda Cascata, propriedade cafeeira que teve papel fundamental na fundação e no desenvolvimento de Marília e região, e marca também a inserção de Marília e região no programa estadual Rotas do Café, valorizando uma das mais importantes cadeias produtivas responsáveis pelo crescimento econômico e cultural local e regional. Com uma programação completa para toda a família, o Festival do Café reúne produtores de café, artesãos, baristas, palestrantes e atrações musicais. O público desfruta de praça de alimentação com food trucks, produtos artesanais, brinquedos infláveis, exposição de tratores e fotos, além de palestras. Valoriza a cadeia produtiva do café, fomenta o turismo e o lazer, difunde conhecimento, história e cultura, além de fortalecer a identidade e o desenvolvimento regional. A entrada é gratuita, com doação voluntária de 1 kg de alimento, das 10h às 18h. | G91: Fazenda Cascata: avenida Cascata, 201-495- Jardim Maria Izabel -Marília/SP | H91: https://www.instagram.com/turismomarilia/ | I91: Setembro | J91: 46284 | K91: 46285 | L91: 0.41666667 | M91: 0.75 | N91: Festival | O91: Artístico/Cultural/Folclórico | P91: Nenhuma das opções acima | Q91: Nehuma das opções acima | R91: Regional | S91: 8000 | T91: 6000 | W91: Prefeitura Municipal de Marília, através da Secretaria Municipal do Trabalho, Turismo e Desenvolvimento Econômico | Y91: turismo@marilia.sp.gov.br | Z91: Não possui | AA91: Não possui | AB91: Não possui | AC91: Livre | AD91: =IFERROR(VLOOKUP(B91,'Regiões Administrativas'!$A$1:$B$646,2,0),"") -> Marília | AE91: =IFERROR(VLOOKUP(Form_Responses[[#This Row],[Município]],'Regiões Administrativas'!$A$1:$I$646,3,0),"") -> 16464 | AF91: =IFERROR(VLOOKUP(Form_Responses[[#This Row],[Município]],'Regiões Administrativas'!$A$1:$I$646,4,0),"") -> 352900505000001 | AG91: =IFERROR(VLOOKUP(Form_Responses[[#This Row],[Município]],'Regiões Administrativas'!$A$1:$I$646,4,0),"") -> 352900505000001 | AH91: =IFERROR(VLOOKUP(B91,'Regiões Administrativas'!$A$1:$I$646,5,0),"") -> 3529005 | AI91: =IFERROR(VLOOKUP(B91,'Regiões Administrativas'!$A$1:$I$646,6,0),"") -> -49.951646 | AJ91: =IFERROR(VLOOKUP(B91,'Regiões Administrativas'!$A$1:$I$646,8,0),"") -> 657.30619 | AK91: =IFERROR(VLOOKUP(Form_Responses[[#This Row],[Município]],'Regiões Administrativas'!$A$1:$I$646,9,0),"") -> 1J6RQZYeWgj>
A92: 46009.382 | B92: MARÍLIA | C92: Alto Cafezal | D92: Rota das Capelas Alto Cafezal | E92: O evento na Rota das Capelas Alto Cafezal é um evento de cicloturismo, que reúne ciclistas de Marília e região. Com 100 quilômetros de extensão e 1.800 metros de altimetria, a Rota das Capelas é um percurso ecumênico e turístico que conecta fé, natureza e história. Ao longo do trajeto, os participantes passam por oito edificações religiosas — uma catedral, um mosteiro, uma igreja, quatro capelas e uma gruta — em um percurso que também resgata parte da história da região, ao seguir trechos da primeira estrada aberta durante o desbravamento da expedição geográfica de Campos Novos Paulista. O circuito tem início no centro de Marília, na Praça da Catedral Basílica de São Bento, seguindo pela zona sul da cidade e deixando o perímetro urbano pela Avenida Durval de Menezes, até a ponte sobre o Rio do Peixe, em direção a Ocauçu. Já na cidade vizinha, o trajeto contempla paisagens naturais de grande beleza, como a formação rochosa conhecida como Dedo de Deus e a Gruta de Nossa Senhora Auxiliadora, com a imagem da santa incrustada em um paredão de pedra. O percurso segue ainda pelos distritos de Nova Colômbia e São Benedito (Ocauçu), por Amadeu Amaral e finaliza em Avencas, no Mosteiro da Divina Misericórdia, encerrando uma jornada de fé, superação e conexão com a natureza. Mais do que um pedal, o evento é uma experiência transformadora, que une esporte, espiritualidade e turismo sustentável. O trajeto, de nível de dificuldade alto, é amplamente elogiado pela beleza de suas paisagens, sinalização de qualidade e estrutura de apoio. Durante o evento, há pontos de hidratação, suporte mecânico e ambulância de prontidão para garantir a segurança dos participantes. O evento é realizado uma vez por ano, pela Associação Rota das Capelas Alto Cafezal e apoio da Prefeitura Municipal de Marília, através da Secretaria do Trabalho, Turismo e Desenvolvimento Econômico. Porém, durante todo o ano é frequentada por ciclistas e peregrino, sendo a rota autoguiada. | G92: Rota das Capelas Alto Cafezal | H92: https://www.instagram.com/rotadascapelas.altocafezal/ | I92: Setembro | J92: 46271 | K92: 46271 | L92: 0.25 | M92: 0.54166667 | N92: Campeonato/Torneio/Concurso | O92: Esportivo | P92: Nenhuma das opções acima | Q92: Nehuma das opções acima | R92: Regional | S92: 700 | T92: 500 | U92: 500 | V92: 400 | W92: Associação Rota das Capelas Alto Cafezal e apoio da Prefeitura Municipal de Marília, através da Secretaria do Trabalho, Turismo e Desenvolvimento Econômico | X92: https://www.instagram.com/rotadascapelas.altocafezal/ | Y92: https://www.instagram.com/rotadascapelas.altocafezal/ | Z92: Não possui | AA92: Não possui | AB92: Não possui | AC92: Livre | AD92: =IFERROR(VLOOKUP(B92,'Regiões Administrativas'!$A$1:$B$646,2,0),"") -> Marília | AE92: =IFERROR(VLOOKUP(Form_Responses[[#This Row],[Município]],'Regiões Administrativas'!$A$1:$I$646,3,0),"") -> 16464 | AF92: =IFERROR(VLOOKUP(Form_Responses[[#This Row],[Município]],'Regiões Administrativas'!$A$1:$I$646,4,0),"") -> 352900505000001 | AG92: =IFERROR(VLOOKUP(Form_Responses[[#This Row],[Município]],'Regiões Administrativas'!$A$1:$I$646,4,0),"") -> 352900505000001 | AH92: =IFERROR(VLOOKUP(B92,'Regiões Administrativas'!$A$1:$I$646,5,0),"") -> 3529005 | AI92: =IFERROR(VLOOKUP(B92,'Regiões Administrativas'!$A$1:$I$646,6,0),"") -> -49.951646 | AJ92: =IFERROR(VLOOKUP(B92,'Regiões Administrativas'!$A$1:$I$646,8,0),"") -> 657.30619 | AK92: =IFERROR(VLOOKUP(Form_Responses[[#This Row],[Município]],'Regiões Administrativas'!$A$1:$I$646,9,0),"") -> 1J6RQZYeWgj>
A93: 46009.404 | B93: SÃO SIMÃO | C93: Alta Mogiana | D93: FESICA - Festival Simonense da Canção | E93: O FESICA – Festival Simonense da Canção teve início em 1973, idealizado por um grupo de jovens simonenses da Juventude Unida Simonense (JUS). Começando de forma simples, o festival rapidamente ganhou projeção e alcançou dimensão nacional, consolidando-se como um dos mais importantes eventos culturais da cidade. A primeira edição foi realizada no Cine-Theatro Carlos Gomes. Já no terceiro ano, devido ao grande sucesso de público, o festival passou a acontecer no Cine Oásis, espaço mais amplo, onde permaneceu até 1988 — período considerado o auge do FESICA, marcado por dias de glória e pela passagem de artistas que mais tarde se consagraram na música brasileira. Entre os destaques estão André de Souza e Neusa Mahlow, representantes de São Simão. Entre 1989 e 1996, o festival foi realizado no Ginásio de Esportes Amadeu Geraigire. Em 1997, ocorreu uma edição comemorativa pelos 25 anos do FESICA, sem caráter competitivo. No ano seguinte, 1998, o festival foi realizado pela última vez naquele ciclo. Após um longo período de pausa, o FESICA foi retomado em 2022 pela Prefeitura Municipal de São Simão, com edições realizadas nos dias 07, 08 e 09 de julho, reunindo artistas de diversas regiões do Brasil. O festival teve continuidade em 2023 e 2024 e, em 2025, celebrou 30 anos de Voos e Vozes, apresentando nova roupagem e identidade visual, batendo recordes de inscrições, recebendo artistas de norte a sul do país e sendo amplamente aclamado pelo público e pela região, reafirmando sua relevância cultural e artística. | F93: - | G93: Praça da República - Centro - São Simão | H93: https://www.instagram.com/fesica_ss/ https://linktr.ee/FESICA2025?utm_source=linktree_profile_share&ltsid=73d2714a-8749-42df-ad81-584f6339e467 | I93: Julho | J93: 46220 | K93: 46222 | L93: 0.79166667 | M93: 0 | N93: Festival | O93: Artístico/Cultural/Folclórico | P93: Nenhuma das opções acima | Q93: Nehuma das opções acima | R93: Nacional | S93: 15000 | T93: 12000 | U93: 10000 | V93: 10000 | W93: Secretaria Municipal de Turismo e Desenvolvimento Ecônomico / Secretaria Municipal de Cultura / Prefeitura de São Simão | X93: - | Y93: turismo@saosimao.sp.gov.br | Z93: Deficiência Fisica, Deficiência Visual, Deficiência Auditiva, Deficiência Intelectual | AA93: Piso Tátil, Rampa, Banheiro Acessível, Balcão de atendimento com altura reduzida, Portas Largas para PCR (Pessoa com cadeira de rodas) | AB93: Legenda no site do evento | AC93: Livre | AD93: =IFERROR(VLOOKUP(B93,'Regiões Administrativas'!$A$1:$B$646,2,0),"") -> Ribeirão Preto | AE93: =IFERROR(VLOOKUP(Form_Responses[[#This Row],[Município]],'Regiões Administrativas'!$A$1:$I$646,3,0),"") -> 17291 | AF93: =IFERROR(VLOOKUP(Form_Responses[[#This Row],[Município]],'Regiões Administrativas'!$A$1:$I$646,4,0),"") -> 355090205000001 | AG93: =IFERROR(VLOOKUP(Form_Responses[[#This Row],[Município]],'Regiões Administrativas'!$A$1:$I$646,4,0),"") -> 355090205000001 | AH93: =IFERROR(VLOOKUP(B93,'Regiões Administrativas'!$A$1:$I$646,5,0),"") -> 3550902 | AI93: =IFERROR(VLOOKUP(B93,'Regiões Administrativas'!$A$1:$I$646,6,0),"") -> -47.553353 | AJ93: =IFERROR(VLOOKUP(B93,'Regiões Administrativas'!$A$1:$I$646,8,0),"") -> 629.97666 | AK93: =IFERROR(VLOOKUP(Form_Responses[[#This Row],[Município]],'Regiões Administrativas'!$A$1:$I$646,9,0),"") -> 1J6t^Y6?+89>
A94: 46009.414 | B94: SÃO SIMÃO | C94: Alta Mogiana | D94: Carnaval Simonense | E94: O tradicional Carnaval de Rua de São Simão, renovado, cheio de energia e mantendo viva uma das maiores expressões culturais da cidade. A cada edição, a festa cresce, se fortalece e reafirma seu lugar como um dos principais carnavais da região. Com uma programação diversa e democrática, o Carnaval de São Simão reúne famílias, amigos e turistas em um ambiente de alegria, cores e muita música. São noites intensas de festa e matinês pensadas para todas as idades, além de concursos entre repúblicas, desfiles carnavalescos, blocos, shows artísticos e a já tradicional caça ao tesouro, que movimenta a cidade e encanta gerações. Mais do que uma festa, o carnaval simonense é um encontro de histórias, culturas e pessoas, fortalecendo o turismo, a economia local e o sentimento de pertencimento. Um carnaval gratuito, popular, seguro e feito para todos — onde a tradição se renova e a alegria toma conta das ruas. | F94: - | G94: Rodoviária e Praça da República de São Simão | H94: https://www.instagram.com/carnavalsimonense/ Estamos criando redes sociais do Carnaval | I94: Fevereiro | J94: 46066 | K94: 46070 | L94: 0.83333333 | M94: 0.125 | N94: Festa | O94: Artístico/Cultural/Folclórico | P94: Carnaval | Q94: Nehuma das opções acima | R94: Nacional | S94: 20000 | T94: 18000 | U94: 12000 | V94: 12000 | W94: Secretaria de Turismo e Desenvolvimento Ecônomico / Secretaria de Cultura / Prefeitura Municipal de São Simão | X94: - | Y94: turismo@saosimao.sp.gov.br | Z94: Deficiência Fisica, Deficiência Visual, Deficiência Auditiva, Deficiência Intelectual | AA94: Mapa Tátil, Piso Tátil, Rampa, Banheiro Acessível, Balcão de atendimento com altura reduzida, Portas Largas para PCR (Pessoa com cadeira de rodas) | AB94: Áudio Descrição no site do evento, Legenda no site do evento | AC94: Livre | AD94: =IFERROR(VLOOKUP(B94,'Regiões Administrativas'!$A$1:$B$646,2,0),"") -> Ribeirão Preto | AE94: =IFERROR(VLOOKUP(Form_Responses[[#This Row],[Município]],'Regiões Administrativas'!$A$1:$I$646,3,0),"") -> 17291 | AF94: =IFERROR(VLOOKUP(Form_Responses[[#This Row],[Município]],'Regiões Administrativas'!$A$1:$I$646,4,0),"") -> 355090205000001 | AG94: =IFERROR(VLOOKUP(Form_Responses[[#This Row],[Município]],'Regiões Administrativas'!$A$1:$I$646,4,0),"") -> 355090205000001 | AH94: =IFERROR(VLOOKUP(B94,'Regiões Administrativas'!$A$1:$I$646,5,0),"") -> 3550902 | AI94: =IFERROR(VLOOKUP(B94,'Regiões Administrativas'!$A$1:$I$646,6,0),"") -> -47.553353 | AJ94: =IFERROR(VLOOKUP(B94,'Regiões Administrativas'!$A$1:$I$646,8,0),"") -> 629.97666 | AK94: =IFERROR(VLOOKUP(Form_Responses[[#This Row],[Município]],'Regiões Administrativas'!$A$1:$I$646,9,0),"") -> 1J6t^Y6?+89>
A95: 46009.417 | B95: PARIQUERA-AÇU | C95: Lagamar | D95: 17ª Festa das Nações | E95: A Festa das Nações de Pariquera-Açu foi criada com o objetivo de valorizar as etnias que marcaram a colonização do município, destacando as culturas alemã, polonesa, suíça, italiana e portuguesa, que juntas formam uma grande riqueza cultural. Mais do que um evento festivo, a Festa das Nações celebra a identidade do município, promove o encontro de culturas e fortalece o sentimento de pertencimento da comunidade. Em 2026, o evento chega à sua décima sétima edição, já consolidado como um dos principais acontecimentos culturais da região, sendo realizado ao longo de 4 dias de programação, e tendo ultrapassado, nas últimas edições, a marca de 20 mil visitantes, reafirmando sua importância cultural, turística e social para Pariquera-Açu. | G95: Centro de eventos dos Imigrantes, Av. Olímpica, S/N. Pariquera-Açu, CEP 11930-000 | H95: https://www.instagram.com/festadasnacoespariquera?igsh=MXdkbWxjbHFwdDY1Yw== | I95: Junho | J95: 46177 | K95: 46180 | L95: 0.79166667 | N95: Festa | O95: Artístico/Cultural/Folclórico | P95: Social/Cívico/Histórico | Q95: Cultura Alemã | R95: Nacional | S95: 25000 | T95: 20000 | U95: 18000 | V95: 15000 | W95: Prefeitura Municipal de Pariquera Açu | X95: gratuito | Y95: turismo@pariqueraacu.sp.gov.br | Z95: Deficiência Fisica, Deficiência Auditiva | AA95: Atendimento em Línguas de Sinais, Banheiro Acessível, Portas Largas para PCR (Pessoa com cadeira de rodas) | AB95: Não possui | AC95: Livre | AD95: =IFERROR(VLOOKUP(B95,'Regiões Administrativas'!$A$1:$B$646,2,0),"") -> Registro | AE95: =IFERROR(VLOOKUP(Form_Responses[[#This Row],[Município]],'Regiões Administrativas'!$A$1:$I$646,3,0),"") -> 16744 | AF95: =IFERROR(VLOOKUP(Form_Responses[[#This Row],[Município]],'Regiões Administrativas'!$A$1:$I$646,4,0),"") -> 353620805000001 | AG95: =IFERROR(VLOOKUP(Form_Responses[[#This Row],[Município]],'Regiões Administrativas'!$A$1:$I$646,4,0),"") -> 353620805000001 | AH95: =IFERROR(VLOOKUP(B95,'Regiões Administrativas'!$A$1:$I$646,5,0),"") -> 3536208 | AI95: =IFERROR(VLOOKUP(B95,'Regiões Administrativas'!$A$1:$I$646,6,0),"") -> -47.879998 | AJ95: =IFERROR(VLOOKUP(B95,'Regiões Administrativas'!$A$1:$I$646,8,0),"") -> 32.946368 | AK95: =IFERROR(VLOOKUP(Form_Responses[[#This Row],[Município]],'Regiões Administrativas'!$A$1:$I$646,9,0),"") -> 1J6U,?;Q\T]p
A96: 46009.431 | B96: PARIQUERA-AÇU | C96: Lagamar | D96: FEI BANANA (14ª Feira Nacional da Bananicultura) | E96: A FEIBANANA – Feira Nacional da Bananicultura é um dos principais eventos do país voltados à cadeia produtiva da banana. Realizada em Pariquera-Açu, a feira reúne produtores, pesquisadores, empresas e o público em geral para apresentar inovações tecnológicas, compartilhar conhecimento por meio de palestras especializadas e valorizar a cultura local, com artesanato, atrações culturais e shows. Consolidada como um grande ponto de encontro do setor, a FEIBANANA promove o desenvolvimento da bananicultura e atrai milhares de visitantes a cada edição. | G96: Centro de Eventos dos Imigrantes, Av. Olímpica, S/N. Pariquera-Açu. CEP 11930-000. | I96: Maio | J96: 46154 | K96: 46187 | N96: Feira/Exposição/Mostra | O96: Comercial/Promocional | P96: Agropecuária | Q96: Nehuma das opções acima | R96: Internacional | S96: 15000 | W96: ABAVAR - Associação dos Bananicultores do Vale do Ribeira | Y96: turismo@pariqueraacu.sp.gov.br | Z96: Deficiência Fisica | AA96: Banheiro Acessível | AB96: Não possui | AC96: Livre | AD96: =IFERROR(VLOOKUP(B96,'Regiões Administrativas'!$A$1:$B$646,2,0),"") -> Registro | AE96: =IFERROR(VLOOKUP(Form_Responses[[#This Row],[Município]],'Regiões Administrativas'!$A$1:$I$646,3,0),"") -> 16744 | AF96: =IFERROR(VLOOKUP(Form_Responses[[#This Row],[Município]],'Regiões Administrativas'!$A$1:$I$646,4,0),"") -> 353620805000001 | AG96: =IFERROR(VLOOKUP(Form_Responses[[#This Row],[Município]],'Regiões Administrativas'!$A$1:$I$646,4,0),"") -> 353620805000001 | AH96: =IFERROR(VLOOKUP(B96,'Regiões Administrativas'!$A$1:$I$646,5,0),"") -> 3536208 | AI96: =IFERROR(VLOOKUP(B96,'Regiões Administrativas'!$A$1:$I$646,6,0),"") -> -47.879998 | AJ96: =IFERROR(VLOOKUP(B96,'Regiões Administrativas'!$A$1:$I$646,8,0),"") -> 32.946368 | AK96: =IFERROR(VLOOKUP(Form_Responses[[#This Row],[Município]],'Regiões Administrativas'!$A$1:$I$646,9,0),"") -> 1J6U,?;Q\T]p
A97: 46009.437 | B97: VOTUPORANGA | C97: Maravilhas do Rio Grande | D97: CIENP - Congresso Internacional de Educação do Noroeste Paulista | E97: O CIENP é um evento formativo de grande impacto para o Noroeste Paulista, promovido pelo Arranjo de Desenvolvimento da Educação do Noroeste Paulista (ADE Noroeste Paulista), em parceria com a AMA. O congresso simboliza o compromisso coletivo com a educação e representa, na prática, o regime de colaboração horizontal entre os municípios do Noroeste Paulista. Em 2025, o CIENP celebrou sua 10ª edição, marcando uma década de formação continuada para professores, dirigentes e demais profissionais da educação, consolidando-se como um marco regional no fortalecimento da aprendizagem e da gestão educacional. | G97: Centro de Eventos “Helder Henrique Galera” - Angelo Comar - Rod. Vicinal, VTG 020 | H97: https://cienp.com.br | I97: Julho | J97: 46227 | K97: 46228 | L97: 0.33333333 | M97: 0.75 | N97: Congresso e afins | O97: Científico/Técnico | P97: Nenhuma das opções acima | Q97: Nehuma das opções acima | R97: Internacional | S97: 5000 | T97: 3000 | U97: 3000 | V97: 3000 | W97: Arranjo de Desenvolvimento da Educação do Noroeste Paulista (ADE Noroeste Paulista), em parceria com a Associação dos Municípios da Araraquarense (AMA) e a Prefeitura Municipal de Votuporanga | Y97: cultura@votuporanga.sp.gov.br | Z97: Deficiência Fisica, Deficiência Visual, Deficiência Auditiva, Deficiência Intelectual | AA97: Piso Tátil, Rampa, Banheiro Acessível, Portas Largas para PCR (Pessoa com cadeira de rodas) | AB97: Não possui | AC97: Indicado para maiores de 18 anos | AD97: =IFERROR(VLOOKUP(B97,'Regiões Administrativas'!$A$1:$B$646,2,0),"") -> São José do Rio Preto | AE97: =IFERROR(VLOOKUP(Form_Responses[[#This Row],[Município]],'Regiões Administrativas'!$A$1:$I$646,3,0),"") -> 17450 | AF97: =IFERROR(VLOOKUP(Form_Responses[[#This Row],[Município]],'Regiões Administrativas'!$A$1:$I$646,4,0),"") -> 355710505000001 | AG97: =IFERROR(VLOOKUP(Form_Responses[[#This Row],[Município]],'Regiões Administrativas'!$A$1:$I$646,4,0),"") -> 355710505000001 | AH97: =IFERROR(VLOOKUP(B97,'Regiões Administrativas'!$A$1:$I$646,5,0),"") -> 3557105 | AI97: =IFERROR(VLOOKUP(B97,'Regiões Administrativas'!$A$1:$I$646,6,0),"") -> -49.974672 | AJ97: =IFERROR(VLOOKUP(B97,'Regiões Administrativas'!$A$1:$I$646,8,0),"") -> 518.33459 | AK97: =IFERROR(VLOOKUP(Form_Responses[[#This Row],[Município]],'Regiões Administrativas'!$A$1:$I$646,9,0),"") -> 1J6R3Zw@HH+p
A98: 46009.453 | B98: ITATIBA | C98: Circuito das Frutas | D98: 21ª Festa do Caqui e Cia. | E98: A Festa do Caqui e Cia. é o maior evento turístico de Itatiba e tem como objetivo valorizar o agroturismo e a produção local. É realizada sempre em meados de Abril, no Parque Luis Latorre (Parque da Juventude), e, além de divulgar a fruta com especial destaque para o agronegócio, proporciona também diversas outras atrações que agradam os visitantes: passeios turísticos às propriedades rurais, aulas de culinária que têm o caqui como matéria-prima principal, praça de alimentação, exposição de frutas premiadas e leilão, produtores rurais, artesanato, espaço turismo, cidade das crianças, espaço de convivência etc. O evento busca valorizar a cultura local com apresentações de artistas e bandas da cidade e região. A festa tem caráter filantrópico, pois a praça de alimentação é composta pelas entidades assistenciais da cidade que angariam fundos para seus trabalhos sociais. Os produtores rurais comercializam frutas in natura, produtos orgânicos, sucos, vinhos, geleias, doces e compotas, dentre outros, e são enaltecidos pelo público que prestigia a Festa do Caqui e Cia. | G98: Parque Luis Latorre (Parque da Juventude)- Avenida Prefeito Erasmo Chrispim, 100, no Bairro do Engenho, Itatiba | H98: https://itatiba.sp.gov.br/ | I98: Abril | J98: 46122 | K98: 46131 | N98: Festa | O98: Artístico/Cultural/Folclórico | P98: Nenhuma das opções acima | Q98: Nehuma das opções acima | R98: Nacional | S98: 130000 | T98: 100000 | U98: 125000 | V98: 130000 | W98: Prefeitura do Município de Itatiba | Y98: turismo@cultura.itatiba.sp.gov.br | Z98: Deficiência Fisica | AA98: Banheiro Acessível | AB98: Não possui | AC98: Livre | AD98: =IFERROR(VLOOKUP(B98,'Regiões Administrativas'!$A$1:$B$646,2,0),"") -> Campinas | AE98: =IFERROR(VLOOKUP(Form_Responses[[#This Row],[Município]],'Regiões Administrativas'!$A$1:$I$646,3,0),"") -> 16138 | AF98: =IFERROR(VLOOKUP(Form_Responses[[#This Row],[Município]],'Regiões Administrativas'!$A$1:$I$646,4,0),"") -> 352340405000001 | AG98: =IFERROR(VLOOKUP(Form_Responses[[#This Row],[Município]],'Regiões Administrativas'!$A$1:$I$646,4,0),"") -> 352340405000001 | AH98: =IFERROR(VLOOKUP(B98,'Regiões Administrativas'!$A$1:$I$646,5,0),"") -> 3523404 | AI98: =IFERROR(VLOOKUP(B98,'Regiões Administrativas'!$A$1:$I$646,6,0),"") -> -46.837558 | AJ98: =IFERROR(VLOOKUP(B98,'Regiões Administrativas'!$A$1:$I$646,8,0),"") -> 766.77427 | AK98: =IFERROR(VLOOKUP(Form_Responses[[#This Row],[Município]],'Regiões Administrativas'!$A$1:$I$646,9,0),"") -> 1J6tn\{r;71f
A99: 46009.479 | B99: VOTUPORANGA | C99: Maravilhas do Rio Grande | D99: 27ª Exposição de Orquídeas | E99: A Exposição Nacional de Orquídeas de Votuporanga é um evento tradicional do município que reúne expositores e orquidófilos de diversas regiões do país, apresentando ao público centenas de espécies e variedades de orquídeas. Organizada pela Associação Votuporanguense de Orquidófilos (AVORQ), com apoio do poder público, a exposição combina contemplação, troca de conhecimentos e valorização ambiental, contando com julgamento técnico das plantas, orientações sobre cultivo e venda de mudas. Além do caráter técnico e educativo, o evento também se consolida como uma atração cultural e turística, integrando atividades culturais, artesanato e lazer, com entrada gratuita e ampla participação da comunidade. | G99: Parque da Cultura - Rua Francisco Ramalho de Mendonça, 3112, Jardim Alvorada - Votuporanga/SP | I99: Setembro | J99: 46284 | K99: 46286 | L99: 0.33333333 | M99: 0.91666667 | N99: Feira/Exposição/Mostra | O99: Artístico/Cultural/Folclórico | P99: Nenhuma das opções acima | Q99: Nehuma das opções acima | R99: Nacional | S99: 5000 | T99: 4000 | U99: 3000 | V99: 3000 | W99: Associação Votuporanguense dos Orquidófilos com apoio da Prefeitura Municipal de Votuporanga | X99: Gratuito | Y99: cultura@votuporanga.sp.gov.br | Z99: Deficiência Fisica, Deficiência Visual, Deficiência Auditiva, Deficiência Intelectual | AA99: Piso Tátil, Rampa, Elevador, Banheiro Acessível, Portas Largas para PCR (Pessoa com cadeira de rodas) | AB99: Não possui | AC99: Livre | AD99: =IFERROR(VLOOKUP(B99,'Regiões Administrativas'!$A$1:$B$646,2,0),"") -> São José do Rio Preto | AE99: =IFERROR(VLOOKUP(Form_Responses[[#This Row],[Município]],'Regiões Administrativas'!$A$1:$I$646,3,0),"") -> 17450 | AF99: =IFERROR(VLOOKUP(Form_Responses[[#This Row],[Município]],'Regiões Administrativas'!$A$1:$I$646,4,0),"") -> 355710505000001 | AG99: =IFERROR(VLOOKUP(Form_Responses[[#This Row],[Município]],'Regiões Administrativas'!$A$1:$I$646,4,0),"") -> 355710505000001 | AH99: =IFERROR(VLOOKUP(B99,'Regiões Administrativas'!$A$1:$I$646,5,0),"") -> 3557105 | AI99: =IFERROR(VLOOKUP(B99,'Regiões Administrativas'!$A$1:$I$646,6,0),"") -> -49.974672 | AJ99: =IFERROR(VLOOKUP(B99,'Regiões Administrativas'!$A$1:$I$646,8,0),"") -> 518.33459 | AK99: =IFERROR(VLOOKUP(Form_Responses[[#This Row],[Município]],'Regiões Administrativas'!$A$1:$I$646,9,0),"") -> 1J6R3Zw@HH+p
